Workbook

Sheet Hoja3
A1: EMPRESA | B1: ALGADI
A3: Etiquetas de fila | B3: Suma de COSTE TOTAL
A4: CORRETURNOS/RAPPELS | B4: -19437.937 | C4: =+VLOOKUP(A4,#REF!,2,) -> #REF!
A5: COL. VEDRUNA CARABANCHEL | B5: -15405.305 | C5: =+VLOOKUP(A5,#REF!,2,) -> #REF!
A6: COL. SAG. CORAZONES MARTIN HEROS | B6: -8125.2855 | C6: =+VLOOKUP(A6,#REF!,2,) -> #REF!
A7: COLEGIO NTRA SRA BUEN CONSEJO | B7: -7030.9953 | C7: =+VLOOKUP(A7,#REF!,2,) -> #REF!
A8: COLEGIO JESUS MAESTRO | B8: -5853.1845 | C8: =+VLOOKUP(A8,#REF!,2,) -> #REF!
A9: COLEGIO AGUSTINIANO | B9: -5026.6597 | C9: =+VLOOKUP(A9,#REF!,2,) -> #REF!
A10: COLEGIO MAYOR ALCALA | B10: -4959.0878 | C10: =+VLOOKUP(A10,#REF!,2,) -> #REF!
A11: COL. SAN AGUSTIN -LOS NEGRALES | B11: -4523.8566 | C11: =+VLOOKUP(A11,#REF!,2,) -> #REF!
A12: COL. SAGRADA. FAMILIA-PINTO | B12: -4443.2338 | C12: =+VLOOKUP(A12,#REF!,2,) -> #REF!
A13: CLARETIANOS COLMENAR SEMINARIO | B13: -3866.7947 | C13: =+VLOOKUP(A13,#REF!,2,) -> #REF!
A14: COLEGIO SAGRADA FAMILIA | B14: -3145.688 | C14: =+VLOOKUP(A14,#REF!,2,) -> #REF!
A15: C.M.U. SAN AGUSTIN | B15: -2968.875 | C15: =+VLOOKUP(A15,#REF!,2,) -> #REF!
... A93: Total general | B93: -144389.17 | C93: =+VLOOKUP(A93,#REF!,2,) -> #REF!

Sheet Hoja4
A1: EMPRESA | B1: ALGADI
A3: Etiquetas de fila | B3: Suma de COSTE TOTAL
A4: ACADE | B4: 826.97667 | C4: =+VLOOKUP(A4,#REF!,2,) -> #REF!
A5: BELIVE RESIDENCIA SAGRADO CORAZON | B5: 139.70172 | C5: =+VLOOKUP(A5,#REF!,2,) -> #REF!
A6: BREWSTER MADRID | B6: 1405.9478 | C6: =+VLOOKUP(A6,#REF!,2,) -> #REF!
A7: BREWSTER MADRID CAMPUS LA MORALEJA | B7: 188.6885
A8: C. IRLANDESAS CASTILLEJA | B8: 1413.1845 | C8: =+VLOOKUP(A8,#REF!,2,) -> #REF!
A9: C.M.STA.MARIA DEL PINO | B9: 1098.4837 | C9: =+VLOOKUP(A9,#REF!,2,) -> #REF!
A10: C.M.U. JAIME DEL AMO | B10: 8252.116 | C10: =+VLOOKUP(A10,#REF!,2,) -> #REF!
A11: C.M.U. SAN AGUSTIN | B11: 2660.7735 | C11: =+VLOOKUP(A11,#REF!,2,) -> #REF!
A12: C.P. CONCEPCIONISTAS - BELISANA | B12: 422.24 | C12: =+VLOOKUP(A12,#REF!,2,) -> #REF!
A13: C.P. PP. AGUSTINOS "PROV. S. JUAN SAHAGUN" | B13: 3041.8829 | C13: =+VLOOKUP(A13,#REF!,2,) -> #REF!
A14: C.P. PP. REPARADORES - BALBINA VALVERDE | B14: 1363.419 | C14: =+VLOOKUP(A14,#REF!,2,) -> #REF!
A15: C.P. TERCIARIOS CAPUCHINOS | B15: 72.5725 | C15: =+VLOOKUP(A15,#REF!,2,) -> #REF!
A16: C.STA TERESA DE JESÚS EL VEDAT | B16: 513.94525 | C16: =+VLOOKUP(A16,#REF!,2,) -> #REF!
A17: C.VIRGEN DEL CARMEN | B17: 2077.4838 | C17: =+VLOOKUP(A17,#REF!,2,) -> #REF!
A18: CASA DE EJERCICIOS SAN JOSE | B18: 392.32622 | C18: =+VLOOKUP(A18,#REF!,2,) -> #REF!
A19: CASA GENERAL MM. CONCEPCIONISTAS | B19: 105.56 | C19: =+VLOOKUP(A19,#REF!,2,) -> #REF!
... A54: COLEGIO JESUS MAESTRO | B54: 225.6345 | C54: =+VLOOKUP(A54,#REF!,2,) -> #REF!
A55: COLEGIO LUX MUNDI | B55: 769.2685
A56: COLEGIO MAYOR ALCALA | B56: 3440.192 | C56: =+VLOOKUP(A56,#REF!,2,) -> #REF!
A57: COLEGIO MAYOR CESAR CARLOS | B57: 5982.1384 | C57: =+VLOOKUP(A57,#REF!,2,) -> #REF!
A58: COLEGIO MM. CONCEPCIONISTAS BURGOS | B58: 430.81675 | C58: =+VLOOKUP(A58,#REF!,2,) -> #REF!
A59: COLEGIO N. S. DE LA PAZ - CANTABRIA | B59: 79.17 | C59: =+VLOOKUP(A59,#REF!,2,) -> #REF!
A60: COLEGIO NTRA SRA BUEN CONSEJO | B60: 4338.2521 | C60: =+VLOOKUP(A60,#REF!,2,) -> #REF!
A61: COLEGIO PADRE DEHON | B61: 413.66325 | C61: =+VLOOKUP(A61,#REF!,2,) -> #REF!
A62: COLEGIO RAFAELA YBARRA | B62: 1231.755 | C62: =+VLOOKUP(A62,#REF!,2,) -> #REF!
A63: COLEGIO RAIMUNDO LULIO | B63: 292.929 | C63: =+VLOOKUP(A63,#REF!,2,) -> #REF!
A64: COLEGIO SAGRADA FAMILIA | B64: 4683.974 | C64: =+VLOOKUP(A64,#REF!,2,) -> #REF!
A65: COLEGIO SAN HERMENEGILDO | B65: 587.83725 | C65: =+VLOOKUP(A65,#REF!,2,) -> #REF!
A66: COLEGIO SANTA RITA | B66: 941.14832 | C66: =+VLOOKUP(A66,#REF!,2,) -> #REF!
A67: COLEGIO TERESIANAS GANDUXER | B67: 1774.7803 | C67: =+VLOOKUP(A67,#REF!,2,) -> #REF!
... A96: VEMARE, S.L | B96: 1419.45 | C96: =+VLOOKUP(A96,#REF!,2,) -> #REF!
A97: Total general | B97: 144002.11 | C97: =+SUM(C4:C96) -> #REF! | D97: =+GETPIVOTDATA("COSTE TOTAL",$A$3)-C97 -> #REF!

Sheet Hoja5
A1: EMPRESA | B1: ALGADI
A3: Etiquetas de fila | B3: Suma de COSTE TOTAL
A4: ACADE | B4: 826.97667 | C4: =+VLOOKUP(A4,[1]Hoja1!$A$4:$B$97,2,) -> 826.97667 | D4: =+B4-C4 -> 0
A5: BELIVE RESIDENCIA SAGRADO CORAZON | B5: 139.70172 | C5: =+VLOOKUP(A5,[1]Hoja1!$A$4:$B$97,2,) -> 139.70172 | D5: =+B5-C5 -> 0
A6: BREWSTER MADRID | B6: 1405.9478 | C6: =+VLOOKUP(A6,[1]Hoja1!$A$4:$B$97,2,) -> 1405.9478 | D6: =+B6-C6 -> 0
A7: BREWSTER MADRID CAMPUS LA MORALEJA | B7: 188.6885 | C7: =+VLOOKUP(A7,[1]Hoja1!$A$4:$B$97,2,) -> 188.6885 | D7: =+B7-C7 -> 0
A8: C. IRLANDESAS CASTILLEJA | B8: 1413.1845 | C8: =+VLOOKUP(A8,[1]Hoja1!$A$4:$B$97,2,) -> 1413.1845 | D8: =+B8-C8 -> 0
A9: C.M.STA.MARIA DEL PINO | B9: 1098.4837 | C9: =+VLOOKUP(A9,[1]Hoja1!$A$4:$B$97,2,) -> 1098.4837 | D9: =+B9-C9 -> 0
A10: C.M.U. JAIME DEL AMO | B10: 8252.116 | C10: =+VLOOKUP(A10,[1]Hoja1!$A$4:$B$97,2,) -> 8252.116 | D10: =+B10-C10 -> 0
A11: C.M.U. SAN AGUSTIN | B11: 2660.7735 | C11: =+VLOOKUP(A11,[1]Hoja1!$A$4:$B$97,2,) -> 2660.7735 | D11: =+B11-C11 -> 0
A12: C.P. CONCEPCIONISTAS - BELISANA | B12: 422.24 | C12: =+VLOOKUP(A12,[1]Hoja1!$A$4:$B$97,2,) -> 422.24 | D12: =+B12-C12 -> 0
A13: C.P. PP. AGUSTINOS "PROV. S. JUAN SAHAGUN" | B13: 3041.8829 | C13: =+VLOOKUP(A13,[1]Hoja1!$A$4:$B$97,2,) -> 3041.8829 | D13: =+B13-C13 -> 0
A14: C.P. PP. REPARADORES - BALBINA VALVERDE | B14: 1363.419 | C14: =+VLOOKUP(A14,[1]Hoja1!$A$4:$B$97,2,) -> 1363.419 | D14: =+B14-C14 -> 0
A15: C.P. TERCIARIOS CAPUCHINOS | B15: 72.5725 | C15: =+VLOOKUP(A15,[1]Hoja1!$A$4:$B$97,2,) -> 72.5725 | D15: =+B15-C15 -> 0
... A97: Total general | B97: 144002.11 | C97: =+VLOOKUP(A97,[1]Hoja1!$A$4:$B$97,2,) -> 143571.3 | D97: =+B97-C97 -> 430.81675

Sheet Incidencias
D1: Campos Obligatorios | M1: Campos automáticos | P1: Campos Obligatorios | X1: Campos automáticos | AA1: Campos Obligatorios | AC1: Campos automáticos
D2: No se pueden quedar estos campos en blanco | J2: DESTINO | P2: INCIDENCIA | S2: NOCTURNIDAD | V2: TRASLADO | AH2: Origen | AN2: Destino | AQ2: NOCTURNIDAD | BD2: ORIGEN | BV2: DESTINO
A3: Fecha envio | B3: Fecha baja | C3: Nº de días vacaciones a pagar | D3: Jefe de Operaciones | E3: Mes imputació nómina | F3: Facturable | G3: Servicio | H3: Motivo | I3: Trabajador | J3: Empresa Destino | K3: Código Crown Destino | L3: control | M3: Centro Destino | N3: CAMPO DE ATENCION | O3: Categoría | P3: Cuantia | Q3: Precio | R3: TOTAL | S3: Cuantía | T3: Precio | U3: TOTAL | V3: HORAS | W3: TOTAL COSTE | X3: Empresa Origen | Y3: Código Crown Origen | Z3: Centro Origen | AA3: Fecha | AB3: Observaciones | AD3: 70/71 - Festivos Total | AE3: 72 - IncentivosTotal | AF3: 73 - Plus sustitución Total | AG3: 74 - Plus nocturnidad Total | AH3: Número empresa Origen | AI3: Número empleado | AJ3: Sección | AK3: Coste Hora | AL3: Convenio | AM3: Categoria | AN3: EMPRESA | AO3: SECCION | AQ3: 99100165012016 | AR3: 28009435011996 | AS3: 99010825011997 | BD3: EMPRESA | BE3: TIPO NOMINA | BF3: MES | BG3: Centro | BH3: Centro preferente | BI3: Denom. Centro prefe | BJ3: Trabajador | BK3: Contrato | BL3: Categoría | BM3: Jornada | BN3: R | BO3: L | BP3: TOTAL | BQ3: dias | BR3: COSTE TOTAL | BV3: EMPRESA | BW3: TIPO NOMINA | BX3: MES | BY3: Centro | BZ3: Centro preferente | CA3: Denom. Centro prefe | CB3: Incidencia | CC3: Contrato | CD3: Categoría | CE3: Jornada | CF3: R | CG3: L | CH3: TOTAL | CI3: dias | CJ3: COSTE TOTAL
D4: 945 | E4: 9-SEPTIEMBRE | F4: NO | G4: 010 Restauración | H4: Permiso retribuido | I4: AGUIRRE NUÑEZ, ADELAIDA | J4: ALGADI | K4: 110021 | L4: =IF(W4>0,IF(OR(E4="",F4="",G4="",H4="",I4="",J4="",K4=""),"faltan datos","ok")," ") -> ok | M4: =IFERROR(VLOOKUP(K4,Centros!$E$2:$G$340,2,FALSE)," ") -> COLEGIO FUNDACION CALDEIRO | N4: =IF(J4=" "," ",IF(J4=X4," ","Emp Orig/dest. Distinta")) | O4: =IFERROR(VLOOKUP($I4,Trabajadores!$C$3:$AF$1684,19,FALSE)," ") -> Cociner@ | P4: 35.6 | Q4: 9 | R4: =+P4*Q4 -> 320.4 | T4: =IF(AL4="99100165012016",AQ4,IF(AL4="28009435011996",AR4,IF(AL4="99010825011997",AS4))) -> 1.7437656 | U4: =IF(T4="no corresponde",0,+S4*T4) -> 0 | W4: =+V4*AK4+((+R4+U4)*1.3195) -> 422.7678 | X4: =IFERROR(VLOOKUP($I4,Trabajadores!$C$2:$AS$1684,42,FALSE)," ") -> ALGADI | Y4: =IFERROR(VLOOKUP($I4,Trabajadores!$C$2:$AS$1684,40,FALSE)," ") -> 340084 | Z4: =IFERROR(VLOOKUP(Y4,Centros!$X$2:$Y$228,2,FALSE)," ") -> MISIONERAS CLARETIANAS J.HERNANDEZ | AA4: Septiembre´25 | AB4: Excedencia Johanna Villegas (limpieza Caldeiro) | AC4: =IFERROR(VLOOKUP(H4,Centros!$AI$2:$AN$10,6,FALSE),0) -> 72 | AD4: =IF(AC4=70,R4,0) -> 0 | AE4: =IF(AC4=72,R4,0) -> 320.4 | AF4: =IF(AC4=73,+R4,0) -> 0 | AG4: =+U4 -> 0 | AH4: =IFERROR(VLOOKUP($I4,Trabajadores!$C$3:$AT$1684,44,FALSE),0) -> 19228 | AI4: =IFERROR(VLOOKUP($I4,Trabajadores!$C$3:$AT$1684,2,FALSE),0) -> 1683 | AJ4: =IFERROR(VLOOKUP($I4,Trabajadores!$C$3:$AY$1270,21,FALSE),0) -> 70 | AK4: =IFERROR(VLOOKUP($I4,Trabajadores!$C$3:$AN$1684,38,FALSE),0) -> 5.79375 | AL4: =IFERROR(VLOOKUP($I4,Trabajadores!$C$3:$AN$1684,28,FALSE),0) -> 99100165012016 | AM4: =IFERROR(VLOOKUP($I4,Trabajadores!$C$3:$AN$1684,19,FALSE),0) -> Cociner@ | AN4: =IFERROR(IF($J4="algadi",VLOOKUP($K4,Centros!$AB$2:$AD$142,2,FALSE),VLOOKUP($K4,Centros!$AB$143:$AD$282,2,FALSE)),0) -> 19228 | AO4: =IFERROR(IF($J4="algadi",VLOOKUP($K4,Centros!$AB$2:$AD$142,3,FALSE),VLOOKUP($K4,Centros!$AB$143:$AD$222,3,FALSE)),0) -> 20 | AQ4: =IFERROR(VLOOKUP($AM4,Centros!$AR$2:$AS$405,2,FALSE),0) -> 1.7437656 | AR4: =IFERROR(VLOOKUP($AM4,Centros!$AZ$2:$BA$6,2,FALSE),0) -> 2.32225 | AS4: =IFERROR(VLOOKUP($AM4,Centros!$BE$2:$BF$6,2,FALSE),0) -> 0 | BD4: =+X4 -> ALGADI | BE4: INCIDENCIA | BF4: =+E4 -> 9-SEPTIEMBRE | BG4: =+Y4 -> 340084 | BH4: =VLOOKUP(Y4,Hoja1!$A$2:$O$599,14,FALSE) -> 340084 | BI4: =VLOOKUP(BH4,Hoja1!$A$2:$O$599,2,FALSE) -> MISIONERAS CLARETIANAS J.HERNANDEZ | BJ4: =+I4 -> AGUIRRE NUÑEZ, ADELAIDA | BK4: =VLOOKUP(BJ4,Trabajadores!$C$3:$AN$3285,14,FALSE) -> 100 | BL4: =VLOOKUP($BJ4,Trabajadores!$C$3:$AN$3285,19,FALSE) -> Cociner@ | BM4: =VLOOKUP($BJ4,Trabajadores!$C$3:$AN$3285,16,FALSE) -> 100 | BN4: =IF($G4="010 Restauración",100%,0%) -> 1 | BO4: =IF($G4="020 Limpieza",100%,0%) -> 0 | BP4: =+BN4+BO4 -> 1 | BR4: =-W4 -> -422.7678 | BV4: =+J4 -> ALGADI | BW4: INCIDENCIA | BX4: =+E4 -> 9-SEPTIEMBRE | BY4: =+K4 -> 110021 | BZ4: =VLOOKUP(BY4,Hoja1!$A$2:$O$599,14,FALSE) -> 110021 | CA4: =VLOOKUP(BZ4,Hoja1!$A$2:$O$599,2,FALSE) -> COLEGIO FUNDACION CALDEIRO | CB4: =+H4 -> Permiso retribuido | CC4: 888 | CD4: =+BW4 -> INCIDENCIA | CJ4: =+W4 -> 422.7678
D5: 945 | E5: 9-SEPTIEMBRE | F5: NO | G5: 010 Restauración | H5: Festivos y Fines de Semana | I5: ALONSO ALONSO, ANGEL LUIS | J5: ALGADI | K5: 510005 | L5: =IF(W5>0,IF(OR(E5="",F5="",G5="",H5="",I5="",J5="",K5=""),"faltan datos","ok")," ") -> ok | M5: =IFERROR(VLOOKUP(K5,Centros!$E$2:$G$340,2,FALSE)," ") -> C.P. TERCIARIOS CAPUCHINOS | N5: =IF(J5=" "," ",IF(J5=X5," ","Emp Orig/dest. Distinta")) | O5: =IFERROR(VLOOKUP($I5,Trabajadores!$C$3:$AF$1684,19,FALSE)," ") -> h Cociner@ | P5: 1 | Q5: 55 | R5: =+P5*Q5 -> 55 | T5: =IF(AL5="99100165012016",AQ5,IF(AL5="28009435011996",AR5,IF(AL5="99010825011997",AS5))) -> 1.7437656 | U5: =IF(T5="no corresponde",0,+S5*T5) -> 0 | W5: =+V5*AK5+((+R5+U5)*1.3195) -> 72.5725 | X5: =IFERROR(VLOOKUP($I5,Trabajadores!$C$2:$AS$1684,42,FALSE)," ") -> ALGADI | Y5: =IFERROR(VLOOKUP($I5,Trabajadores!$C$2:$AS$1684,40,FALSE)," ") -> 110216 | Z5: =IFERROR(VLOOKUP(Y5,Centros!$X$2:$Y$228,2,FALSE)," ") -> COL. MATER INMACULATA | AA5: 45913 | AB5: Sábado Belisana | AC5: =IFERROR(VLOOKUP(H5,Centros!$AI$2:$AN$10,6,FALSE),0) -> 70 | AD5: =IF(AC5=70,R5,0) -> 55 | AE5: =IF(AC5=72,R5,0) -> 0 | AF5: =IF(AC5=73,+R5,0) -> 0 | AG5: =+U5 -> 0 | AH5: =IFERROR(VLOOKUP($I5,Trabajadores!$C$3:$AT$1684,44,FALSE),0) -> 19228 | AI5: =IFERROR(VLOOKUP($I5,Trabajadores!$C$3:$AT$1684,2,FALSE),0) -> 1334 | AJ5: =IFERROR(VLOOKUP($I5,Trabajadores!$C$3:$AY$1270,21,FALSE),0) -> 107 | AK5: =IFERROR(VLOOKUP($I5,Trabajadores!$C$3:$AN$1684,38,FALSE),0) -> 11.40625 | AL5: =IFERROR(VLOOKUP($I5,Trabajadores!$C$3:$AN$1684,28,FALSE),0) -> 99100165012016 | AM5: =IFERROR(VLOOKUP($I5,Trabajadores!$C$3:$AN$1684,19,FALSE),0) -> h Cociner@ | AN5: =IFERROR(IF($J5="algadi",VLOOKUP($K5,Centros!$AB$2:$AD$142,2,FALSE),VLOOKUP($K5,Centros!$AB$143:$AD$282,2,FALSE)),0) -> 5027 | AO5: =IFERROR(IF($J5="algadi",VLOOKUP($K5,Centros!$AB$2:$AD$142,3,FALSE),VLOOKUP($K5,Centros!$AB$143:$AD$222,3,FALSE)),0) -> 51 | AQ5: =IFERROR(VLOOKUP($AM5,Centros!$AR$2:$AS$405,2,FALSE),0) -> 1.7437656 | AR5: =IFERROR(VLOOKUP($AM5,Centros!$AZ$2:$BA$6,2,FALSE),0) -> 0 | AS5: =IFERROR(VLOOKUP($AM5,Centros!$BE$2:$BF$6,2,FALSE),0) -> 0 | BD5: =+X5 -> ALGADI | BE5: INCIDENCIA | BF5: =+E5 -> 9-SEPTIEMBRE | BG5: =+Y5 -> 110216 | BH5: =VLOOKUP(Y5,Hoja1!$A$2:$O$599,14,FALSE) -> 110216 | BI5: =VLOOKUP(BH5,Hoja1!$A$2:$O$599,2,FALSE) -> COL. MATER INMACULATA | BJ5: =+I5 -> ALONSO ALONSO, ANGEL LUIS | BK5: =VLOOKUP(BJ5,Trabajadores!$C$3:$AN$3285,14,FALSE) -> 300 | BL5: =VLOOKUP($BJ5,Trabajadores!$C$3:$AN$3285,19,FALSE) -> h Cociner@ | BM5: =VLOOKUP($BJ5,Trabajadores!$C$3:$AN$3285,16,FALSE) -> 100 | BN5: =IF($G5="010 Restauración",100%,0%) -> 1 | BO5: =IF($G5="020 Limpieza",100%,0%) -> 0 | BP5: =+BN5+BO5 -> 1 | BR5: =-W5 -> -72.5725 | BV5: =+J5 -> ALGADI | BW5: INCIDENCIA | BX5: =+E5 -> 9-SEPTIEMBRE | BY5: =+K5 -> 510005 | BZ5: =VLOOKUP(BY5,Hoja1!$A$2:$O$599,14,FALSE) -> 510005 | CA5: =VLOOKUP(BZ5,Hoja1!$A$2:$O$599,2,FALSE) -> C.P. TERCIARIOS CAPUCHINOS | CB5: =+H5 -> Festivos y Fines de Semana | CC5: 888 | CD5: =+BW5 -> INCIDENCIA | CJ5: =+W5 -> 72.5725
D6: 945 | E6: 9-SEPTIEMBRE | F6: NO | G6: 010 Restauración | H6: Festivos y Fines de Semana | I6: ALONSO ALONSO, ANGEL LUIS | J6: ALGADI | K6: 510006 | L6: =IF(W6>0,IF(OR(E6="",F6="",G6="",H6="",I6="",J6="",K6=""),"faltan datos","ok")," ") -> ok | M6: =IFERROR(VLOOKUP(K6,Centros!$E$2:$G$340,2,FALSE)," ") -> C.P. CONCEPCIONISTAS - BELISANA | N6: =IF(J6=" "," ",IF(J6=X6," ","Emp Orig/dest. Distinta")) | O6: =IFERROR(VLOOKUP($I6,Trabajadores!$C$3:$AF$1684,19,FALSE)," ") -> h Cociner@ | P6: 1 | Q6: 80 | R6: =+P6*Q6 -> 80 | T6: =IF(AL6="99100165012016",AQ6,IF(AL6="28009435011996",AR6,IF(AL6="99010825011997",AS6))) -> 1.7437656 | U6: =IF(T6="no corresponde",0,+S6*T6) -> 0 | W6: =+V6*AK6+((+R6+U6)*1.3195) -> 105.56 | X6: =IFERROR(VLOOKUP($I6,Trabajadores!$C$2:$AS$1684,42,FALSE)," ") -> ALGADI | Y6: =IFERROR(VLOOKUP($I6,Trabajadores!$C$2:$AS$1684,40,FALSE)," ") -> 110216 | Z6: =IFERROR(VLOOKUP(Y6,Centros!$X$2:$Y$228,2,FALSE)," ") -> COL. MATER INMACULATA | AA6: 45920 | AB6: Sábado Belisana | AC6: =IFERROR(VLOOKUP(H6,Centros!$AI$2:$AN$10,6,FALSE),0) -> 70 | AD6: =IF(AC6=70,R6,0) -> 80 | AE6: =IF(AC6=72,R6,0) -> 0 | AF6: =IF(AC6=73,+R6,0) -> 0 | AG6: =+U6 -> 0 | AH6: =IFERROR(VLOOKUP($I6,Trabajadores!$C$3:$AT$1684,44,FALSE),0) -> 19228 | AI6: =IFERROR(VLOOKUP($I6,Trabajadores!$C$3:$AT$1684,2,FALSE),0) -> 1334 | AJ6: =IFERROR(VLOOKUP($I6,Trabajadores!$C$3:$AY$1270,21,FALSE),0) -> 107 | AK6: =IFERROR(VLOOKUP($I6,Trabajadores!$C$3:$AN$1684,38,FALSE),0) -> 11.40625 | AL6: =IFERROR(VLOOKUP($I6,Trabajadores!$C$3:$AN$1684,28,FALSE),0) -> 99100165012016 | AM6: =IFERROR(VLOOKUP($I6,Trabajadores!$C$3:$AN$1684,19,FALSE),0) -> h Cociner@ | AN6: =IFERROR(IF($J6="algadi",VLOOKUP($K6,Centros!$AB$2:$AD$142,2,FALSE),VLOOKUP($K6,Centros!$AB$143:$AD$282,2,FALSE)),0) -> 5027 | AO6: =IFERROR(IF($J6="algadi",VLOOKUP($K6,Centros!$AB$2:$AD$142,3,FALSE),VLOOKUP($K6,Centros!$AB$143:$AD$222,3,FALSE)),0) -> 70 | AQ6: =IFERROR(VLOOKUP($AM6,Centros!$AR$2:$AS$405,2,FALSE),0) -> 1.7437656 | AR6: =IFERROR(VLOOKUP($AM6,Centros!$AZ$2:$BA$6,2,FALSE),0) -> 0 | AS6: =IFERROR(VLOOKUP($AM6,Centros!$BE$2:$BF$6,2,FALSE),0) -> 0 | BD6: =+X6 -> ALGADI | BE6: INCIDENCIA | BF6: =+E6 -> 9-SEPTIEMBRE | BG6: =+Y6 -> 110216 | BH6: =VLOOKUP(Y6,Hoja1!$A$2:$O$599,14,FALSE) -> 110216 | BI6: =VLOOKUP(BH6,Hoja1!$A$2:$O$599,2,FALSE) -> COL. MATER INMACULATA | BJ6: =+I6 -> ALONSO ALONSO, ANGEL LUIS | BK6: =VLOOKUP(BJ6,Trabajadores!$C$3:$AN$3285,14,FALSE) -> 300 | BL6: =VLOOKUP($BJ6,Trabajadores!$C$3:$AN$3285,19,FALSE) -> h Cociner@ | BM6: =VLOOKUP($BJ6,Trabajadores!$C$3:$AN$3285,16,FALSE) -> 100 | BN6: =IF($G6="010 Restauración",100%,0%) -> 1 | BO6: =IF($G6="020 Limpieza",100%,0%) -> 0 | BP6: =+BN6+BO6 -> 1 | BR6: =-W6 -> -105.56 | BV6: =+J6 -> ALGADI | BW6: INCIDENCIA | BX6: =+E6 -> 9-SEPTIEMBRE | BY6: =+K6 -> 510006 | BZ6: =VLOOKUP(BY6,Hoja1!$A$2:$O$599,14,FALSE) -> 510006 | CA6: =VLOOKUP(BZ6,Hoja1!$A$2:$O$599,2,FALSE) -> C.P. CONCEPCIONISTAS - BELISANA | CB6: =+H6 -> Festivos y Fines de Semana | CC6: 888 | CD6: =+BW6 -> INCIDENCIA | CJ6: =+W6 -> 105.56
D7: 945 | E7: 9-SEPTIEMBRE | F7: NO | G7: 010 Restauración | H7: Festivos y Fines de Semana | I7: ALONSO ALONSO, ANGEL LUIS | J7: ALGADI | K7: 510015 | L7: =IF(W7>0,IF(OR(E7="",F7="",G7="",H7="",I7="",J7="",K7=""),"faltan datos","ok")," ") -> ok | M7: =IFERROR(VLOOKUP(K7,Centros!$E$2:$G$340,2,FALSE)," ") -> CASA GENERAL MM. CONCEPCIONISTAS | N7: =IF(J7=" "," ",IF(J7=X7," ","Emp Orig/dest. Distinta")) | O7: =IFERROR(VLOOKUP($I7,Trabajadores!$C$3:$AF$1684,19,FALSE)," ") -> h Cociner@ | P7: 1 | Q7: 80 | R7: =+P7*Q7 -> 80 | T7: =IF(AL7="99100165012016",AQ7,IF(AL7="28009435011996",AR7,IF(AL7="99010825011997",AS7))) -> 1.7437656 | U7: =IF(T7="no corresponde",0,+S7*T7) -> 0 | W7: =+V7*AK7+((+R7+U7)*1.3195) -> 105.56 | X7: =IFERROR(VLOOKUP($I7,Trabajadores!$C$2:$AS$1684,42,FALSE)," ") -> ALGADI | Y7: =IFERROR(VLOOKUP($I7,Trabajadores!$C$2:$AS$1684,40,FALSE)," ") -> 110216 | Z7: =IFERROR(VLOOKUP(Y7,Centros!$X$2:$Y$228,2,FALSE)," ") -> COL. MATER INMACULATA | AA7: 45892 | AB7: Elvia no puede hacer el sábado en Sanchez Guerrero y hay grupo | AC7: =IFERROR(VLOOKUP(H7,Centros!$AI$2:$AN$10,6,FALSE),0) -> 70 | AD7: =IF(AC7=70,R7,0) -> 80 | AE7: =IF(AC7=72,R7,0) -> 0 | AF7: =IF(AC7=73,+R7,0) -> 0 | AG7: =+U7 -> 0 | AH7: =IFERROR(VLOOKUP($I7,Trabajadores!$C$3:$AT$1684,44,FALSE),0) -> 19228 | AI7: =IFERROR(VLOOKUP($I7,Trabajadores!$C$3:$AT$1684,2,FALSE),0) -> 1334 | AJ7: =IFERROR(VLOOKUP($I7,Trabajadores!$C$3:$AY$1270,21,FALSE),0) -> 107 | AK7: =IFERROR(VLOOKUP($I7,Trabajadores!$C$3:$AN$1684,38,FALSE),0) -> 11.40625 | AL7: =IFERROR(VLOOKUP($I7,Trabajadores!$C$3:$AN$1684,28,FALSE),0) -> 99100165012016 | AM7: =IFERROR(VLOOKUP($I7,Trabajadores!$C$3:$AN$1684,19,FALSE),0) -> h Cociner@ | AN7: =IFERROR(IF($J7="algadi",VLOOKUP($K7,Centros!$AB$2:$AD$142,2,FALSE),VLOOKUP($K7,Centros!$AB$143:$AD$282,2,FALSE)),0) -> 19228 | AO7: =IFERROR(IF($J7="algadi",VLOOKUP($K7,Centros!$AB$2:$AD$142,3,FALSE),VLOOKUP($K7,Centros!$AB$143:$AD$222,3,FALSE)),0) -> 33 | AQ7: =IFERROR(VLOOKUP($AM7,Centros!$AR$2:$AS$405,2,FALSE),0) -> 1.7437656 | AR7: =IFERROR(VLOOKUP($AM7,Centros!$AZ$2:$BA$6,2,FALSE),0) -> 0 | AS7: =IFERROR(VLOOKUP($AM7,Centros!$BE$2:$BF$6,2,FALSE),0) -> 0 | BD7: =+X7 -> ALGADI | BE7: INCIDENCIA | BF7: =+E7 -> 9-SEPTIEMBRE | BG7: =+Y7 -> 110216 | BH7: =VLOOKUP(Y7,Hoja1!$A$2:$O$599,14,FALSE) -> 110216 | BI7: =VLOOKUP(BH7,Hoja1!$A$2:$O$599,2,FALSE) -> COL. MATER INMACULATA | BJ7: =+I7 -> ALONSO ALONSO, ANGEL LUIS | BK7: =VLOOKUP(BJ7,Trabajadores!$C$3:$AN$3285,14,FALSE) -> 300 | BL7: =VLOOKUP($BJ7,Trabajadores!$C$3:$AN$3285,19,FALSE) -> h Cociner@ | BM7: =VLOOKUP($BJ7,Trabajadores!$C$3:$AN$3285,16,FALSE) -> 100 | BN7: =IF($G7="010 Restauración",100%,0%) -> 1 | BO7: =IF($G7="020 Limpieza",100%,0%) -> 0 | BP7: =+BN7+BO7 -> 1 | BR7: =-W7 -> -105.56 | BV7: =+J7 -> ALGADI | BW7: INCIDENCIA | BX7: =+E7 -> 9-SEPTIEMBRE | BY7: =+K7 -> 510015 | BZ7: =VLOOKUP(BY7,Hoja1!$A$2:$O$599,14,FALSE) -> 510015 | CA7: =VLOOKUP(BZ7,Hoja1!$A$2:$O$599,2,FALSE) -> CASA GENERAL MM. CONCEPCIONISTAS | CB7: =+H7 -> Festivos y Fines de Semana | CC7: 888 | CD7: =+BW7 -> INCIDENCIA | CJ7: =+W7 -> 105.56
D8: 945 | E8: 9-SEPTIEMBRE | F8: NO | G8: 020 Limpieza | H8: Permiso retribuido | I8: ALZATE CARDENAS, MELISSA | J8: ALGADI | K8: 110082 | L8: =IF(W8>0,IF(OR(E8="",F8="",G8="",H8="",I8="",J8="",K8=""),"faltan datos","ok")," ") -> ok | M8: =IFERROR(VLOOKUP(K8,Centros!$E$2:$G$340,2,FALSE)," ") -> COL. SAN MIGUEL ARCANGEL | N8: =IF(J8=" "," ",IF(J8=X8," ","Emp Orig/dest. Distinta")) | O8: =IFERROR(VLOOKUP($I8,Trabajadores!$C$3:$AF$1684,19,FALSE)," ") -> ASL | P8: 7 | Q8: 9 | R8: =+P8*Q8 -> 63 | T8: =IF(AL8="99100165012016",AQ8,IF(AL8="28009435011996",AR8,IF(AL8="99010825011997",AS8))) -> 1.6367812 | U8: =IF(T8="no corresponde",0,+S8*T8) -> 0 | W8: =+V8*AK8+((+R8+U8)*1.3195) -> 83.1285 | X8: =IFERROR(VLOOKUP($I8,Trabajadores!$C$2:$AS$1684,42,FALSE)," ") -> ALGADI | Y8: =IFERROR(VLOOKUP($I8,Trabajadores!$C$2:$AS$1684,40,FALSE)," ") -> 110082 | Z8: =IFERROR(VLOOKUP(Y8,Centros!$X$2:$Y$228,2,FALSE)," ") -> COL. SAN MIGUEL ARCANGEL | AA8: 19, 22 y 23 sept´25 | AB8: PR de Pilar Fernández (ingreso hermano) | AC8: =IFERROR(VLOOKUP(H8,Centros!$AI$2:$AN$10,6,FALSE),0) -> 72 | AD8: =IF(AC8=70,R8,0) -> 0 | AE8: =IF(AC8=72,R8,0) -> 63 | AF8: =IF(AC8=73,+R8,0) -> 0 | AG8: =+U8 -> 0 | AH8: =IFERROR(VLOOKUP($I8,Trabajadores!$C$3:$AT$1684,44,FALSE),0) -> 19228 | AI8: =IFERROR(VLOOKUP($I8,Trabajadores!$C$3:$AT$1684,2,FALSE),0) -> 1035 | AJ8: =IFERROR(VLOOKUP($I8,Trabajadores!$C$3:$AY$1270,21,FALSE),0) -> 4 | AK8: =IFERROR(VLOOKUP($I8,Trabajadores!$C$3:$AN$1684,38,FALSE),0) -> 7.8 | AL8: =IFERROR(VLOOKUP($I8,Trabajadores!$C$3:$AN$1684,28,FALSE),0) -> 99100165012016 | AM8: =IFERROR(VLOOKUP($I8,Trabajadores!$C$3:$AN$1684,19,FALSE),0) -> ASL | AN8: =IFERROR(IF($J8="algadi",VLOOKUP($K8,Centros!$AB$2:$AD$142,2,FALSE),VLOOKUP($K8,Centros!$AB$143:$AD$282,2,FALSE)),0) -> 19228 | AO8: =IFERROR(IF($J8="algadi",VLOOKUP($K8,Centros!$AB$2:$AD$142,3,FALSE),VLOOKUP($K8,Centros!$AB$143:$AD$222,3,FALSE)),0) -> 4 | AQ8: =IFERROR(VLOOKUP($AM8,Centros!$AR$2:$AS$405,2,FALSE),0) -> 1.6367812 | AR8: =IFERROR(VLOOKUP($AM8,Centros!$AZ$2:$BA$6,2,FALSE),0) -> 0 | AS8: =IFERROR(VLOOKUP($AM8,Centros!$BE$2:$BF$6,2,FALSE),0) -> 2.05 | BD8: =+X8 -> ALGADI | BE8: INCIDENCIA | BF8: =+E8 -> 9-SEPTIEMBRE | BG8: =+Y8 -> 110082 | BH8: =VLOOKUP(Y8,Hoja1!$A$2:$O$599,14,FALSE) -> 110082 | BI8: =VLOOKUP(BH8,Hoja1!$A$2:$O$599,2,FALSE) -> COL. SAN MIGUEL ARCANGEL | BJ8: =+I8 -> ALZATE CARDENAS, MELISSA | BK8: =VLOOKUP(BJ8,Trabajadores!$C$3:$AN$3285,14,FALSE) -> 510 | BL8: =VLOOKUP($BJ8,Trabajadores!$C$3:$AN$3285,19,FALSE) -> ASL | BM8: =VLOOKUP($BJ8,Trabajadores!$C$3:$AN$3285,16,FALSE) -> 50 | BN8: =IF($G8="010 Restauración",100%,0%) -> 0 | BO8: =IF($G8="020 Limpieza",100%,0%) -> 1 | BP8: =+BN8+BO8 -> 1 | BR8: =-W8 -> -83.1285 | BV8: =+J8 -> ALGADI | BW8: INCIDENCIA | BX8: =+E8 -> 9-SEPTIEMBRE | BY8: =+K8 -> 110082 | BZ8: =VLOOKUP(BY8,Hoja1!$A$2:$O$599,14,FALSE) -> 110082 | CA8: =VLOOKUP(BZ8,Hoja1!$A$2:$O$599,2,FALSE) -> COL. SAN MIGUEL ARCANGEL | CB8: =+H8 -> Permiso retribuido | CC8: 888 | CD8: =+BW8 -> INCIDENCIA | CJ8: =+W8 -> 83.1285
D9: 945 | E9: 9-SEPTIEMBRE | F9: SI | G9: 020 Limpieza | H9: Refuerzo | I9: ALZATE CARDENAS, MELISSA | J9: ALGADI | K9: 110082 | L9: =IF(W9>0,IF(OR(E9="",F9="",G9="",H9="",I9="",J9="",K9=""),"faltan datos","ok")," ") -> ok | M9: =IFERROR(VLOOKUP(K9,Centros!$E$2:$G$340,2,FALSE)," ") -> COL. SAN MIGUEL ARCANGEL | N9: =IF(J9=" "," ",IF(J9=X9," ","Emp Orig/dest. Distinta")) | O9: =IFERROR(VLOOKUP($I9,Trabajadores!$C$3:$AF$1684,19,FALSE)," ") -> ASL | P9: 4 | Q9: 9 | R9: =+P9*Q9 -> 36 | T9: =IF(AL9="99100165012016",AQ9,IF(AL9="28009435011996",AR9,IF(AL9="99010825011997",AS9))) -> 1.6367812 | U9: =IF(T9="no corresponde",0,+S9*T9) -> 0 | W9: =+V9*AK9+((+R9+U9)*1.3195) -> 47.502 | X9: =IFERROR(VLOOKUP($I9,Trabajadores!$C$2:$AS$1684,42,FALSE)," ") -> ALGADI | Y9: =IFERROR(VLOOKUP($I9,Trabajadores!$C$2:$AS$1684,40,FALSE)," ") -> 110082 | Z9: =IFERROR(VLOOKUP(Y9,Centros!$X$2:$Y$228,2,FALSE)," ") -> COL. SAN MIGUEL ARCANGEL | AA9: 4, 5 y 6 Septiembre´25 | AB9: LIMPIEZA TEATRO | AC9: =IFERROR(VLOOKUP(H9,Centros!$AI$2:$AN$10,6,FALSE),0) -> 72 | AD9: =IF(AC9=70,R9,0) -> 0 | AE9: =IF(AC9=72,R9,0) -> 36 | AF9: =IF(AC9=73,+R9,0) -> 0 | AG9: =+U9 -> 0 | AH9: =IFERROR(VLOOKUP($I9,Trabajadores!$C$3:$AT$1684,44,FALSE),0) -> 19228 | AI9: =IFERROR(VLOOKUP($I9,Trabajadores!$C$3:$AT$1684,2,FALSE),0) -> 1035 | AJ9: =IFERROR(VLOOKUP($I9,Trabajadores!$C$3:$AY$1270,21,FALSE),0) -> 4 | AK9: =IFERROR(VLOOKUP($I9,Trabajadores!$C$3:$AN$1684,38,FALSE),0) -> 7.8 | AL9: =IFERROR(VLOOKUP($I9,Trabajadores!$C$3:$AN$1684,28,FALSE),0) -> 99100165012016 | AM9: =IFERROR(VLOOKUP($I9,Trabajadores!$C$3:$AN$1684,19,FALSE),0) -> ASL | AN9: =IFERROR(IF($J9="algadi",VLOOKUP($K9,Centros!$AB$2:$AD$142,2,FALSE),VLOOKUP($K9,Centros!$AB$143:$AD$282,2,FALSE)),0) -> 19228 | AO9: =IFERROR(IF($J9="algadi",VLOOKUP($K9,Centros!$AB$2:$AD$142,3,FALSE),VLOOKUP($K9,Centros!$AB$143:$AD$222,3,FALSE)),0) -> 4 | AQ9: =IFERROR(VLOOKUP($AM9,Centros!$AR$2:$AS$405,2,FALSE),0) -> 1.6367812 | AR9: =IFERROR(VLOOKUP($AM9,Centros!$AZ$2:$BA$6,2,FALSE),0) -> 0 | AS9: =IFERROR(VLOOKUP($AM9,Centros!$BE$2:$BF$6,2,FALSE),0) -> 2.05 | BD9: =+X9 -> ALGADI | BE9: INCIDENCIA | BF9: =+E9 -> 9-SEPTIEMBRE | BG9: =+Y9 -> 110082 | BH9: =VLOOKUP(Y9,Hoja1!$A$2:$O$599,14,FALSE) -> 110082 | BI9: =VLOOKUP(BH9,Hoja1!$A$2:$O$599,2,FALSE) -> COL. SAN MIGUEL ARCANGEL | BJ9: =+I9 -> ALZATE CARDENAS, MELISSA | BK9: =VLOOKUP(BJ9,Trabajadores!$C$3:$AN$3285,14,FALSE) -> 510 | BL9: =VLOOKUP($BJ9,Trabajadores!$C$3:$AN$3285,19,FALSE) -> ASL | BM9: =VLOOKUP($BJ9,Trabajadores!$C$3:$AN$3285,16,FALSE) -> 50 | BN9: =IF($G9="010 Restauración",100%,0%) -> 0 | BO9: =IF($G9="020 Limpieza",100%,0%) -> 1 | BP9: =+BN9+BO9 -> 1 | BR9: =-W9 -> -47.502 | BV9: =+J9 -> ALGADI | BW9: INCIDENCIA | BX9: =+E9 -> 9-SEPTIEMBRE | BY9: =+K9 -> 110082 | BZ9: =VLOOKUP(BY9,Hoja1!$A$2:$O$599,14,FALSE) -> 110082 | CA9: =VLOOKUP(BZ9,Hoja1!$A$2:$O$599,2,FALSE) -> COL. SAN MIGUEL ARCANGEL | CB9: =+H9 -> Refuerzo | CC9: 888 | CD9: =+BW9 -> INCIDENCIA | CJ9: =+W9 -> 47.502
D10: 945 | E10: 9-SEPTIEMBRE | F10: SI | G10: 020 Limpieza | H10: Refuerzo | I10: ALZATE CARDENAS, MELISSA | J10: ALGADI | K10: 110082 | L10: =IF(W10>0,IF(OR(E10="",F10="",G10="",H10="",I10="",J10="",K10=""),"faltan datos","ok")," ") -> ok | M10: =IFERROR(VLOOKUP(K10,Centros!$E$2:$G$340,2,FALSE)," ") -> COL. SAN MIGUEL ARCANGEL | N10: =IF(J10=" "," ",IF(J10=X10," ","Emp Orig/dest. Distinta")) | O10: =IFERROR(VLOOKUP($I10,Trabajadores!$C$3:$AF$1684,19,FALSE)," ") -> ASL | P10: 16 | Q10: 9 | R10: =+P10*Q10 -> 144 | T10: =IF(AL10="99100165012016",AQ10,IF(AL10="28009435011996",AR10,IF(AL10="99010825011997",AS10))) -> 1.6367812 | U10: =IF(T10="no corresponde",0,+S10*T10) -> 0 | W10: =+V10*AK10+((+R10+U10)*1.3195) -> 190.008 | X10: =IFERROR(VLOOKUP($I10,Trabajadores!$C$2:$AS$1684,42,FALSE)," ") -> ALGADI | Y10: =IFERROR(VLOOKUP($I10,Trabajadores!$C$2:$AS$1684,40,FALSE)," ") -> 110082 | Z10: =IFERROR(VLOOKUP(Y10,Centros!$X$2:$Y$228,2,FALSE)," ") -> COL. SAN MIGUEL ARCANGEL | AA10: Agosto´25 | AB10: Refuerzo por NSPP de Nikole (refuerzo limpieza pedido cliente) | AC10: =IFERROR(VLOOKUP(H10,Centros!$AI$2:$AN$10,6,FALSE),0) -> 72 | AD10: =IF(AC10=70,R10,0) -> 0 | AE10: =IF(AC10=72,R10,0) -> 144 | AF10: =IF(AC10=73,+R10,0) -> 0 | AG10: =+U10 -> 0 | AH10: =IFERROR(VLOOKUP($I10,Trabajadores!$C$3:$AT$1684,44,FALSE),0) -> 19228 | AI10: =IFERROR(VLOOKUP($I10,Trabajadores!$C$3:$AT$1684,2,FALSE),0) -> 1035 | AJ10: =IFERROR(VLOOKUP($I10,Trabajadores!$C$3:$AY$1270,21,FALSE),0) -> 4 | AK10: =IFERROR(VLOOKUP($I10,Trabajadores!$C$3:$AN$1684,38,FALSE),0) -> 7.8 | AL10: =IFERROR(VLOOKUP($I10,Trabajadores!$C$3:$AN$1684,28,FALSE),0) -> 99100165012016 | AM10: =IFERROR(VLOOKUP($I10,Trabajadores!$C$3:$AN$1684,19,FALSE),0) -> ASL | AN10: =IFERROR(IF($J10="algadi",VLOOKUP($K10,Centros!$AB$2:$AD$142,2,FALSE),VLOOKUP($K10,Centros!$AB$143:$AD$282,2,FALSE)),0) -> 19228 | AO10: =IFERROR(IF($J10="algadi",VLOOKUP($K10,Centros!$AB$2:$AD$142,3,FALSE),VLOOKUP($K10,Centros!$AB$143:$AD$222,3,FALSE)),0) -> 4 | AQ10: =IFERROR(VLOOKUP($AM10,Centros!$AR$2:$AS$405,2,FALSE),0) -> 1.6367812 | AR10: =IFERROR(VLOOKUP($AM10,Centros!$AZ$2:$BA$6,2,FALSE),0) -> 0 | AS10: =IFERROR(VLOOKUP($AM10,Centros!$BE$2:$BF$6,2,FALSE),0) -> 2.05 | BD10: =+X10 -> ALGADI | BE10: INCIDENCIA | BF10: =+E10 -> 9-SEPTIEMBRE | BG10: =+Y10 -> 110082 | BH10: =VLOOKUP(Y10,Hoja1!$A$2:$O$599,14,FALSE) -> 110082 | BI10: =VLOOKUP(BH10,Hoja1!$A$2:$O$599,2,FALSE) -> COL. SAN MIGUEL ARCANGEL | BJ10: =+I10 -> ALZATE CARDENAS, MELISSA | BK10: =VLOOKUP(BJ10,Trabajadores!$C$3:$AN$3285,14,FALSE) -> 510 | BL10: =VLOOKUP($BJ10,Trabajadores!$C$3:$AN$3285,19,FALSE) -> ASL | BM10: =VLOOKUP($BJ10,Trabajadores!$C$3:$AN$3285,16,FALSE) -> 50 | BN10: =IF($G10="010 Restauración",100%,0%) -> 0 | BO10: =IF($G10="020 Limpieza",100%,0%) -> 1 | BP10: =+BN10+BO10 -> 1 | BR10: =-W10 -> -190.008 | BV10: =+J10 -> ALGADI | BW10: INCIDENCIA | BX10: =+E10 -> 9-SEPTIEMBRE | BY10: =+K10 -> 110082 | BZ10: =VLOOKUP(BY10,Hoja1!$A$2:$O$599,14,FALSE) -> 110082 | CA10: =VLOOKUP(BZ10,Hoja1!$A$2:$O$599,2,FALSE) -> COL. SAN MIGUEL ARCANGEL | CB10: =+H10 -> Refuerzo | CC10: 888 | CD10: =+BW10 -> INCIDENCIA | CJ10: =+W10 -> 190.008
D11: 945 | E11: 9-SEPTIEMBRE | F11: NO | G11: 010 Restauración | H11: Otros | I11: BELTRE GOMEZ, CARMEN G | J11: ALGADI | K11: 110065 | L11: =IF(W11>0,IF(OR(E11="",F11="",G11="",H11="",I11="",J11="",K11=""),"faltan datos","ok")," ") -> ok | M11: =IFERROR(VLOOKUP(K11,Centros!$E$2:$G$340,2,FALSE)," ") -> COLEGIO SANTA RITA | N11: =IF(J11=" "," ",IF(J11=X11," ","Emp Orig/dest. Distinta")) | O11: =IFERROR(VLOOKUP($I11,Trabajadores!$C$3:$AF$1684,19,FALSE)," ") -> ASL | P11: 11.5 | Q11: 5.76 | R11: =+P11*Q11 -> 66.24 | T11: =IF(AL11="99100165012016",AQ11,IF(AL11="28009435011996",AR11,IF(AL11="99010825011997",AS11))) -> 1.6367812 | U11: =IF(T11="no corresponde",0,+S11*T11) -> 0 | W11: =+V11*AK11+((+R11+U11)*1.3195) -> 87.40368 | X11: =IFERROR(VLOOKUP($I11,Trabajadores!$C$2:$AS$1684,42,FALSE)," ") -> ALGADI | Y11: =IFERROR(VLOOKUP($I11,Trabajadores!$C$2:$AS$1684,40,FALSE)," ") -> 110065 | Z11: =IFERROR(VLOOKUP(Y11,Centros!$X$2:$Y$228,2,FALSE)," ") -> COLEGIO SANTA RITA | AA11: Serp´25 | AB11: 1/2 hora diaria por fuera contrato (SMI) desde el 8-09-25 | AC11: =IFERROR(VLOOKUP(H11,Centros!$AI$2:$AN$10,6,FALSE),0) -> 72 | AD11: =IF(AC11=70,R11,0) -> 0 | AE11: =IF(AC11=72,R11,0) -> 66.24 | AF11: =IF(AC11=73,+R11,0) -> 0 | AG11: =+U11 -> 0 | AH11: =IFERROR(VLOOKUP($I11,Trabajadores!$C$3:$AT$1684,44,FALSE),0) -> 19228 | AI11: =IFERROR(VLOOKUP($I11,Trabajadores!$C$3:$AT$1684,2,FALSE),0) -> 1444 | AJ11: =IFERROR(VLOOKUP($I11,Trabajadores!$C$3:$AY$1270,21,FALSE),0) -> 6 | AK11: =IFERROR(VLOOKUP($I11,Trabajadores!$C$3:$AN$1684,38,FALSE),0) -> 7.7885714 | AL11: =IFERROR(VLOOKUP($I11,Trabajadores!$C$3:$AN$1684,28,FALSE),0) -> 99100165012016 | AM11: =IFERROR(VLOOKUP($I11,Trabajadores!$C$3:$AN$1684,19,FALSE),0) -> ASL | AN11: =IFERROR(IF($J11="algadi",VLOOKUP($K11,Centros!$AB$2:$AD$142,2,FALSE),VLOOKUP($K11,Centros!$AB$143:$AD$282,2,FALSE)),0) -> 5027 | AO11: =IFERROR(IF($J11="algadi",VLOOKUP($K11,Centros!$AB$2:$AD$142,3,FALSE),VLOOKUP($K11,Centros!$AB$143:$AD$222,3,FALSE)),0) -> 33 | AQ11: =IFERROR(VLOOKUP($AM11,Centros!$AR$2:$AS$405,2,FALSE),0) -> 1.6367812 | AR11: =IFERROR(VLOOKUP($AM11,Centros!$AZ$2:$BA$6,2,FALSE),0) -> 0 | AS11: =IFERROR(VLOOKUP($AM11,Centros!$BE$2:$BF$6,2,FALSE),0) -> 2.05 | BD11: =+X11 -> ALGADI | BE11: INCIDENCIA | BF11: =+E11 -> 9-SEPTIEMBRE | BG11: =+Y11 -> 110065 | BH11: =VLOOKUP(Y11,Hoja1!$A$2:$O$599,14,FALSE) -> 110065 | BI11: =VLOOKUP(BH11,Hoja1!$A$2:$O$599,2,FALSE) -> COLEGIO SANTA RITA | BJ11: =+I11 -> BELTRE GOMEZ, CARMEN G | BK11: =VLOOKUP(BJ11,Trabajadores!$C$3:$AN$3285,14,FALSE) -> 300 | BL11: =VLOOKUP($BJ11,Trabajadores!$C$3:$AN$3285,19,FALSE) -> ASL | BM11: =VLOOKUP($BJ11,Trabajadores!$C$3:$AN$3285,16,FALSE) -> 43.75 | BN11: =IF($G11="010 Restauración",100%,0%) -> 1 | BO11: =IF($G11="020 Limpieza",100%,0%) -> 0 | BP11: =+BN11+BO11 -> 1 | BR11: =-W11 -> -87.40368 | BV11: =+J11 -> ALGADI | BW11: INCIDENCIA | BX11: =+E11 -> 9-SEPTIEMBRE | BY11: =+K11 -> 110065 | BZ11: =VLOOKUP(BY11,Hoja1!$A$2:$O$599,14,FALSE) -> 110065 | CA11: =VLOOKUP(BZ11,Hoja1!$A$2:$O$599,2,FALSE) -> COLEGIO SANTA RITA | CB11: =+H11 -> Otros | CC11: 888 | CD11: =+BW11 -> INCIDENCIA | CJ11: =+W11 -> 87.40368
D12: 945 | E12: 9-SEPTIEMBRE | F12: NO | G12: 020 Limpieza | H12: Permiso retribuido | I12: CABELLO CLAJER, ANA BELEN | J12: ALGADI | K12: 110021 | L12: =IF(W12>0,IF(OR(E12="",F12="",G12="",H12="",I12="",J12="",K12=""),"faltan datos","ok")," ") -> ok | M12: =IFERROR(VLOOKUP(K12,Centros!$E$2:$G$340,2,FALSE)," ") -> COLEGIO FUNDACION CALDEIRO | N12: =IF(J12=" "," ",IF(J12=X12," ","Emp Orig/dest. Distinta")) | O12: =IFERROR(VLOOKUP($I12,Trabajadores!$C$3:$AF$1684,19,FALSE)," ") -> ASL | P12: 28.5 | Q12: 9 | R12: =+P12*Q12 -> 256.5 | T12: =IF(AL12="99100165012016",AQ12,IF(AL12="28009435011996",AR12,IF(AL12="99010825011997",AS12))) -> 1.6367812 | U12: =IF(T12="no corresponde",0,+S12*T12) -> 0 | W12: =+V12*AK12+((+R12+U12)*1.3195) -> 338.45175 | X12: =IFERROR(VLOOKUP($I12,Trabajadores!$C$2:$AS$1684,42,FALSE)," ") -> ALGADI | Y12: =IFERROR(VLOOKUP($I12,Trabajadores!$C$2:$AS$1684,40,FALSE)," ") -> 888888 | Z12: =IFERROR(VLOOKUP(Y12,Centros!$X$2:$Y$228,2,FALSE)," ") -> CORRETURNOS/RAPPELS | AA12: 25 la 29 de agosto | AB12: IT LUCIA JIMENEZ | AC12: =IFERROR(VLOOKUP(H12,Centros!$AI$2:$AN$10,6,FALSE),0) -> 72 | AD12: =IF(AC12=70,R12,0) -> 0 | AE12: =IF(AC12=72,R12,0) -> 256.5 | AF12: =IF(AC12=73,+R12,0) -> 0 | AG12: =+U12 -> 0 | AH12: =IFERROR(VLOOKUP($I12,Trabajadores!$C$3:$AT$1684,44,FALSE),0) -> 19228 | AI12: =IFERROR(VLOOKUP($I12,Trabajadores!$C$3:$AT$1684,2,FALSE),0) -> 2107 | AJ12: =IFERROR(VLOOKUP($I12,Trabajadores!$C$3:$AY$1270,21,FALSE),0) -> 55 | AK12: =IFERROR(VLOOKUP($I12,Trabajadores!$C$3:$AN$1684,38,FALSE),0) -> 8.365 | AL12: =IFERROR(VLOOKUP($I12,Trabajadores!$C$3:$AN$1684,28,FALSE),0) -> 99100165012016 | AM12: =IFERROR(VLOOKUP($I12,Trabajadores!$C$3:$AN$1684,19,FALSE),0) -> ASL | AN12: =IFERROR(IF($J12="algadi",VLOOKUP($K12,Centros!$AB$2:$AD$142,2,FALSE),VLOOKUP($K12,Centros!$AB$143:$AD$282,2,FALSE)),0) -> 19228 | AO12: =IFERROR(IF($J12="algadi",VLOOKUP($K12,Centros!$AB$2:$AD$142,3,FALSE),VLOOKUP($K12,Centros!$AB$143:$AD$222,3,FALSE)),0) -> 20 | AQ12: =IFERROR(VLOOKUP($AM12,Centros!$AR$2:$AS$405,2,FALSE),0) -> 1.6367812 | AR12: =IFERROR(VLOOKUP($AM12,Centros!$AZ$2:$BA$6,2,FALSE),0) -> 0 | AS12: =IFERROR(VLOOKUP($AM12,Centros!$BE$2:$BF$6,2,FALSE),0) -> 2.05 | BD12: =+X12 -> ALGADI | BE12: INCIDENCIA | BF12: =+E12 -> 9-SEPTIEMBRE | BG12: =+Y12 -> 888888 | BH12: =VLOOKUP(Y12,Hoja1!$A$2:$O$599,14,FALSE) -> 888888 | BI12: =VLOOKUP(BH12,Hoja1!$A$2:$O$599,2,FALSE) -> CORRETURNOS/RAPPELS | BJ12: =+I12 -> CABELLO CLAJER, ANA BELEN | BK12: =VLOOKUP(BJ12,Trabajadores!$C$3:$AN$3285,14,FALSE) -> 389 | BL12: =VLOOKUP($BJ12,Trabajadores!$C$3:$AN$3285,19,FALSE) -> ASL | BM12: =VLOOKUP($BJ12,Trabajadores!$C$3:$AN$3285,16,FALSE) -> 50 | BN12: =IF($G12="010 Restauración",100%,0%) -> 0 | BO12: =IF($G12="020 Limpieza",100%,0%) -> 1 | BP12: =+BN12+BO12 -> 1 | BR12: =-W12 -> -338.45175 | BV12: =+J12 -> ALGADI | BW12: INCIDENCIA | BX12: =+E12 -> 9-SEPTIEMBRE | BY12: =+K12 -> 110021 | BZ12: =VLOOKUP(BY12,Hoja1!$A$2:$O$599,14,FALSE) -> 110021 | CA12: =VLOOKUP(BZ12,Hoja1!$A$2:$O$599,2,FALSE) -> COLEGIO FUNDACION CALDEIRO | CB12: =+H12 -> Permiso retribuido | CC12: 888 | CD12: =+BW12 -> INCIDENCIA | CJ12: =+W12 -> 338.45175
D13: 945 | E13: 9-SEPTIEMBRE | F13: NO | G13: 010 Restauración | H13: Festivos y Fines de Semana | I13: CANDO ROSERO, LAURA R | J13: ALGADI | K13: 110030 | L13: =IF(W13>0,IF(OR(E13="",F13="",G13="",H13="",I13="",J13="",K13=""),"faltan datos","ok")," ") -> ok | M13: =IFERROR(VLOOKUP(K13,Centros!$E$2:$G$340,2,FALSE)," ") -> COLEGIO INMACULADA | N13: =IF(J13=" "," ",IF(J13=X13," ","Emp Orig/dest. Distinta")) | O13: =IFERROR(VLOOKUP($I13,Trabajadores!$C$3:$AF$1684,19,FALSE)," ") -> h Ay Cocin | P13: 1 | Q13: 82.5 | R13: =+P13*Q13 -> 82.5 | T13: =IF(AL13="99100165012016",AQ13,IF(AL13="28009435011996",AR13,IF(AL13="99010825011997",AS13))) -> 1.6906094 | U13: =IF(T13="no corresponde",0,+S13*T13) -> 0 | W13: =+V13*AK13+((+R13+U13)*1.3195) -> 108.85875 | X13: =IFERROR(VLOOKUP($I13,Trabajadores!$C$2:$AS$1684,42,FALSE)," ") -> ALGADI | Y13: =IFERROR(VLOOKUP($I13,Trabajadores!$C$2:$AS$1684,40,FALSE)," ") -> 110030 | Z13: =IFERROR(VLOOKUP(Y13,Centros!$X$2:$Y$228,2,FALSE)," ") -> COLEGIO INMACULADA | AA13: 45920 | AB13: 1/2 especial y 1/2 ASL | AC13: =IFERROR(VLOOKUP(H13,Centros!$AI$2:$AN$10,6,FALSE),0) -> 70 | AD13: =IF(AC13=70,R13,0) -> 82.5 | AE13: =IF(AC13=72,R13,0) -> 0 | AF13: =IF(AC13=73,+R13,0) -> 0 | AG13: =+U13 -> 0 | AH13: =IFERROR(VLOOKUP($I13,Trabajadores!$C$3:$AT$1684,44,FALSE),0) -> 19228 | AI13: =IFERROR(VLOOKUP($I13,Trabajadores!$C$3:$AT$1684,2,FALSE),0) -> 198 | AJ13: =IFERROR(VLOOKUP($I13,Trabajadores!$C$3:$AY$1270,21,FALSE),0) -> 36 | AK13: =IFERROR(VLOOKUP($I13,Trabajadores!$C$3:$AN$1684,38,FALSE),0) -> 8.45625 | AL13: =IFERROR(VLOOKUP($I13,Trabajadores!$C$3:$AN$1684,28,FALSE),0) -> 99100165012016 | AM13: =IFERROR(VLOOKUP($I13,Trabajadores!$C$3:$AN$1684,19,FALSE),0) -> h Ay Cocin | AN13: =IFERROR(IF($J13="algadi",VLOOKUP($K13,Centros!$AB$2:$AD$142,2,FALSE),VLOOKUP($K13,Centros!$AB$143:$AD$282,2,FALSE)),0) -> 19228 | AO13: =IFERROR(IF($J13="algadi",VLOOKUP($K13,Centros!$AB$2:$AD$142,3,FALSE),VLOOKUP($K13,Centros!$AB$143:$AD$222,3,FALSE)),0) -> 36 | AQ13: =IFERROR(VLOOKUP($AM13,Centros!$AR$2:$AS$405,2,FALSE),0) -> 1.6906094 | AR13: =IFERROR(VLOOKUP($AM13,Centros!$AZ$2:$BA$6,2,FALSE),0) -> 0 | AS13: =IFERROR(VLOOKUP($AM13,Centros!$BE$2:$BF$6,2,FALSE),0) -> 0 | BD13: =+X13 -> ALGADI | BE13: INCIDENCIA | BF13: =+E13 -> 9-SEPTIEMBRE | BG13: =+Y13 -> 110030 | BH13: =VLOOKUP(Y13,Hoja1!$A$2:$O$599,14,FALSE) -> 110030 | BI13: =VLOOKUP(BH13,Hoja1!$A$2:$O$599,2,FALSE) -> COLEGIO INMACULADA | BJ13: =+I13 -> CANDO ROSERO, LAURA R | BK13: =VLOOKUP(BJ13,Trabajadores!$C$3:$AN$3285,14,FALSE) -> 100 | BL13: =VLOOKUP($BJ13,Trabajadores!$C$3:$AN$3285,19,FALSE) -> h Ay Cocin | BM13: =VLOOKUP($BJ13,Trabajadores!$C$3:$AN$3285,16,FALSE) -> 100 | BN13: =IF($G13="010 Restauración",100%,0%) -> 1 | BO13: =IF($G13="020 Limpieza",100%,0%) -> 0 | BP13: =+BN13+BO13 -> 1 | BR13: =-W13 -> -108.85875 | BV13: =+J13 -> ALGADI | BW13: INCIDENCIA | BX13: =+E13 -> 9-SEPTIEMBRE | BY13: =+K13 -> 110030 | BZ13: =VLOOKUP(BY13,Hoja1!$A$2:$O$599,14,FALSE) -> 110030 | CA13: =VLOOKUP(BZ13,Hoja1!$A$2:$O$599,2,FALSE) -> COLEGIO INMACULADA | CB13: =+H13 -> Festivos y Fines de Semana | CC13: 888 | CD13: =+BW13 -> INCIDENCIA | CJ13: =+W13 -> 108.85875
D14: 945 | E14: 9-SEPTIEMBRE | F14: NO | G14: 010 Restauración | H14: Festivos y Fines de Semana | I14: CAÑIZARES SAEZ, DAVID | J14: ALGADI | K14: 510006 | L14: =IF(W14>0,IF(OR(E14="",F14="",G14="",H14="",I14="",J14="",K14=""),"faltan datos","ok")," ") -> ok | M14: =IFERROR(VLOOKUP(K14,Centros!$E$2:$G$340,2,FALSE)," ") -> C.P. CONCEPCIONISTAS - BELISANA | N14: =IF(J14=" "," ",IF(J14=X14," ","Emp Orig/dest. Distinta")) | O14: =IFERROR(VLOOKUP($I14,Trabajadores!$C$3:$AF$1684,19,FALSE)," ") -> Cociner@ | P14: 1 | Q14: 80 | R14: =+P14*Q14 -> 80 | T14: =IF(AL14="99100165012016",AQ14,IF(AL14="28009435011996",AR14,IF(AL14="99010825011997",AS14))) -> 1.7437656 | U14: =IF(T14="no corresponde",0,+S14*T14) -> 0 | W14: =+V14*AK14+((+R14+U14)*1.3195) -> 105.56 | X14: =IFERROR(VLOOKUP($I14,Trabajadores!$C$2:$AS$1684,42,FALSE)," ") -> ALGADI | Y14: =IFERROR(VLOOKUP($I14,Trabajadores!$C$2:$AS$1684,40,FALSE)," ") -> 110807 | Z14: =IFERROR(VLOOKUP(Y14,Centros!$X$2:$Y$228,2,FALSE)," ") -> COLEGIO NTRA SRA BUEN CONSEJO | AA14: 6 sept´25 | AB14: Sábado en Belisana | AC14: =IFERROR(VLOOKUP(H14,Centros!$AI$2:$AN$10,6,FALSE),0) -> 70 | AD14: =IF(AC14=70,R14,0) -> 80 | AE14: =IF(AC14=72,R14,0) -> 0 | AF14: =IF(AC14=73,+R14,0) -> 0 | AG14: =+U14 -> 0 | AH14: =IFERROR(VLOOKUP($I14,Trabajadores!$C$3:$AT$1684,44,FALSE),0) -> 19228 | AI14: =IFERROR(VLOOKUP($I14,Trabajadores!$C$3:$AT$1684,2,FALSE),0) -> 1777 | AJ14: =IFERROR(VLOOKUP($I14,Trabajadores!$C$3:$AY$1270,21,FALSE),0) -> 61 | AK14: =IFERROR(VLOOKUP($I14,Trabajadores!$C$3:$AN$1684,38,FALSE),0) -> 7.60125 | AL14: =IFERROR(VLOOKUP($I14,Trabajadores!$C$3:$AN$1684,28,FALSE),0) -> 99100165012016 | AM14: =IFERROR(VLOOKUP($I14,Trabajadores!$C$3:$AN$1684,19,FALSE),0) -> Cociner@ | AN14: =IFERROR(IF($J14="algadi",VLOOKUP($K14,Centros!$AB$2:$AD$142,2,FALSE),VLOOKUP($K14,Centros!$AB$143:$AD$282,2,FALSE)),0) -> 5027 | AO14: =IFERROR(IF($J14="algadi",VLOOKUP($K14,Centros!$AB$2:$AD$142,3,FALSE),VLOOKUP($K14,Centros!$AB$143:$AD$222,3,FALSE)),0) -> 70 | AQ14: =IFERROR(VLOOKUP($AM14,Centros!$AR$2:$AS$405,2,FALSE),0) -> 1.7437656 | AR14: =IFERROR(VLOOKUP($AM14,Centros!$AZ$2:$BA$6,2,FALSE),0) -> 2.32225 | AS14: =IFERROR(VLOOKUP($AM14,Centros!$BE$2:$BF$6,2,FALSE),0) -> 0 | BD14: =+X14 -> ALGADI | BE14: INCIDENCIA | BF14: =+E14 -> 9-SEPTIEMBRE | BG14: =+Y14 -> 110807 | BH14: =VLOOKUP(Y14,Hoja1!$A$2:$O$599,14,FALSE) -> 110807 | BI14: =VLOOKUP(BH14,Hoja1!$A$2:$O$599,2,FALSE) -> COLEGIO NTRA SRA BUEN CONSEJO | BJ14: =+I14 -> CAÑIZARES SAEZ, DAVID | BK14: =VLOOKUP(BJ14,Trabajadores!$C$3:$AN$3285,14,FALSE) -> 100 | BL14: =VLOOKUP($BJ14,Trabajadores!$C$3:$AN$3285,19,FALSE) -> Cociner@ | BM14: =VLOOKUP($BJ14,Trabajadores!$C$3:$AN$3285,16,FALSE) -> 100 | BN14: =IF($G14="010 Restauración",100%,0%) -> 1 | BO14: =IF($G14="020 Limpieza",100%,0%) -> 0 | BP14: =+BN14+BO14 -> 1 | BR14: =-W14 -> -105.56 | BV14: =+J14 -> ALGADI | BW14: INCIDENCIA | BX14: =+E14 -> 9-SEPTIEMBRE | BY14: =+K14 -> 510006 | BZ14: =VLOOKUP(BY14,Hoja1!$A$2:$O$599,14,FALSE) -> 510006 | CA14: =VLOOKUP(BZ14,Hoja1!$A$2:$O$599,2,FALSE) -> C.P. CONCEPCIONISTAS - BELISANA | CB14: =+H14 -> Festivos y Fines de Semana | CC14: 888 | CD14: =+BW14 -> INCIDENCIA | CJ14: =+W14 -> 105.56
D15: 945 | E15: 9-SEPTIEMBRE | F15: NO | G15: 010 Restauración | H15: Eventos | I15: CARRO GUERRERO, M CARMEN | J15: ALGADI | K15: 110091 | L15: =IF(W15>0,IF(OR(E15="",F15="",G15="",H15="",I15="",J15="",K15=""),"faltan datos","ok")," ") -> ok | M15: =IFERROR(VLOOKUP(K15,Centros!$E$2:$G$340,2,FALSE)," ") -> COLEGIO CLARET -MADRID | N15: =IF(J15=" "," ",IF(J15=X15," ","Emp Orig/dest. Distinta")) | O15: =IFERROR(VLOOKUP($I15,Trabajadores!$C$3:$AF$1684,19,FALSE)," ") -> h ASL | P15: 3 | Q15: 9 | R15: =+P15*Q15 -> 27 | T15: =IF(AL15="99100165012016",AQ15,IF(AL15="28009435011996",AR15,IF(AL15="99010825011997",AS15))) -> 1.6367812 | U15: =IF(T15="no corresponde",0,+S15*T15) -> 0 | W15: =+V15*AK15+((+R15+U15)*1.3195) -> 35.6265 | X15: =IFERROR(VLOOKUP($I15,Trabajadores!$C$2:$AS$1684,42,FALSE)," ") -> ALGADI | Y15: =IFERROR(VLOOKUP($I15,Trabajadores!$C$2:$AS$1684,40,FALSE)," ") -> 110091 | Z15: =IFERROR(VLOOKUP(Y15,Centros!$X$2:$Y$228,2,FALSE)," ") -> COLEGIO CLARET -MADRID | AA15: 45901 | AB15: Desayunos comienzo profesores | AC15: =IFERROR(VLOOKUP(H15,Centros!$AI$2:$AN$10,6,FALSE),0) -> 72 | AD15: =IF(AC15=70,R15,0) -> 0 | AE15: =IF(AC15=72,R15,0) -> 27 | AF15: =IF(AC15=73,+R15,0) -> 0 | AG15: =+U15 -> 0 | AH15: =IFERROR(VLOOKUP($I15,Trabajadores!$C$3:$AT$1684,44,FALSE),0) -> 19228 | AI15: =IFERROR(VLOOKUP($I15,Trabajadores!$C$3:$AT$1684,2,FALSE),0) -> 276 | AJ15: =IFERROR(VLOOKUP($I15,Trabajadores!$C$3:$AY$1270,21,FALSE),0) -> 50 | AK15: =IFERROR(VLOOKUP($I15,Trabajadores!$C$3:$AN$1684,38,FALSE),0) -> 9.47 | AL15: =IFERROR(VLOOKUP($I15,Trabajadores!$C$3:$AN$1684,28,FALSE),0) -> 99100165012016 | AM15: =IFERROR(VLOOKUP($I15,Trabajadores!$C$3:$AN$1684,19,FALSE),0) -> h ASL | AN15: =IFERROR(IF($J15="algadi",VLOOKUP($K15,Centros!$AB$2:$AD$142,2,FALSE),VLOOKUP($K15,Centros!$AB$143:$AD$282,2,FALSE)),0) -> 0 | AO15: =IFERROR(IF($J15="algadi",VLOOKUP($K15,Centros!$AB$2:$AD$142,3,FALSE),VLOOKUP($K15,Centros!$AB$143:$AD$222,3,FALSE)),0) -> 0 | AQ15: =IFERROR(VLOOKUP($AM15,Centros!$AR$2:$AS$405,2,FALSE),0) -> 1.6367812 | AR15: =IFERROR(VLOOKUP($AM15,Centros!$AZ$2:$BA$6,2,FALSE),0) -> 0 | AS15: =IFERROR(VLOOKUP($AM15,Centros!$BE$2:$BF$6,2,FALSE),0) -> 0 | BD15: =+X15 -> ALGADI | BE15: INCIDENCIA | BF15: =+E15 -> 9-SEPTIEMBRE | BG15: =+Y15 -> 110091 | BH15: =VLOOKUP(Y15,Hoja1!$A$2:$O$599,14,FALSE) -> 110091 | BI15: =VLOOKUP(BH15,Hoja1!$A$2:$O$599,2,FALSE) -> COLEGIO CLARET -MADRID | BJ15: =+I15 -> CARRO GUERRERO, M CARMEN | BK15: =VLOOKUP(BJ15,Trabajadores!$C$3:$AN$3285,14,FALSE) -> 300 | BL15: =VLOOKUP($BJ15,Trabajadores!$C$3:$AN$3285,19,FALSE) -> h ASL | BM15: =VLOOKUP($BJ15,Trabajadores!$C$3:$AN$3285,16,FALSE) -> 50 | BN15: =IF($G15="010 Restauración",100%,0%) -> 1 | BO15: =IF($G15="020 Limpieza",100%,0%) -> 0 | BP15: =+BN15+BO15 -> 1 | BR15: =-W15 -> -35.6265 | BV15: =+J15 -> ALGADI | BW15: INCIDENCIA | BX15: =+E15 -> 9-SEPTIEMBRE | BY15: =+K15 -> 110091 | BZ15: =VLOOKUP(BY15,Hoja1!$A$2:$O$599,14,FALSE) -> 110091 | CA15: =VLOOKUP(BZ15,Hoja1!$A$2:$O$599,2,FALSE) -> COLEGIO CLARET -MADRID | CB15: =+H15 -> Eventos | CC15: 888 | CD15: =+BW15 -> INCIDENCIA | CJ15: =+W15 -> 35.6265
D16: 945 | E16: 9-SEPTIEMBRE | F16: NO | G16: 010 Restauración | H16: Permiso retribuido | I16: CARRO GUERRERO, M CARMEN | J16: ALGADI | K16: 110091 | L16: =IF(W16>0,IF(OR(E16="",F16="",G16="",H16="",I16="",J16="",K16=""),"faltan datos","ok")," ") -> ok | M16: =IFERROR(VLOOKUP(K16,Centros!$E$2:$G$340,2,FALSE)," ") -> COLEGIO CLARET -MADRID | N16: =IF(J16=" "," ",IF(J16=X16," ","Emp Orig/dest. Distinta")) | O16: =IFERROR(VLOOKUP($I16,Trabajadores!$C$3:$AF$1684,19,FALSE)," ") -> h ASL | P16: 2 | Q16: 9 | R16: =+P16*Q16 -> 18 | T16: =IF(AL16="99100165012016",AQ16,IF(AL16="28009435011996",AR16,IF(AL16="99010825011997",AS16))) -> 1.6367812 | U16: =IF(T16="no corresponde",0,+S16*T16) -> 0 | W16: =+V16*AK16+((+R16+U16)*1.3195) -> 23.751 | X16: =IFERROR(VLOOKUP($I16,Trabajadores!$C$2:$AS$1684,42,FALSE)," ") -> ALGADI | Y16: =IFERROR(VLOOKUP($I16,Trabajadores!$C$2:$AS$1684,40,FALSE)," ") -> 110091 | Z16: =IFERROR(VLOOKUP(Y16,Centros!$X$2:$Y$228,2,FALSE)," ") -> COLEGIO CLARET -MADRID | AA16: 4 y 5 septiembre | AB16: Fallecimiento nieta Berni | AC16: =IFERROR(VLOOKUP(H16,Centros!$AI$2:$AN$10,6,FALSE),0) -> 72 | AD16: =IF(AC16=70,R16,0) -> 0 | AE16: =IF(AC16=72,R16,0) -> 18 | AF16: =IF(AC16=73,+R16,0) -> 0 | AG16: =+U16 -> 0 | AH16: =IFERROR(VLOOKUP($I16,Trabajadores!$C$3:$AT$1684,44,FALSE),0) -> 19228 | AI16: =IFERROR(VLOOKUP($I16,Trabajadores!$C$3:$AT$1684,2,FALSE),0) -> 276 | AJ16: =IFERROR(VLOOKUP($I16,Trabajadores!$C$3:$AY$1270,21,FALSE),0) -> 50 | AK16: =IFERROR(VLOOKUP($I16,Trabajadores!$C$3:$AN$1684,38,FALSE),0) -> 9.47 | AL16: =IFERROR(VLOOKUP($I16,Trabajadores!$C$3:$AN$1684,28,FALSE),0) -> 99100165012016 | AM16: =IFERROR(VLOOKUP($I16,Trabajadores!$C$3:$AN$1684,19,FALSE),0) -> h ASL | AN16: =IFERROR(IF($J16="algadi",VLOOKUP($K16,Centros!$AB$2:$AD$142,2,FALSE),VLOOKUP($K16,Centros!$AB$143:$AD$282,2,FALSE)),0) -> 0 | AO16: =IFERROR(IF($J16="algadi",VLOOKUP($K16,Centros!$AB$2:$AD$142,3,FALSE),VLOOKUP($K16,Centros!$AB$143:$AD$222,3,FALSE)),0) -> 0 | AQ16: =IFERROR(VLOOKUP($AM16,Centros!$AR$2:$AS$405,2,FALSE),0) -> 1.6367812 | AR16: =IFERROR(VLOOKUP($AM16,Centros!$AZ$2:$BA$6,2,FALSE),0) -> 0 | AS16: =IFERROR(VLOOKUP($AM16,Centros!$BE$2:$BF$6,2,FALSE),0) -> 0 | BD16: =+X16 -> ALGADI | BE16: INCIDENCIA | BF16: =+E16 -> 9-SEPTIEMBRE | BG16: =+Y16 -> 110091 | BH16: =VLOOKUP(Y16,Hoja1!$A$2:$O$599,14,FALSE) -> 110091 | BI16: =VLOOKUP(BH16,Hoja1!$A$2:$O$599,2,FALSE) -> COLEGIO CLARET -MADRID | BJ16: =+I16 -> CARRO GUERRERO, M CARMEN | BK16: =VLOOKUP(BJ16,Trabajadores!$C$3:$AN$3285,14,FALSE) -> 300 | BL16: =VLOOKUP($BJ16,Trabajadores!$C$3:$AN$3285,19,FALSE) -> h ASL | BM16: =VLOOKUP($BJ16,Trabajadores!$C$3:$AN$3285,16,FALSE) -> 50 | BN16: =IF($G16="010 Restauración",100%,0%) -> 1 | BO16: =IF($G16="020 Limpieza",100%,0%) -> 0 | BP16: =+BN16+BO16 -> 1 | BR16: =-W16 -> -23.751 | BV16: =+J16 -> ALGADI | BW16: INCIDENCIA | BX16: =+E16 -> 9-SEPTIEMBRE | BY16: =+K16 -> 110091 | BZ16: =VLOOKUP(BY16,Hoja1!$A$2:$O$599,14,FALSE) -> 110091 | CA16: =VLOOKUP(BZ16,Hoja1!$A$2:$O$599,2,FALSE) -> COLEGIO CLARET -MADRID | CB16: =+H16 -> Permiso retribuido | CC16: 888 | CD16: =+BW16 -> INCIDENCIA | CJ16: =+W16 -> 23.751
D17: 945 | E17: 9-SEPTIEMBRE | F17: NO | G17: 010 Restauración | H17: Eventos | I17: CELESTER RODRIGUEZ, ENCARNACIN | J17: ALGADI | K17: 110021 | L17: =IF(W17>0,IF(OR(E17="",F17="",G17="",H17="",I17="",J17="",K17=""),"faltan datos","ok")," ") -> ok | M17: =IFERROR(VLOOKUP(K17,Centros!$E$2:$G$340,2,FALSE)," ") -> COLEGIO FUNDACION CALDEIRO | N17: =IF(J17=" "," ",IF(J17=X17," ","Emp Orig/dest. Distinta")) | O17: =IFERROR(VLOOKUP($I17,Trabajadores!$C$3:$AF$1684,19,FALSE)," ") -> h Cociner@ | P17: 1 | Q17: 11 | R17: =+P17*Q17 -> 11 | T17: =IF(AL17="99100165012016",AQ17,IF(AL17="28009435011996",AR17,IF(AL17="99010825011997",AS17))) -> 1.7437656 | U17: =IF(T17="no corresponde",0,+S17*T17) -> 0 | W17: =+V17*AK17+((+R17+U17)*1.3195) -> 14.5145 | X17: =IFERROR(VLOOKUP($I17,Trabajadores!$C$2:$AS$1684,42,FALSE)," ") -> ALGADI | Y17: =IFERROR(VLOOKUP($I17,Trabajadores!$C$2:$AS$1684,40,FALSE)," ") -> 110021 | Z17: =IFERROR(VLOOKUP(Y17,Centros!$X$2:$Y$228,2,FALSE)," ") -> COLEGIO FUNDACION CALDEIRO | AA17: 45835 | AB17: Evento Caldeiro | AC17: =IFERROR(VLOOKUP(H17,Centros!$AI$2:$AN$10,6,FALSE),0) -> 72 | AD17: =IF(AC17=70,R17,0) -> 0 | AE17: =IF(AC17=72,R17,0) -> 11 | AF17: =IF(AC17=73,+R17,0) -> 0 | AG17: =+U17 -> 0 | AH17: =IFERROR(VLOOKUP($I17,Trabajadores!$C$3:$AT$1684,44,FALSE),0) -> 19228 | AI17: =IFERROR(VLOOKUP($I17,Trabajadores!$C$3:$AT$1684,2,FALSE),0) -> 153 | AJ17: =IFERROR(VLOOKUP($I17,Trabajadores!$C$3:$AY$1270,21,FALSE),0) -> 20 | AK17: =IFERROR(VLOOKUP($I17,Trabajadores!$C$3:$AN$1684,38,FALSE),0) -> 8.68375 | AL17: =IFERROR(VLOOKUP($I17,Trabajadores!$C$3:$AN$1684,28,FALSE),0) -> 99100165012016 | AM17: =IFERROR(VLOOKUP($I17,Trabajadores!$C$3:$AN$1684,19,FALSE),0) -> h Cociner@ | AN17: =IFERROR(IF($J17="algadi",VLOOKUP($K17,Centros!$AB$2:$AD$142,2,FALSE),VLOOKUP($K17,Centros!$AB$143:$AD$282,2,FALSE)),0) -> 19228 | AO17: =IFERROR(IF($J17="algadi",VLOOKUP($K17,Centros!$AB$2:$AD$142,3,FALSE),VLOOKUP($K17,Centros!$AB$143:$AD$222,3,FALSE)),0) -> 20 | AQ17: =IFERROR(VLOOKUP($AM17,Centros!$AR$2:$AS$405,2,FALSE),0) -> 1.7437656 | AR17: =IFERROR(VLOOKUP($AM17,Centros!$AZ$2:$BA$6,2,FALSE),0) -> 0 | AS17: =IFERROR(VLOOKUP($AM17,Centros!$BE$2:$BF$6,2,FALSE),0) -> 0 | BD17: =+X17 -> ALGADI | BE17: INCIDENCIA | BF17: =+E17 -> 9-SEPTIEMBRE | BG17: =+Y17 -> 110021 | BH17: =VLOOKUP(Y17,Hoja1!$A$2:$O$599,14,FALSE) -> 110021 | BI17: =VLOOKUP(BH17,Hoja1!$A$2:$O$599,2,FALSE) -> COLEGIO FUNDACION CALDEIRO | BJ17: =+I17 -> CELESTER RODRIGUEZ, ENCARNACIN | BK17: =VLOOKUP(BJ17,Trabajadores!$C$3:$AN$3285,14,FALSE) -> 100 | BL17: =VLOOKUP($BJ17,Trabajadores!$C$3:$AN$3285,19,FALSE) -> h Cociner@ | BM17: =VLOOKUP($BJ17,Trabajadores!$C$3:$AN$3285,16,FALSE) -> 100 | BN17: =IF($G17="010 Restauración",100%,0%) -> 1 | BO17: =IF($G17="020 Limpieza",100%,0%) -> 0 | BP17: =+BN17+BO17 -> 1 | BR17: =-W17 -> -14.5145 | BV17: =+J17 -> ALGADI | BW17: INCIDENCIA | BX17: =+E17 -> 9-SEPTIEMBRE | BY17: =+K17 -> 110021 | BZ17: =VLOOKUP(BY17,Hoja1!$A$2:$O$599,14,FALSE) -> 110021 | CA17: =VLOOKUP(BZ17,Hoja1!$A$2:$O$599,2,FALSE) -> COLEGIO FUNDACION CALDEIRO | CB17: =+H17 -> Eventos | CC17: 888 | CD17: =+BW17 -> INCIDENCIA | CJ17: =+W17 -> 14.5145
D18: 945 | E18: 9-SEPTIEMBRE | F18: NO | G18: 010 Restauración | H18: Permiso retribuido | I18: CERCAS LORENZO, AURORA B. | J18: ALGADI | K18: 110030 | L18: =IF(W18>0,IF(OR(E18="",F18="",G18="",H18="",I18="",J18="",K18=""),"faltan datos","ok")," ") -> ok | M18: =IFERROR(VLOOKUP(K18,Centros!$E$2:$G$340,2,FALSE)," ") -> COLEGIO INMACULADA | N18: =IF(J18=" "," ",IF(J18=X18," ","Emp Orig/dest. Distinta")) | O18: =IFERROR(VLOOKUP($I18,Trabajadores!$C$3:$AF$1684,19,FALSE)," ") -> h ASL | P18: 1.25 | Q18: 9 | R18: =+P18*Q18 -> 11.25 | T18: =IF(AL18="99100165012016",AQ18,IF(AL18="28009435011996",AR18,IF(AL18="99010825011997",AS18))) -> 1.6367812 | U18: =IF(T18="no corresponde",0,+S18*T18) -> 0 | W18: =+V18*AK18+((+R18+U18)*1.3195) -> 14.844375 | X18: =IFERROR(VLOOKUP($I18,Trabajadores!$C$2:$AS$1684,42,FALSE)," ") -> ALGADI | Y18: =IFERROR(VLOOKUP($I18,Trabajadores!$C$2:$AS$1684,40,FALSE)," ") -> 110030 | Z18: =IFERROR(VLOOKUP(Y18,Centros!$X$2:$Y$228,2,FALSE)," ") -> COLEGIO INMACULADA | AA18: 45905 | AB18: No sustitución de Mildred Mogollón | AC18: =IFERROR(VLOOKUP(H18,Centros!$AI$2:$AN$10,6,FALSE),0) -> 72 | AD18: =IF(AC18=70,R18,0) -> 0 | AE18: =IF(AC18=72,R18,0) -> 11.25 | AF18: =IF(AC18=73,+R18,0) -> 0 | AG18: =+U18 -> 0 | AH18: =IFERROR(VLOOKUP($I18,Trabajadores!$C$3:$AT$1684,44,FALSE),0) -> 19228 | AI18: =IFERROR(VLOOKUP($I18,Trabajadores!$C$3:$AT$1684,2,FALSE),0) -> 202 | AJ18: =IFERROR(VLOOKUP($I18,Trabajadores!$C$3:$AY$1270,21,FALSE),0) -> 36 | AK18: =IFERROR(VLOOKUP($I18,Trabajadores!$C$3:$AN$1684,38,FALSE),0) -> 8.2275 | AL18: =IFERROR(VLOOKUP($I18,Trabajadores!$C$3:$AN$1684,28,FALSE),0) -> 99100165012016 | AM18: =IFERROR(VLOOKUP($I18,Trabajadores!$C$3:$AN$1684,19,FALSE),0) -> h ASL | AN18: =IFERROR(IF($J18="algadi",VLOOKUP($K18,Centros!$AB$2:$AD$142,2,FALSE),VLOOKUP($K18,Centros!$AB$143:$AD$282,2,FALSE)),0) -> 19228 | AO18: =IFERROR(IF($J18="algadi",VLOOKUP($K18,Centros!$AB$2:$AD$142,3,FALSE),VLOOKUP($K18,Centros!$AB$143:$AD$222,3,FALSE)),0) -> 36 | AQ18: =IFERROR(VLOOKUP($AM18,Centros!$AR$2:$AS$405,2,FALSE),0) -> 1.6367812 | AR18: =IFERROR(VLOOKUP($AM18,Centros!$AZ$2:$BA$6,2,FALSE),0) -> 0 | AS18: =IFERROR(VLOOKUP($AM18,Centros!$BE$2:$BF$6,2,FALSE),0) -> 0 | BD18: =+X18 -> ALGADI | BE18: INCIDENCIA | BF18: =+E18 -> 9-SEPTIEMBRE | BG18: =+Y18 -> 110030 | BH18: =VLOOKUP(Y18,Hoja1!$A$2:$O$599,14,FALSE) -> 110030 | BI18: =VLOOKUP(BH18,Hoja1!$A$2:$O$599,2,FALSE) -> COLEGIO INMACULADA | BJ18: =+I18 -> CERCAS LORENZO, AURORA B. | BK18: =VLOOKUP(BJ18,Trabajadores!$C$3:$AN$3285,14,FALSE) -> 300 | BL18: =VLOOKUP($BJ18,Trabajadores!$C$3:$AN$3285,19,FALSE) -> h ASL | BM18: =VLOOKUP($BJ18,Trabajadores!$C$3:$AN$3285,16,FALSE) -> 100 | BN18: =IF($G18="010 Restauración",100%,0%) -> 1 | BO18: =IF($G18="020 Limpieza",100%,0%) -> 0 | BP18: =+BN18+BO18 -> 1 | BR18: =-W18 -> -14.844375 | BV18: =+J18 -> ALGADI | BW18: INCIDENCIA | BX18: =+E18 -> 9-SEPTIEMBRE | BY18: =+K18 -> 110030 | BZ18: =VLOOKUP(BY18,Hoja1!$A$2:$O$599,14,FALSE) -> 110030 | CA18: =VLOOKUP(BZ18,Hoja1!$A$2:$O$599,2,FALSE) -> COLEGIO INMACULADA | CB18: =+H18 -> Permiso retribuido | CC18: 888 | CD18: =+BW18 -> INCIDENCIA | CJ18: =+W18 -> 14.844375
D19: 945 | E19: 9-SEPTIEMBRE | F19: NO | G19: 010 Restauración | H19: Festivos y Fines de Semana | I19: CERCAS LORENZO, AURORA B. | J19: ALGADI | K19: 110030 | L19: =IF(W19>0,IF(OR(E19="",F19="",G19="",H19="",I19="",J19="",K19=""),"faltan datos","ok")," ") -> ok | M19: =IFERROR(VLOOKUP(K19,Centros!$E$2:$G$340,2,FALSE)," ") -> COLEGIO INMACULADA | N19: =IF(J19=" "," ",IF(J19=X19," ","Emp Orig/dest. Distinta")) | O19: =IFERROR(VLOOKUP($I19,Trabajadores!$C$3:$AF$1684,19,FALSE)," ") -> h ASL | P19: 1.25 | Q19: 9 | R19: =+P19*Q19 -> 11.25 | T19: =IF(AL19="99100165012016",AQ19,IF(AL19="28009435011996",AR19,IF(AL19="99010825011997",AS19))) -> 1.6367812 | U19: =IF(T19="no corresponde",0,+S19*T19) -> 0 | W19: =+V19*AK19+((+R19+U19)*1.3195) -> 14.844375 | X19: =IFERROR(VLOOKUP($I19,Trabajadores!$C$2:$AS$1684,42,FALSE)," ") -> ALGADI | Y19: =IFERROR(VLOOKUP($I19,Trabajadores!$C$2:$AS$1684,40,FALSE)," ") -> 110030 | Z19: =IFERROR(VLOOKUP(Y19,Centros!$X$2:$Y$228,2,FALSE)," ") -> COLEGIO INMACULADA | AA19: 45927 | AB19: ASL Sábado comunidad | AC19: =IFERROR(VLOOKUP(H19,Centros!$AI$2:$AN$10,6,FALSE),0) -> 70 | AD19: =IF(AC19=70,R19,0) -> 11.25 | AE19: =IF(AC19=72,R19,0) -> 0 | AF19: =IF(AC19=73,+R19,0) -> 0 | AG19: =+U19 -> 0 | AH19: =IFERROR(VLOOKUP($I19,Trabajadores!$C$3:$AT$1684,44,FALSE),0) -> 19228 | AI19: =IFERROR(VLOOKUP($I19,Trabajadores!$C$3:$AT$1684,2,FALSE),0) -> 202 | AJ19: =IFERROR(VLOOKUP($I19,Trabajadores!$C$3:$AY$1270,21,FALSE),0) -> 36 | AK19: =IFERROR(VLOOKUP($I19,Trabajadores!$C$3:$AN$1684,38,FALSE),0) -> 8.2275 | AL19: =IFERROR(VLOOKUP($I19,Trabajadores!$C$3:$AN$1684,28,FALSE),0) -> 99100165012016 | AM19: =IFERROR(VLOOKUP($I19,Trabajadores!$C$3:$AN$1684,19,FALSE),0) -> h ASL | AN19: =IFERROR(IF($J19="algadi",VLOOKUP($K19,Centros!$AB$2:$AD$142,2,FALSE),VLOOKUP($K19,Centros!$AB$143:$AD$282,2,FALSE)),0) -> 19228 | AO19: =IFERROR(IF($J19="algadi",VLOOKUP($K19,Centros!$AB$2:$AD$142,3,FALSE),VLOOKUP($K19,Centros!$AB$143:$AD$222,3,FALSE)),0) -> 36 | AQ19: =IFERROR(VLOOKUP($AM19,Centros!$AR$2:$AS$405,2,FALSE),0) -> 1.6367812 | AR19: =IFERROR(VLOOKUP($AM19,Centros!$AZ$2:$BA$6,2,FALSE),0) -> 0 | AS19: =IFERROR(VLOOKUP($AM19,Centros!$BE$2:$BF$6,2,FALSE),0) -> 0 | BD19: =+X19 -> ALGADI | BE19: INCIDENCIA | BF19: =+E19 -> 9-SEPTIEMBRE | BG19: =+Y19 -> 110030 | BH19: =VLOOKUP(Y19,Hoja1!$A$2:$O$599,14,FALSE) -> 110030 | BI19: =VLOOKUP(BH19,Hoja1!$A$2:$O$599,2,FALSE) -> COLEGIO INMACULADA | BJ19: =+I19 -> CERCAS LORENZO, AURORA B. | BK19: =VLOOKUP(BJ19,Trabajadores!$C$3:$AN$3285,14,FALSE) -> 300 | BL19: =VLOOKUP($BJ19,Trabajadores!$C$3:$AN$3285,19,FALSE) -> h ASL | BM19: =VLOOKUP($BJ19,Trabajadores!$C$3:$AN$3285,16,FALSE) -> 100 | BN19: =IF($G19="010 Restauración",100%,0%) -> 1 | BO19: =IF($G19="020 Limpieza",100%,0%) -> 0 | BP19: =+BN19+BO19 -> 1 | BR19: =-W19 -> -14.844375 | BV19: =+J19 -> ALGADI | BW19: INCIDENCIA | BX19: =+E19 -> 9-SEPTIEMBRE | BY19: =+K19 -> 110030 | BZ19: =VLOOKUP(BY19,Hoja1!$A$2:$O$599,14,FALSE) -> 110030 | CA19: =VLOOKUP(BZ19,Hoja1!$A$2:$O$599,2,FALSE) -> COLEGIO INMACULADA | CB19: =+H19 -> Festivos y Fines de Semana | CC19: 888 | CD19: =+BW19 -> INCIDENCIA | CJ19: =+W19 -> 14.844375
D20: 945 | E20: 9-SEPTIEMBRE | F20: SI | G20: 010 Restauración | H20: Festivos y Fines de Semana | I20: CRUZ MALLQUI, MILAGROS G | J20: ALGADI | K20: 340085 | L20: =IF(W20>0,IF(OR(E20="",F20="",G20="",H20="",I20="",J20="",K20=""),"faltan datos","ok")," ") -> ok | M20: =IFERROR(VLOOKUP(K20,Centros!$E$2:$G$340,2,FALSE)," ") -> CASA MISIONERAS CLARETIANAS | N20: =IF(J20=" "," ",IF(J20=X20," ","Emp Orig/dest. Distinta")) | O20: =IFERROR(VLOOKUP($I20,Trabajadores!$C$3:$AF$1684,19,FALSE)," ") -> Cociner@ | P20: 1 | Q20: 80 | R20: =+P20*Q20 -> 80 | T20: =IF(AL20="99100165012016",AQ20,IF(AL20="28009435011996",AR20,IF(AL20="99010825011997",AS20))) -> 1.7437656 | U20: =IF(T20="no corresponde",0,+S20*T20) -> 0 | W20: =+V20*AK20+((+R20+U20)*1.3195) -> 105.56 | X20: =IFERROR(VLOOKUP($I20,Trabajadores!$C$2:$AS$1684,42,FALSE)," ") -> ALGADI | Y20: =IFERROR(VLOOKUP($I20,Trabajadores!$C$2:$AS$1684,40,FALSE)," ") -> 340085 | Z20: =IFERROR(VLOOKUP(Y20,Centros!$X$2:$Y$228,2,FALSE)," ") -> CASA MISIONERAS CLARETIANAS | AA20: 45872 | AB20: Domingo Ángela Figuera | AC20: =IFERROR(VLOOKUP(H20,Centros!$AI$2:$AN$10,6,FALSE),0) -> 70 | AD20: =IF(AC20=70,R20,0) -> 80 | AE20: =IF(AC20=72,R20,0) -> 0 | AF20: =IF(AC20=73,+R20,0) -> 0 | AG20: =+U20 -> 0 | AH20: =IFERROR(VLOOKUP($I20,Trabajadores!$C$3:$AT$1684,44,FALSE),0) -> 19228 | AI20: =IFERROR(VLOOKUP($I20,Trabajadores!$C$3:$AT$1684,2,FALSE),0) -> 832 | AJ20: =IFERROR(VLOOKUP($I20,Trabajadores!$C$3:$AY$1270,21,FALSE),0) -> 82 | AK20: =IFERROR(VLOOKUP($I20,Trabajadores!$C$3:$AN$1684,38,FALSE),0) -> 8.26875 | AL20: =IFERROR(VLOOKUP($I20,Trabajadores!$C$3:$AN$1684,28,FALSE),0) -> 99100165012016 | AM20: =IFERROR(VLOOKUP($I20,Trabajadores!$C$3:$AN$1684,19,FALSE),0) -> Cociner@ | AN20: =IFERROR(IF($J20="algadi",VLOOKUP($K20,Centros!$AB$2:$AD$142,2,FALSE),VLOOKUP($K20,Centros!$AB$143:$AD$282,2,FALSE)),0) -> 0 | AO20: =IFERROR(IF($J20="algadi",VLOOKUP($K20,Centros!$AB$2:$AD$142,3,FALSE),VLOOKUP($K20,Centros!$AB$143:$AD$222,3,FALSE)),0) -> 0 | AQ20: =IFERROR(VLOOKUP($AM20,Centros!$AR$2:$AS$405,2,FALSE),0) -> 1.7437656 | AR20: =IFERROR(VLOOKUP($AM20,Centros!$AZ$2:$BA$6,2,FALSE),0) -> 2.32225 | AS20: =IFERROR(VLOOKUP($AM20,Centros!$BE$2:$BF$6,2,FALSE),0) -> 0 | BD20: =+X20 -> ALGADI | BE20: INCIDENCIA | BF20: =+E20 -> 9-SEPTIEMBRE | BG20: =+Y20 -> 340085 | BH20: =VLOOKUP(Y20,Hoja1!$A$2:$O$599,14,FALSE) -> 340085 | BI20: =VLOOKUP(BH20,Hoja1!$A$2:$O$599,2,FALSE) -> CASA MISIONERAS CLARETIANAS | BJ20: =+I20 -> CRUZ MALLQUI, MILAGROS G | BK20: =VLOOKUP(BJ20,Trabajadores!$C$3:$AN$3285,14,FALSE) -> 100 | BL20: =VLOOKUP($BJ20,Trabajadores!$C$3:$AN$3285,19,FALSE) -> Cociner@ | BM20: =VLOOKUP($BJ20,Trabajadores!$C$3:$AN$3285,16,FALSE) -> 100 | BN20: =IF($G20="010 Restauración",100%,0%) -> 1 | BO20: =IF($G20="020 Limpieza",100%,0%) -> 0 | BP20: =+BN20+BO20 -> 1 | BR20: =-W20 -> -105.56 | BV20: =+J20 -> ALGADI | BW20: INCIDENCIA | BX20: =+E20 -> 9-SEPTIEMBRE | BY20: =+K20 -> 340085 | BZ20: =VLOOKUP(BY20,Hoja1!$A$2:$O$599,14,FALSE) -> 340085 | CA20: =VLOOKUP(BZ20,Hoja1!$A$2:$O$599,2,FALSE) -> CASA MISIONERAS CLARETIANAS | CB20: =+H20 -> Festivos y Fines de Semana | CC20: 888 | CD20: =+BW20 -> INCIDENCIA | CJ20: =+W20 -> 105.56
D21: 945 | E21: 9-SEPTIEMBRE | F21: NO | G21: 010 Restauración | H21: Festivos y Fines de Semana | I21: CUATIN ZAPATA, ELVIA MARI | J21: ALGADI | K21: 400020 | L21: =IF(W21>0,IF(OR(E21="",F21="",G21="",H21="",I21="",J21="",K21=""),"faltan datos","ok")," ") -> ok | M21: =IFERROR(VLOOKUP(K21,Centros!$E$2:$G$340,2,FALSE)," ") -> HOGAR INFANTIL LUIS AMIGO | N21: =IF(J21=" "," ",IF(J21=X21," ","Emp Orig/dest. Distinta")) | O21: =IFERROR(VLOOKUP($I21,Trabajadores!$C$3:$AF$1684,19,FALSE)," ") -> Cociner@ | P21: 1 | Q21: 45 | R21: =+P21*Q21 -> 45 | T21: =IF(AL21="99100165012016",AQ21,IF(AL21="28009435011996",AR21,IF(AL21="99010825011997",AS21))) -> 1.7437656 | U21: =IF(T21="no corresponde",0,+S21*T21) -> 0 | W21: =+V21*AK21+((+R21+U21)*1.3195) -> 59.3775 | X21: =IFERROR(VLOOKUP($I21,Trabajadores!$C$2:$AS$1684,42,FALSE)," ") -> ALGADI | Y21: =IFERROR(VLOOKUP($I21,Trabajadores!$C$2:$AS$1684,40,FALSE)," ") -> 340011 | Z21: =IFERROR(VLOOKUP(Y21,Centros!$X$2:$Y$228,2,FALSE)," ") -> CLARETIANOS CORAZON DE MARIA | AA21: 45907 | AB21: Domingo Luis amigó | AC21: =IFERROR(VLOOKUP(H21,Centros!$AI$2:$AN$10,6,FALSE),0) -> 70 | AD21: =IF(AC21=70,R21,0) -> 45 | AE21: =IF(AC21=72,R21,0) -> 0 | AF21: =IF(AC21=73,+R21,0) -> 0 | AG21: =+U21 -> 0 | AH21: =IFERROR(VLOOKUP($I21,Trabajadores!$C$3:$AT$1684,44,FALSE),0) -> 19228 | AI21: =IFERROR(VLOOKUP($I21,Trabajadores!$C$3:$AT$1684,2,FALSE),0) -> 687 | AJ21: =IFERROR(VLOOKUP($I21,Trabajadores!$C$3:$AY$1270,21,FALSE),0) -> 59 | AK21: =IFERROR(VLOOKUP($I21,Trabajadores!$C$3:$AN$1684,38,FALSE),0) -> 7.8181818 | AL21: =IFERROR(VLOOKUP($I21,Trabajadores!$C$3:$AN$1684,28,FALSE),0) -> 99100165012016 | AM21: =IFERROR(VLOOKUP($I21,Trabajadores!$C$3:$AN$1684,19,FALSE),0) -> Cociner@ | AN21: =IFERROR(IF($J21="algadi",VLOOKUP($K21,Centros!$AB$2:$AD$142,2,FALSE),VLOOKUP($K21,Centros!$AB$143:$AD$282,2,FALSE)),0) -> 5027 | AO21: =IFERROR(IF($J21="algadi",VLOOKUP($K21,Centros!$AB$2:$AD$142,3,FALSE),VLOOKUP($K21,Centros!$AB$143:$AD$222,3,FALSE)),0) -> 68 | AQ21: =IFERROR(VLOOKUP($AM21,Centros!$AR$2:$AS$405,2,FALSE),0) -> 1.7437656 | AR21: =IFERROR(VLOOKUP($AM21,Centros!$AZ$2:$BA$6,2,FALSE),0) -> 2.32225 | AS21: =IFERROR(VLOOKUP($AM21,Centros!$BE$2:$BF$6,2,FALSE),0) -> 0 | BD21: =+X21 -> ALGADI | BE21: INCIDENCIA | BF21: =+E21 -> 9-SEPTIEMBRE | BG21: =+Y21 -> 340011 | BH21: =VLOOKUP(Y21,Hoja1!$A$2:$O$599,14,FALSE) -> 340011 | BI21: =VLOOKUP(BH21,Hoja1!$A$2:$O$599,2,FALSE) -> CLARETIANOS CORAZON DE MARIA | BJ21: =+I21 -> CUATIN ZAPATA, ELVIA MARI | BK21: =VLOOKUP(BJ21,Trabajadores!$C$3:$AN$3285,14,FALSE) -> 200 | BL21: =VLOOKUP($BJ21,Trabajadores!$C$3:$AN$3285,19,FALSE) -> Cociner@ | BM21: =VLOOKUP($BJ21,Trabajadores!$C$3:$AN$3285,16,FALSE) -> 27.5 | BN21: =IF($G21="010 Restauración",100%,0%) -> 1 | BO21: =IF($G21="020 Limpieza",100%,0%) -> 0 | BP21: =+BN21+BO21 -> 1 | BR21: =-W21 -> -59.3775 | BV21: =+J21 -> ALGADI | BW21: INCIDENCIA | BX21: =+E21 -> 9-SEPTIEMBRE | BY21: =+K21 -> 400020 | BZ21: =VLOOKUP(BY21,Hoja1!$A$2:$O$599,14,FALSE) -> 400020 | CA21: =VLOOKUP(BZ21,Hoja1!$A$2:$O$599,2,FALSE) -> HOGAR INFANTIL LUIS AMIGO | CB21: =+H21 -> Festivos y Fines de Semana | CC21: 888 | CD21: =+BW21 -> INCIDENCIA | CJ21: =+W21 -> 59.3775
D22: 945 | E22: 9-SEPTIEMBRE | F22: NO | G22: 010 Restauración | H22: Festivos y Fines de Semana | I22: CUATIN ZAPATA, ELVIA MARI | J22: ALGADI | K22: 400020 | L22: =IF(W22>0,IF(OR(E22="",F22="",G22="",H22="",I22="",J22="",K22=""),"faltan datos","ok")," ") -> ok | M22: =IFERROR(VLOOKUP(K22,Centros!$E$2:$G$340,2,FALSE)," ") -> HOGAR INFANTIL LUIS AMIGO | N22: =IF(J22=" "," ",IF(J22=X22," ","Emp Orig/dest. Distinta")) | O22: =IFERROR(VLOOKUP($I22,Trabajadores!$C$3:$AF$1684,19,FALSE)," ") -> Cociner@ | P22: 9 | Q22: 9 | R22: =+P22*Q22 -> 81 | T22: =IF(AL22="99100165012016",AQ22,IF(AL22="28009435011996",AR22,IF(AL22="99010825011997",AS22))) -> 1.7437656 | U22: =IF(T22="no corresponde",0,+S22*T22) -> 0 | W22: =+V22*AK22+((+R22+U22)*1.3195) -> 106.8795 | X22: =IFERROR(VLOOKUP($I22,Trabajadores!$C$2:$AS$1684,42,FALSE)," ") -> ALGADI | Y22: =IFERROR(VLOOKUP($I22,Trabajadores!$C$2:$AS$1684,40,FALSE)," ") -> 340011 | Z22: =IFERROR(VLOOKUP(Y22,Centros!$X$2:$Y$228,2,FALSE)," ") -> CLARETIANOS CORAZON DE MARIA | AA22: 17, 18 y 19 septiembre | AB22: Miercoles a viernes 3 horas limpieza | AC22: =IFERROR(VLOOKUP(H22,Centros!$AI$2:$AN$10,6,FALSE),0) -> 70 | AD22: =IF(AC22=70,R22,0) -> 81 | AE22: =IF(AC22=72,R22,0) -> 0 | AF22: =IF(AC22=73,+R22,0) -> 0 | AG22: =+U22 -> 0 | AH22: =IFERROR(VLOOKUP($I22,Trabajadores!$C$3:$AT$1684,44,FALSE),0) -> 19228 | AI22: =IFERROR(VLOOKUP($I22,Trabajadores!$C$3:$AT$1684,2,FALSE),0) -> 687 | AJ22: =IFERROR(VLOOKUP($I22,Trabajadores!$C$3:$AY$1270,21,FALSE),0) -> 59 | AK22: =IFERROR(VLOOKUP($I22,Trabajadores!$C$3:$AN$1684,38,FALSE),0) -> 7.8181818 | AL22: =IFERROR(VLOOKUP($I22,Trabajadores!$C$3:$AN$1684,28,FALSE),0) -> 99100165012016 | AM22: =IFERROR(VLOOKUP($I22,Trabajadores!$C$3:$AN$1684,19,FALSE),0) -> Cociner@ | AN22: =IFERROR(IF($J22="algadi",VLOOKUP($K22,Centros!$AB$2:$AD$142,2,FALSE),VLOOKUP($K22,Centros!$AB$143:$AD$282,2,FALSE)),0) -> 5027 | AO22: =IFERROR(IF($J22="algadi",VLOOKUP($K22,Centros!$AB$2:$AD$142,3,FALSE),VLOOKUP($K22,Centros!$AB$143:$AD$222,3,FALSE)),0) -> 68 | AQ22: =IFERROR(VLOOKUP($AM22,Centros!$AR$2:$AS$405,2,FALSE),0) -> 1.7437656 | AR22: =IFERROR(VLOOKUP($AM22,Centros!$AZ$2:$BA$6,2,FALSE),0) -> 2.32225 | AS22: =IFERROR(VLOOKUP($AM22,Centros!$BE$2:$BF$6,2,FALSE),0) -> 0 | BD22: =+X22 -> ALGADI | BE22: INCIDENCIA | BF22: =+E22 -> 9-SEPTIEMBRE | BG22: =+Y22 -> 340011 | BH22: =VLOOKUP(Y22,Hoja1!$A$2:$O$599,14,FALSE) -> 340011 | BI22: =VLOOKUP(BH22,Hoja1!$A$2:$O$599,2,FALSE) -> CLARETIANOS CORAZON DE MARIA | BJ22: =+I22 -> CUATIN ZAPATA, ELVIA MARI | BK22: =VLOOKUP(BJ22,Trabajadores!$C$3:$AN$3285,14,FALSE) -> 200 | BL22: =VLOOKUP($BJ22,Trabajadores!$C$3:$AN$3285,19,FALSE) -> Cociner@ | BM22: =VLOOKUP($BJ22,Trabajadores!$C$3:$AN$3285,16,FALSE) -> 27.5 | BN22: =IF($G22="010 Restauración",100%,0%) -> 1 | BO22: =IF($G22="020 Limpieza",100%,0%) -> 0 | BP22: =+BN22+BO22 -> 1 | BR22: =-W22 -> -106.8795 | BV22: =+J22 -> ALGADI | BW22: INCIDENCIA | BX22: =+E22 -> 9-SEPTIEMBRE | BY22: =+K22 -> 400020 | BZ22: =VLOOKUP(BY22,Hoja1!$A$2:$O$599,14,FALSE) -> 400020 | CA22: =VLOOKUP(BZ22,Hoja1!$A$2:$O$599,2,FALSE) -> HOGAR INFANTIL LUIS AMIGO | CB22: =+H22 -> Festivos y Fines de Semana | CC22: 888 | CD22: =+BW22 -> INCIDENCIA | CJ22: =+W22 -> 106.8795
D23: 945 | E23: 9-SEPTIEMBRE | F23: NO | G23: 010 Restauración | H23: Festivos y Fines de Semana | I23: CUATIN ZAPATA, ELVIA MARI | J23: ALGADI | K23: 400020 | L23: =IF(W23>0,IF(OR(E23="",F23="",G23="",H23="",I23="",J23="",K23=""),"faltan datos","ok")," ") -> ok | M23: =IFERROR(VLOOKUP(K23,Centros!$E$2:$G$340,2,FALSE)," ") -> HOGAR INFANTIL LUIS AMIGO | N23: =IF(J23=" "," ",IF(J23=X23," ","Emp Orig/dest. Distinta")) | O23: =IFERROR(VLOOKUP($I23,Trabajadores!$C$3:$AF$1684,19,FALSE)," ") -> Cociner@ | P23: 12 | Q23: 11 | R23: =+P23*Q23 -> 132 | T23: =IF(AL23="99100165012016",AQ23,IF(AL23="28009435011996",AR23,IF(AL23="99010825011997",AS23))) -> 1.7437656 | U23: =IF(T23="no corresponde",0,+S23*T23) -> 0 | W23: =+V23*AK23+((+R23+U23)*1.3195) -> 174.174 | X23: =IFERROR(VLOOKUP($I23,Trabajadores!$C$2:$AS$1684,42,FALSE)," ") -> ALGADI | Y23: =IFERROR(VLOOKUP($I23,Trabajadores!$C$2:$AS$1684,40,FALSE)," ") -> 340011 | Z23: =IFERROR(VLOOKUP(Y23,Centros!$X$2:$Y$228,2,FALSE)," ") -> CLARETIANOS CORAZON DE MARIA | AA23: 17, 18 y 19 septiembre | AB23: Miercoles a viernes 4 horas cocina | AC23: =IFERROR(VLOOKUP(H23,Centros!$AI$2:$AN$10,6,FALSE),0) -> 70 | AD23: =IF(AC23=70,R23,0) -> 132 | AE23: =IF(AC23=72,R23,0) -> 0 | AF23: =IF(AC23=73,+R23,0) -> 0 | AG23: =+U23 -> 0 | AH23: =IFERROR(VLOOKUP($I23,Trabajadores!$C$3:$AT$1684,44,FALSE),0) -> 19228 | AI23: =IFERROR(VLOOKUP($I23,Trabajadores!$C$3:$AT$1684,2,FALSE),0) -> 687 | AJ23: =IFERROR(VLOOKUP($I23,Trabajadores!$C$3:$AY$1270,21,FALSE),0) -> 59 | AK23: =IFERROR(VLOOKUP($I23,Trabajadores!$C$3:$AN$1684,38,FALSE),0) -> 7.8181818 | AL23: =IFERROR(VLOOKUP($I23,Trabajadores!$C$3:$AN$1684,28,FALSE),0) -> 99100165012016 | AM23: =IFERROR(VLOOKUP($I23,Trabajadores!$C$3:$AN$1684,19,FALSE),0) -> Cociner@ | AN23: =IFERROR(IF($J23="algadi",VLOOKUP($K23,Centros!$AB$2:$AD$142,2,FALSE),VLOOKUP($K23,Centros!$AB$143:$AD$282,2,FALSE)),0) -> 5027 | AO23: =IFERROR(IF($J23="algadi",VLOOKUP($K23,Centros!$AB$2:$AD$142,3,FALSE),VLOOKUP($K23,Centros!$AB$143:$AD$222,3,FALSE)),0) -> 68 | AQ23: =IFERROR(VLOOKUP($AM23,Centros!$AR$2:$AS$405,2,FALSE),0) -> 1.7437656 | AR23: =IFERROR(VLOOKUP($AM23,Centros!$AZ$2:$BA$6,2,FALSE),0) -> 2.32225 | AS23: =IFERROR(VLOOKUP($AM23,Centros!$BE$2:$BF$6,2,FALSE),0) -> 0 | BD23: =+X23 -> ALGADI | BE23: INCIDENCIA | BF23: =+E23 -> 9-SEPTIEMBRE | BG23: =+Y23 -> 340011 | BH23: =VLOOKUP(Y23,Hoja1!$A$2:$O$599,14,FALSE) -> 340011 | BI23: =VLOOKUP(BH23,Hoja1!$A$2:$O$599,2,FALSE) -> CLARETIANOS CORAZON DE MARIA | BJ23: =+I23 -> CUATIN ZAPATA, ELVIA MARI | BK23: =VLOOKUP(BJ23,Trabajadores!$C$3:$AN$3285,14,FALSE) -> 200 | BL23: =VLOOKUP($BJ23,Trabajadores!$C$3:$AN$3285,19,FALSE) -> Cociner@ | BM23: =VLOOKUP($BJ23,Trabajadores!$C$3:$AN$3285,16,FALSE) -> 27.5 | BN23: =IF($G23="010 Restauración",100%,0%) -> 1 | BO23: =IF($G23="020 Limpieza",100%,0%) -> 0 | BP23: =+BN23+BO23 -> 1 | BR23: =-W23 -> -174.174 | BV23: =+J23 -> ALGADI | BW23: INCIDENCIA | BX23: =+E23 -> 9-SEPTIEMBRE | BY23: =+K23 -> 400020 | BZ23: =VLOOKUP(BY23,Hoja1!$A$2:$O$599,14,FALSE) -> 400020 | CA23: =VLOOKUP(BZ23,Hoja1!$A$2:$O$599,2,FALSE) -> HOGAR INFANTIL LUIS AMIGO | CB23: =+H23 -> Festivos y Fines de Semana | CC23: 888 | CD23: =+BW23 -> INCIDENCIA | CJ23: =+W23 -> 174.174
D24: 945 | E24: 9-SEPTIEMBRE | F24: NO | G24: 010 Restauración | H24: Festivos y Fines de Semana | I24: DELGADO MORENO, JULIA | J24: ALGADI | K24: 110065 | L24: =IF(W24>0,IF(OR(E24="",F24="",G24="",H24="",I24="",J24="",K24=""),"faltan datos","ok")," ") -> ok | M24: =IFERROR(VLOOKUP(K24,Centros!$E$2:$G$340,2,FALSE)," ") -> COLEGIO SANTA RITA | N24: =IF(J24=" "," ",IF(J24=X24," ","Emp Orig/dest. Distinta")) | O24: =IFERROR(VLOOKUP($I24,Trabajadores!$C$3:$AF$1684,19,FALSE)," ") -> h ASL | P24: 4 | Q24: 72.42 | R24: =+P24*Q24 -> 289.68 | T24: =IF(AL24="99100165012016",AQ24,IF(AL24="28009435011996",AR24,IF(AL24="99010825011997",AS24))) -> 1.6367812 | U24: =IF(T24="no corresponde",0,+S24*T24) -> 0 | W24: =+V24*AK24+((+R24+U24)*1.3195) -> 382.23276 | X24: =IFERROR(VLOOKUP($I24,Trabajadores!$C$2:$AS$1684,42,FALSE)," ") -> ALGADI | Y24: =IFERROR(VLOOKUP($I24,Trabajadores!$C$2:$AS$1684,40,FALSE)," ") -> 110065 | Z24: =IFERROR(VLOOKUP(Y24,Centros!$X$2:$Y$228,2,FALSE)," ") -> COLEGIO SANTA RITA | AA24: 13,14, 27 y 28 septiembre | AB24: Fines de semana Santa Rita | AC24: =IFERROR(VLOOKUP(H24,Centros!$AI$2:$AN$10,6,FALSE),0) -> 70 | AD24: =IF(AC24=70,R24,0) -> 289.68 | AE24: =IF(AC24=72,R24,0) -> 0 | AF24: =IF(AC24=73,+R24,0) -> 0 | AG24: =+U24 -> 0 | AH24: =IFERROR(VLOOKUP($I24,Trabajadores!$C$3:$AT$1684,44,FALSE),0) -> 19228 | AI24: =IFERROR(VLOOKUP($I24,Trabajadores!$C$3:$AT$1684,2,FALSE),0) -> 45 | AJ24: =IFERROR(VLOOKUP($I24,Trabajadores!$C$3:$AY$1270,21,FALSE),0) -> 6 | AK24: =IFERROR(VLOOKUP($I24,Trabajadores!$C$3:$AN$1684,38,FALSE),0) -> 9.7416667 | AL24: =IFERROR(VLOOKUP($I24,Trabajadores!$C$3:$AN$1684,28,FALSE),0) -> 99100165012016 | AM24: =IFERROR(VLOOKUP($I24,Trabajadores!$C$3:$AN$1684,19,FALSE),0) -> h ASL | AN24: =IFERROR(IF($J24="algadi",VLOOKUP($K24,Centros!$AB$2:$AD$142,2,FALSE),VLOOKUP($K24,Centros!$AB$143:$AD$282,2,FALSE)),0) -> 5027 | AO24: =IFERROR(IF($J24="algadi",VLOOKUP($K24,Centros!$AB$2:$AD$142,3,FALSE),VLOOKUP($K24,Centros!$AB$143:$AD$222,3,FALSE)),0) -> 33 | AQ24: =IFERROR(VLOOKUP($AM24,Centros!$AR$2:$AS$405,2,FALSE),0) -> 1.6367812 | AR24: =IFERROR(VLOOKUP($AM24,Centros!$AZ$2:$BA$6,2,FALSE),0) -> 0 | AS24: =IFERROR(VLOOKUP($AM24,Centros!$BE$2:$BF$6,2,FALSE),0) -> 0 | BD24: =+X24 -> ALGADI | BE24: INCIDENCIA | BF24: =+E24 -> 9-SEPTIEMBRE | BG24: =+Y24 -> 110065 | BH24: =VLOOKUP(Y24,Hoja1!$A$2:$O$599,14,FALSE) -> 110065 | BI24: =VLOOKUP(BH24,Hoja1!$A$2:$O$599,2,FALSE) -> COLEGIO SANTA RITA | BJ24: =+I24 -> DELGADO MORENO, JULIA | BK24: =VLOOKUP(BJ24,Trabajadores!$C$3:$AN$3285,14,FALSE) -> 300 | BL24: =VLOOKUP($BJ24,Trabajadores!$C$3:$AN$3285,19,FALSE) -> h ASL | BM24: =VLOOKUP($BJ24,Trabajadores!$C$3:$AN$3285,16,FALSE) -> 75 | BN24: =IF($G24="010 Restauración",100%,0%) -> 1 | BO24: =IF($G24="020 Limpieza",100%,0%) -> 0 | BP24: =+BN24+BO24 -> 1 | BR24: =-W24 -> -382.23276 | BV24: =+J24 -> ALGADI | BW24: INCIDENCIA | BX24: =+E24 -> 9-SEPTIEMBRE | BY24: =+K24 -> 110065 | BZ24: =VLOOKUP(BY24,Hoja1!$A$2:$O$599,14,FALSE) -> 110065 | CA24: =VLOOKUP(BZ24,Hoja1!$A$2:$O$599,2,FALSE) -> COLEGIO SANTA RITA | CB24: =+H24 -> Festivos y Fines de Semana | CC24: 888 | CD24: =+BW24 -> INCIDENCIA | CJ24: =+W24 -> 382.23276
D25: 945 | E25: 9-SEPTIEMBRE | F25: NO | G25: 010 Restauración | H25: Permiso retribuido | I25: DIAZ HELLIN BELTRAN, M MERCEDES | J25: ALGADI | K25: 110030 | L25: =IF(W25>0,IF(OR(E25="",F25="",G25="",H25="",I25="",J25="",K25=""),"faltan datos","ok")," ") -> ok | M25: =IFERROR(VLOOKUP(K25,Centros!$E$2:$G$340,2,FALSE)," ") -> COLEGIO INMACULADA | N25: =IF(J25=" "," ",IF(J25=X25," ","Emp Orig/dest. Distinta")) | O25: =IFERROR(VLOOKUP($I25,Trabajadores!$C$3:$AF$1684,19,FALSE)," ") -> h ASL | P25: 1.25 | Q25: 9 | R25: =+P25*Q25 -> 11.25 | T25: =IF(AL25="99100165012016",AQ25,IF(AL25="28009435011996",AR25,IF(AL25="99010825011997",AS25))) -> 1.6367812 | U25: =IF(T25="no corresponde",0,+S25*T25) -> 0 | W25: =+V25*AK25+((+R25+U25)*1.3195) -> 14.844375 | X25: =IFERROR(VLOOKUP($I25,Trabajadores!$C$2:$AS$1684,42,FALSE)," ") -> ALGADI | Y25: =IFERROR(VLOOKUP($I25,Trabajadores!$C$2:$AS$1684,40,FALSE)," ") -> 110030 | Z25: =IFERROR(VLOOKUP(Y25,Centros!$X$2:$Y$228,2,FALSE)," ") -> COLEGIO INMACULADA | AA25: 45905 | AB25: No sustitución de Mildred Mogollón | AC25: =IFERROR(VLOOKUP(H25,Centros!$AI$2:$AN$10,6,FALSE),0) -> 72 | AD25: =IF(AC25=70,R25,0) -> 0 | AE25: =IF(AC25=72,R25,0) -> 11.25 | AF25: =IF(AC25=73,+R25,0) -> 0 | AG25: =+U25 -> 0 | AH25: =IFERROR(VLOOKUP($I25,Trabajadores!$C$3:$AT$1684,44,FALSE),0) -> 19228 | AI25: =IFERROR(VLOOKUP($I25,Trabajadores!$C$3:$AT$1684,2,FALSE),0) -> 278 | AJ25: =IFERROR(VLOOKUP($I25,Trabajadores!$C$3:$AY$1270,21,FALSE),0) -> 36 | AK25: =IFERROR(VLOOKUP($I25,Trabajadores!$C$3:$AN$1684,38,FALSE),0) -> 9.47 | AL25: =IFERROR(VLOOKUP($I25,Trabajadores!$C$3:$AN$1684,28,FALSE),0) -> 99100165012016 | AM25: =IFERROR(VLOOKUP($I25,Trabajadores!$C$3:$AN$1684,19,FALSE),0) -> h ASL | AN25: =IFERROR(IF($J25="algadi",VLOOKUP($K25,Centros!$AB$2:$AD$142,2,FALSE),VLOOKUP($K25,Centros!$AB$143:$AD$282,2,FALSE)),0) -> 19228 | AO25: =IFERROR(IF($J25="algadi",VLOOKUP($K25,Centros!$AB$2:$AD$142,3,FALSE),VLOOKUP($K25,Centros!$AB$143:$AD$222,3,FALSE)),0) -> 36 | AQ25: =IFERROR(VLOOKUP($AM25,Centros!$AR$2:$AS$405,2,FALSE),0) -> 1.6367812 | AR25: =IFERROR(VLOOKUP($AM25,Centros!$AZ$2:$BA$6,2,FALSE),0) -> 0 | AS25: =IFERROR(VLOOKUP($AM25,Centros!$BE$2:$BF$6,2,FALSE),0) -> 0 | BD25: =+X25 -> ALGADI | BE25: INCIDENCIA | BF25: =+E25 -> 9-SEPTIEMBRE | BG25: =+Y25 -> 110030 | BH25: =VLOOKUP(Y25,Hoja1!$A$2:$O$599,14,FALSE) -> 110030 | BI25: =VLOOKUP(BH25,Hoja1!$A$2:$O$599,2,FALSE) -> COLEGIO INMACULADA | BJ25: =+I25 -> DIAZ HELLIN BELTRAN, M MERCEDES | BK25: =VLOOKUP(BJ25,Trabajadores!$C$3:$AN$3285,14,FALSE) -> 300 | BL25: =VLOOKUP($BJ25,Trabajadores!$C$3:$AN$3285,19,FALSE) -> h ASL | BM25: =VLOOKUP($BJ25,Trabajadores!$C$3:$AN$3285,16,FALSE) -> 50 | BN25: =IF($G25="010 Restauración",100%,0%) -> 1 | BO25: =IF($G25="020 Limpieza",100%,0%) -> 0 | BP25: =+BN25+BO25 -> 1 | BR25: =-W25 -> -14.844375 | BV25: =+J25 -> ALGADI | BW25: INCIDENCIA | BX25: =+E25 -> 9-SEPTIEMBRE | BY25: =+K25 -> 110030 | BZ25: =VLOOKUP(BY25,Hoja1!$A$2:$O$599,14,FALSE) -> 110030 | CA25: =VLOOKUP(BZ25,Hoja1!$A$2:$O$599,2,FALSE) -> COLEGIO INMACULADA | CB25: =+H25 -> Permiso retribuido | CC25: 888 | CD25: =+BW25 -> INCIDENCIA | CJ25: =+W25 -> 14.844375
D26: 945 | E26: 9-SEPTIEMBRE | F26: NO | G26: 020 Limpieza | H26: Permiso retribuido | I26: DJIBA , BERNADETTE | J26: ALGADI | K26: 110021 | L26: =IF(W26>0,IF(OR(E26="",F26="",G26="",H26="",I26="",J26="",K26=""),"faltan datos","ok")," ") -> ok | M26: =IFERROR(VLOOKUP(K26,Centros!$E$2:$G$340,2,FALSE)," ") -> COLEGIO FUNDACION CALDEIRO | N26: =IF(J26=" "," ",IF(J26=X26," ","Emp Orig/dest. Distinta")) | O26: =IFERROR(VLOOKUP($I26,Trabajadores!$C$3:$AF$1684,19,FALSE)," ") -> ASL | P26: 4 | Q26: 9 | R26: =+P26*Q26 -> 36 | T26: =IF(AL26="99100165012016",AQ26,IF(AL26="28009435011996",AR26,IF(AL26="99010825011997",AS26))) -> 1.6367812 | U26: =IF(T26="no corresponde",0,+S26*T26) -> 0 | W26: =+V26*AK26+((+R26+U26)*1.3195) -> 47.502 | X26: =IFERROR(VLOOKUP($I26,Trabajadores!$C$2:$AS$1684,42,FALSE)," ") -> ALGADI | Y26: =IFERROR(VLOOKUP($I26,Trabajadores!$C$2:$AS$1684,40,FALSE)," ") -> 110091 | Z26: =IFERROR(VLOOKUP(Y26,Centros!$X$2:$Y$228,2,FALSE)," ") -> COLEGIO CLARET -MADRID | AA26: 45909 | AB26: Medico hija Irma Galván | AC26: =IFERROR(VLOOKUP(H26,Centros!$AI$2:$AN$10,6,FALSE),0) -> 72 | AD26: =IF(AC26=70,R26,0) -> 0 | AE26: =IF(AC26=72,R26,0) -> 36 | AF26: =IF(AC26=73,+R26,0) -> 0 | AG26: =+U26 -> 0 | AH26: =IFERROR(VLOOKUP($I26,Trabajadores!$C$3:$AT$1684,44,FALSE),0) -> 19228 | AI26: =IFERROR(VLOOKUP($I26,Trabajadores!$C$3:$AT$1684,2,FALSE),0) -> 283 | AJ26: =IFERROR(VLOOKUP($I26,Trabajadores!$C$3:$AY$1270,21,FALSE),0) -> 50 | AK26: =IFERROR(VLOOKUP($I26,Trabajadores!$C$3:$AN$1684,38,FALSE),0) -> 1.845 | AL26: =IFERROR(VLOOKUP($I26,Trabajadores!$C$3:$AN$1684,28,FALSE),0) -> 99100165012016 | AM26: =IFERROR(VLOOKUP($I26,Trabajadores!$C$3:$AN$1684,19,FALSE),0) -> ASL | AN26: =IFERROR(IF($J26="algadi",VLOOKUP($K26,Centros!$AB$2:$AD$142,2,FALSE),VLOOKUP($K26,Centros!$AB$143:$AD$282,2,FALSE)),0) -> 19228 | AO26: =IFERROR(IF($J26="algadi",VLOOKUP($K26,Centros!$AB$2:$AD$142,3,FALSE),VLOOKUP($K26,Centros!$AB$143:$AD$222,3,FALSE)),0) -> 20 | AQ26: =IFERROR(VLOOKUP($AM26,Centros!$AR$2:$AS$405,2,FALSE),0) -> 1.6367812 | AR26: =IFERROR(VLOOKUP($AM26,Centros!$AZ$2:$BA$6,2,FALSE),0) -> 0 | AS26: =IFERROR(VLOOKUP($AM26,Centros!$BE$2:$BF$6,2,FALSE),0) -> 2.05 | BD26: =+X26 -> ALGADI | BE26: INCIDENCIA | BF26: =+E26 -> 9-SEPTIEMBRE | BG26: =+Y26 -> 110091 | BH26: =VLOOKUP(Y26,Hoja1!$A$2:$O$599,14,FALSE) -> 110091 | BI26: =VLOOKUP(BH26,Hoja1!$A$2:$O$599,2,FALSE) -> COLEGIO CLARET -MADRID | BJ26: =+I26 -> DJIBA , BERNADETTE | BK26: =VLOOKUP(BJ26,Trabajadores!$C$3:$AN$3285,14,FALSE) -> 300 | BL26: =VLOOKUP($BJ26,Trabajadores!$C$3:$AN$3285,19,FALSE) -> ASL | BM26: =VLOOKUP($BJ26,Trabajadores!$C$3:$AN$3285,16,FALSE) -> 50 | BN26: =IF($G26="010 Restauración",100%,0%) -> 0 | BO26: =IF($G26="020 Limpieza",100%,0%) -> 1 | BP26: =+BN26+BO26 -> 1 | BR26: =-W26 -> -47.502 | BV26: =+J26 -> ALGADI | BW26: INCIDENCIA | BX26: =+E26 -> 9-SEPTIEMBRE | BY26: =+K26 -> 110021 | BZ26: =VLOOKUP(BY26,Hoja1!$A$2:$O$599,14,FALSE) -> 110021 | CA26: =VLOOKUP(BZ26,Hoja1!$A$2:$O$599,2,FALSE) -> COLEGIO FUNDACION CALDEIRO | CB26: =+H26 -> Permiso retribuido | CC26: 888 | CD26: =+BW26 -> INCIDENCIA | CJ26: =+W26 -> 47.502
D27: 945 | E27: 9-SEPTIEMBRE | F27: NO | G27: 010 Restauración | H27: Refuerzo | I27: DJIBA , BERNADETTE | J27: ALGADI | K27: 110091 | L27: =IF(W27>0,IF(OR(E27="",F27="",G27="",H27="",I27="",J27="",K27=""),"faltan datos","ok")," ") -> ok | M27: =IFERROR(VLOOKUP(K27,Centros!$E$2:$G$340,2,FALSE)," ") -> COLEGIO CLARET -MADRID | N27: =IF(J27=" "," ",IF(J27=X27," ","Emp Orig/dest. Distinta")) | O27: =IFERROR(VLOOKUP($I27,Trabajadores!$C$3:$AF$1684,19,FALSE)," ") -> ASL | P27: 8 | Q27: 9 | R27: =+P27*Q27 -> 72 | T27: =IF(AL27="99100165012016",AQ27,IF(AL27="28009435011996",AR27,IF(AL27="99010825011997",AS27))) -> 1.6367812 | U27: =IF(T27="no corresponde",0,+S27*T27) -> 0 | W27: =+V27*AK27+((+R27+U27)*1.3195) -> 95.004 | X27: =IFERROR(VLOOKUP($I27,Trabajadores!$C$2:$AS$1684,42,FALSE)," ") -> ALGADI | Y27: =IFERROR(VLOOKUP($I27,Trabajadores!$C$2:$AS$1684,40,FALSE)," ") -> 110091 | Z27: =IFERROR(VLOOKUP(Y27,Centros!$X$2:$Y$228,2,FALSE)," ") -> COLEGIO CLARET -MADRID | AA27: 9 al 12 | AB27: Por no incorporación hasta 01-10-25 de la trabajadora de 6 horas/dia | AC27: =IFERROR(VLOOKUP(H27,Centros!$AI$2:$AN$10,6,FALSE),0) -> 72 | AD27: =IF(AC27=70,R27,0) -> 0 | AE27: =IF(AC27=72,R27,0) -> 72 | AF27: =IF(AC27=73,+R27,0) -> 0 | AG27: =+U27 -> 0 | AH27: =IFERROR(VLOOKUP($I27,Trabajadores!$C$3:$AT$1684,44,FALSE),0) -> 19228 | AI27: =IFERROR(VLOOKUP($I27,Trabajadores!$C$3:$AT$1684,2,FALSE),0) -> 283 | AJ27: =IFERROR(VLOOKUP($I27,Trabajadores!$C$3:$AY$1270,21,FALSE),0) -> 50 | AK27: =IFERROR(VLOOKUP($I27,Trabajadores!$C$3:$AN$1684,38,FALSE),0) -> 1.845 | AL27: =IFERROR(VLOOKUP($I27,Trabajadores!$C$3:$AN$1684,28,FALSE),0) -> 99100165012016 | AM27: =IFERROR(VLOOKUP($I27,Trabajadores!$C$3:$AN$1684,19,FALSE),0) -> ASL | AN27: =IFERROR(IF($J27="algadi",VLOOKUP($K27,Centros!$AB$2:$AD$142,2,FALSE),VLOOKUP($K27,Centros!$AB$143:$AD$282,2,FALSE)),0) -> 0 | AO27: =IFERROR(IF($J27="algadi",VLOOKUP($K27,Centros!$AB$2:$AD$142,3,FALSE),VLOOKUP($K27,Centros!$AB$143:$AD$222,3,FALSE)),0) -> 0 | AQ27: =IFERROR(VLOOKUP($AM27,Centros!$AR$2:$AS$405,2,FALSE),0) -> 1.6367812 | AR27: =IFERROR(VLOOKUP($AM27,Centros!$AZ$2:$BA$6,2,FALSE),0) -> 0 | AS27: =IFERROR(VLOOKUP($AM27,Centros!$BE$2:$BF$6,2,FALSE),0) -> 2.05 | BD27: =+X27 -> ALGADI | BE27: INCIDENCIA | BF27: =+E27 -> 9-SEPTIEMBRE | BG27: =+Y27 -> 110091 | BH27: =VLOOKUP(Y27,Hoja1!$A$2:$O$599,14,FALSE) -> 110091 | BI27: =VLOOKUP(BH27,Hoja1!$A$2:$O$599,2,FALSE) -> COLEGIO CLARET -MADRID | BJ27: =+I27 -> DJIBA , BERNADETTE | BK27: =VLOOKUP(BJ27,Trabajadores!$C$3:$AN$3285,14,FALSE) -> 300 | BL27: =VLOOKUP($BJ27,Trabajadores!$C$3:$AN$3285,19,FALSE) -> ASL | BM27: =VLOOKUP($BJ27,Trabajadores!$C$3:$AN$3285,16,FALSE) -> 50 | BN27: =IF($G27="010 Restauración",100%,0%) -> 1 | BO27: =IF($G27="020 Limpieza",100%,0%) -> 0 | BP27: =+BN27+BO27 -> 1 | BR27: =-W27 -> -95.004 | BV27: =+J27 -> ALGADI | BW27: INCIDENCIA | BX27: =+E27 -> 9-SEPTIEMBRE | BY27: =+K27 -> 110091 | BZ27: =VLOOKUP(BY27,Hoja1!$A$2:$O$599,14,FALSE) -> 110091 | CA27: =VLOOKUP(BZ27,Hoja1!$A$2:$O$599,2,FALSE) -> COLEGIO CLARET -MADRID | CB27: =+H27 -> Refuerzo | CC27: 888 | CD27: =+BW27 -> INCIDENCIA | CJ27: =+W27 -> 95.004
D28: 945 | E28: 9-SEPTIEMBRE | F28: NO | G28: 010 Restauración | H28: Otros | I28: ESPINOSA CELESTER, JENIFER | J28: ALGADI | K28: 110091 | L28: =IF(W28>0,IF(OR(E28="",F28="",G28="",H28="",I28="",J28="",K28=""),"faltan datos","ok")," ") -> ok | M28: =IFERROR(VLOOKUP(K28,Centros!$E$2:$G$340,2,FALSE)," ") -> COLEGIO CLARET -MADRID | N28: =IF(J28=" "," ",IF(J28=X28," ","Emp Orig/dest. Distinta")) | O28: =IFERROR(VLOOKUP($I28,Trabajadores!$C$3:$AF$1684,19,FALSE)," ") -> Monitor@ | P28: 28 | Q28: 5.8 | R28: =+P28*Q28 -> 162.4 | T28: =IF(AL28="99100165012016",AQ28,IF(AL28="28009435011996",AR28,IF(AL28="99010825011997",AS28))) -> 1.6367812 | U28: =IF(T28="no corresponde",0,+S28*T28) -> 0 | W28: =+V28*AK28+((+R28+U28)*1.3195) -> 214.2868 | X28: =IFERROR(VLOOKUP($I28,Trabajadores!$C$2:$AS$1684,42,FALSE)," ") -> ALGADI | Y28: =IFERROR(VLOOKUP($I28,Trabajadores!$C$2:$AS$1684,40,FALSE)," ") -> 110216 | Z28: =IFERROR(VLOOKUP(Y28,Centros!$X$2:$Y$228,2,FALSE)," ") -> COL. MATER INMACULATA | AA28: 25 agosto al 5 septiembre | AB28: Baja volulntaria de Fiorella (Por SMI) | AC28: =IFERROR(VLOOKUP(H28,Centros!$AI$2:$AN$10,6,FALSE),0) -> 72 | AD28: =IF(AC28=70,R28,0) -> 0 | AE28: =IF(AC28=72,R28,0) -> 162.4 | AF28: =IF(AC28=73,+R28,0) -> 0 | AG28: =+U28 -> 0 | AH28: =IFERROR(VLOOKUP($I28,Trabajadores!$C$3:$AT$1684,44,FALSE),0) -> 19228 | AI28: =IFERROR(VLOOKUP($I28,Trabajadores!$C$3:$AT$1684,2,FALSE),0) -> 1831 | AJ28: =IFERROR(VLOOKUP($I28,Trabajadores!$C$3:$AY$1270,21,FALSE),0) -> 107 | AK28: =IFERROR(VLOOKUP($I28,Trabajadores!$C$3:$AN$1684,38,FALSE),0) -> 7.8 | AL28: =IFERROR(VLOOKUP($I28,Trabajadores!$C$3:$AN$1684,28,FALSE),0) -> 99100165012016 | AM28: =IFERROR(VLOOKUP($I28,Trabajadores!$C$3:$AN$1684,19,FALSE),0) -> Monitor@ | AN28: =IFERROR(IF($J28="algadi",VLOOKUP($K28,Centros!$AB$2:$AD$142,2,FALSE),VLOOKUP($K28,Centros!$AB$143:$AD$282,2,FALSE)),0) -> 0 | AO28: =IFERROR(IF($J28="algadi",VLOOKUP($K28,Centros!$AB$2:$AD$142,3,FALSE),VLOOKUP($K28,Centros!$AB$143:$AD$222,3,FALSE)),0) -> 0 | AQ28: =IFERROR(VLOOKUP($AM28,Centros!$AR$2:$AS$405,2,FALSE),0) -> 1.6367812 | AR28: =IFERROR(VLOOKUP($AM28,Centros!$AZ$2:$BA$6,2,FALSE),0) -> 0 | AS28: =IFERROR(VLOOKUP($AM28,Centros!$BE$2:$BF$6,2,FALSE),0) -> 0 | BD28: =+X28 -> ALGADI | BE28: INCIDENCIA | BF28: =+E28 -> 9-SEPTIEMBRE | BG28: =+Y28 -> 110216 | BH28: =VLOOKUP(Y28,Hoja1!$A$2:$O$599,14,FALSE) -> 110216 | BI28: =VLOOKUP(BH28,Hoja1!$A$2:$O$599,2,FALSE) -> COL. MATER INMACULATA | BJ28: =+I28 -> ESPINOSA CELESTER, JENIFER | BK28: =VLOOKUP(BJ28,Trabajadores!$C$3:$AN$3285,14,FALSE) -> 300 | BL28: =VLOOKUP($BJ28,Trabajadores!$C$3:$AN$3285,19,FALSE) -> Monitor@ | BM28: =VLOOKUP($BJ28,Trabajadores!$C$3:$AN$3285,16,FALSE) -> 25 | BN28: =IF($G28="010 Restauración",100%,0%) -> 1 | BO28: =IF($G28="020 Limpieza",100%,0%) -> 0 | BP28: =+BN28+BO28 -> 1 | BR28: =-W28 -> -214.2868 | BV28: =+J28 -> ALGADI | BW28: INCIDENCIA | BX28: =+E28 -> 9-SEPTIEMBRE | BY28: =+K28 -> 110091 | BZ28: =VLOOKUP(BY28,Hoja1!$A$2:$O$599,14,FALSE) -> 110091 | CA28: =VLOOKUP(BZ28,Hoja1!$A$2:$O$599,2,FALSE) -> COLEGIO CLARET -MADRID | CB28: =+H28 -> Otros | CC28: 888 | CD28: =+BW28 -> INCIDENCIA | CJ28: =+W28 -> 214.2868
D29: 945 | E29: 9-SEPTIEMBRE | F29: NO | G29: 010 Restauración | H29: Festivos y Fines de Semana | I29: FERNANDEZ BLANCO, ARACELI | J29: ALGADI | K29: 110082 | L29: =IF(W29>0,IF(OR(E29="",F29="",G29="",H29="",I29="",J29="",K29=""),"faltan datos","ok")," ") -> ok | M29: =IFERROR(VLOOKUP(K29,Centros!$E$2:$G$340,2,FALSE)," ") -> COL. SAN MIGUEL ARCANGEL | N29: =IF(J29=" "," ",IF(J29=X29," ","Emp Orig/dest. Distinta")) | O29: =IFERROR(VLOOKUP($I29,Trabajadores!$C$3:$AF$1684,19,FALSE)," ") -> h Cociner@ | P29: 1 | Q29: 70 | R29: =+P29*Q29 -> 70 | T29: =IF(AL29="99100165012016",AQ29,IF(AL29="28009435011996",AR29,IF(AL29="99010825011997",AS29))) -> 1.7437656 | U29: =IF(T29="no corresponde",0,+S29*T29) -> 0 | W29: =+V29*AK29+((+R29+U29)*1.3195) -> 92.365 | X29: =IFERROR(VLOOKUP($I29,Trabajadores!$C$2:$AS$1684,42,FALSE)," ") -> ALGADI | Y29: =IFERROR(VLOOKUP($I29,Trabajadores!$C$2:$AS$1684,40,FALSE)," ") -> 110082 | Z29: =IFERROR(VLOOKUP(Y29,Centros!$X$2:$Y$228,2,FALSE)," ") -> COL. SAN MIGUEL ARCANGEL | AA29: 20 septiembre´25 | AB29: Fin de semana en San Miguel (lo cambia Natalay) | AC29: =IFERROR(VLOOKUP(H29,Centros!$AI$2:$AN$10,6,FALSE),0) -> 70 | AD29: =IF(AC29=70,R29,0) -> 70 | AE29: =IF(AC29=72,R29,0) -> 0 | AF29: =IF(AC29=73,+R29,0) -> 0 | AG29: =+U29 -> 0 | AH29: =IFERROR(VLOOKUP($I29,Trabajadores!$C$3:$AT$1684,44,FALSE),0) -> 19228 | AI29: =IFERROR(VLOOKUP($I29,Trabajadores!$C$3:$AT$1684,2,FALSE),0) -> 21 | AJ29: =IFERROR(VLOOKUP($I29,Trabajadores!$C$3:$AY$1270,21,FALSE),0) -> 4 | AK29: =IFERROR(VLOOKUP($I29,Trabajadores!$C$3:$AN$1684,38,FALSE),0) -> 8.9707692 | AL29: =IFERROR(VLOOKUP($I29,Trabajadores!$C$3:$AN$1684,28,FALSE),0) -> 99100165012016 | AM29: =IFERROR(VLOOKUP($I29,Trabajadores!$C$3:$AN$1684,19,FALSE),0) -> h Cociner@ | AN29: =IFERROR(IF($J29="algadi",VLOOKUP($K29,Centros!$AB$2:$AD$142,2,FALSE),VLOOKUP($K29,Centros!$AB$143:$AD$282,2,FALSE)),0) -> 19228 | AO29: =IFERROR(IF($J29="algadi",VLOOKUP($K29,Centros!$AB$2:$AD$142,3,FALSE),VLOOKUP($K29,Centros!$AB$143:$AD$222,3,FALSE)),0) -> 4 | AQ29: =IFERROR(VLOOKUP($AM29,Centros!$AR$2:$AS$405,2,FALSE),0) -> 1.7437656 | AR29: =IFERROR(VLOOKUP($AM29,Centros!$AZ$2:$BA$6,2,FALSE),0) -> 0 | AS29: =IFERROR(VLOOKUP($AM29,Centros!$BE$2:$BF$6,2,FALSE),0) -> 0 | BD29: =+X29 -> ALGADI | BE29: INCIDENCIA | BF29: =+E29 -> 9-SEPTIEMBRE | BG29: =+Y29 -> 110082 | BH29: =VLOOKUP(Y29,Hoja1!$A$2:$O$599,14,FALSE) -> 110082 | BI29: =VLOOKUP(BH29,Hoja1!$A$2:$O$599,2,FALSE) -> COL. SAN MIGUEL ARCANGEL | BJ29: =+I29 -> FERNANDEZ BLANCO, ARACELI | BK29: =VLOOKUP(BJ29,Trabajadores!$C$3:$AN$3285,14,FALSE) -> 200 | BL29: =VLOOKUP($BJ29,Trabajadores!$C$3:$AN$3285,19,FALSE) -> h Cociner@ | BM29: =VLOOKUP($BJ29,Trabajadores!$C$3:$AN$3285,16,FALSE) -> 81.25 | BN29: =IF($G29="010 Restauración",100%,0%) -> 1 | BO29: =IF($G29="020 Limpieza",100%,0%) -> 0 | BP29: =+BN29+BO29 -> 1 | BR29: =-W29 -> -92.365 | BV29: =+J29 -> ALGADI | BW29: INCIDENCIA | BX29: =+E29 -> 9-SEPTIEMBRE | BY29: =+K29 -> 110082 | BZ29: =VLOOKUP(BY29,Hoja1!$A$2:$O$599,14,FALSE) -> 110082 | CA29: =VLOOKUP(BZ29,Hoja1!$A$2:$O$599,2,FALSE) -> COL. SAN MIGUEL ARCANGEL | CB29: =+H29 -> Festivos y Fines de Semana | CC29: 888 | CD29: =+BW29 -> INCIDENCIA | CJ29: =+W29 -> 92.365
D30: 945 | E30: 9-SEPTIEMBRE | F30: NO | G30: 020 Limpieza | H30: Otros | I30: FERNANDEZ GARCIA, M PILAR | J30: ALGADI | K30: 110082 | L30: =IF(W30>0,IF(OR(E30="",F30="",G30="",H30="",I30="",J30="",K30=""),"faltan datos","ok")," ") -> ok | M30: =IFERROR(VLOOKUP(K30,Centros!$E$2:$G$340,2,FALSE)," ") -> COL. SAN MIGUEL ARCANGEL | N30: =IF(J30=" "," ",IF(J30=X30," ","Emp Orig/dest. Distinta")) | O30: =IFERROR(VLOOKUP($I30,Trabajadores!$C$3:$AF$1684,19,FALSE)," ") -> Limpiador@ | P30: 17 | Q30: 9 | R30: =+P30*Q30 -> 153 | T30: =IF(AL30="99100165012016",AQ30,IF(AL30="28009435011996",AR30,IF(AL30="99010825011997",AS30))) -> FALSE | U30: =IF(T30="no corresponde",0,+S30*T30) -> 0 | W30: =+V30*AK30+((+R30+U30)*1.3195) -> 201.8835 | X30: =IFERROR(VLOOKUP($I30,Trabajadores!$C$2:$AS$1684,42,FALSE)," ") -> ALGADI | Y30: =IFERROR(VLOOKUP($I30,Trabajadores!$C$2:$AS$1684,40,FALSE)," ") -> 110082 | Z30: =IFERROR(VLOOKUP(Y30,Centros!$X$2:$Y$228,2,FALSE)," ") -> COL. SAN MIGUEL ARCANGEL | AA30: 45930 | AB30: media hora diaria y miercoles y jueves 1 hora | AC30: =IFERROR(VLOOKUP(H30,Centros!$AI$2:$AN$10,6,FALSE),0) -> 72 | AD30: =IF(AC30=70,R30,0) -> 0 | AE30: =IF(AC30=72,R30,0) -> 153 | AF30: =IF(AC30=73,+R30,0) -> 0 | AG30: =+U30 -> 0 | AH30: =IFERROR(VLOOKUP($I30,Trabajadores!$C$3:$AT$1684,44,FALSE),0) -> 19228 | AI30: =IFERROR(VLOOKUP($I30,Trabajadores!$C$3:$AT$1684,2,FALSE),0) -> 669 | AJ30: =IFERROR(VLOOKUP($I30,Trabajadores!$C$3:$AY$1270,21,FALSE),0) -> 4 | AK30: =IFERROR(VLOOKUP($I30,Trabajadores!$C$3:$AN$1684,38,FALSE),0) -> 10.301287 | AL30: =IFERROR(VLOOKUP($I30,Trabajadores!$C$3:$AN$1684,28,FALSE),0) -> 28002585011981 | AM30: =IFERROR(VLOOKUP($I30,Trabajadores!$C$3:$AN$1684,19,FALSE),0) -> Limpiador@ | AN30: =IFERROR(IF($J30="algadi",VLOOKUP($K30,Centros!$AB$2:$AD$142,2,FALSE),VLOOKUP($K30,Centros!$AB$143:$AD$282,2,FALSE)),0) -> 19228 | AO30: =IFERROR(IF($J30="algadi",VLOOKUP($K30,Centros!$AB$2:$AD$142,3,FALSE),VLOOKUP($K30,Centros!$AB$143:$AD$222,3,FALSE)),0) -> 4 | AQ30: =IFERROR(VLOOKUP($AM30,Centros!$AR$2:$AS$405,2,FALSE),0) -> 1.6367812 | AR30: =IFERROR(VLOOKUP($AM30,Centros!$AZ$2:$BA$6,2,FALSE),0) -> 0 | AS30: =IFERROR(VLOOKUP($AM30,Centros!$BE$2:$BF$6,2,FALSE),0) -> 0 | BD30: =+X30 -> ALGADI | BE30: INCIDENCIA | BF30: =+E30 -> 9-SEPTIEMBRE | BG30: =+Y30 -> 110082 | BH30: =VLOOKUP(Y30,Hoja1!$A$2:$O$599,14,FALSE) -> 110082 | BI30: =VLOOKUP(BH30,Hoja1!$A$2:$O$599,2,FALSE) -> COL. SAN MIGUEL ARCANGEL | BJ30: =+I30 -> FERNANDEZ GARCIA, M PILAR | BK30: =VLOOKUP(BJ30,Trabajadores!$C$3:$AN$3285,14,FALSE) -> 300 | BL30: =VLOOKUP($BJ30,Trabajadores!$C$3:$AN$3285,19,FALSE) -> Limpiador@ | BM30: =VLOOKUP($BJ30,Trabajadores!$C$3:$AN$3285,16,FALSE) -> 76.92 | BN30: =IF($G30="010 Restauración",100%,0%) -> 0 | BO30: =IF($G30="020 Limpieza",100%,0%) -> 1 | BP30: =+BN30+BO30 -> 1 | BR30: =-W30 -> -201.8835 | BV30: =+J30 -> ALGADI | BW30: INCIDENCIA | BX30: =+E30 -> 9-SEPTIEMBRE | BY30: =+K30 -> 110082 | BZ30: =VLOOKUP(BY30,Hoja1!$A$2:$O$599,14,FALSE) -> 110082 | CA30: =VLOOKUP(BZ30,Hoja1!$A$2:$O$599,2,FALSE) -> COL. SAN MIGUEL ARCANGEL | CB30: =+H30 -> Otros | CC30: 888 | CD30: =+BW30 -> INCIDENCIA | CJ30: =+W30 -> 201.8835
D31: 945 | E31: 9-SEPTIEMBRE | F31: SI | G31: 020 Limpieza | H31: Refuerzo | I31: FERNANDEZ JIMENEZ, Mª DOLORES | J31: ALGADI | K31: 110021 | L31: =IF(W31>0,IF(OR(E31="",F31="",G31="",H31="",I31="",J31="",K31=""),"faltan datos","ok")," ") -> ok | M31: =IFERROR(VLOOKUP(K31,Centros!$E$2:$G$340,2,FALSE)," ") -> COLEGIO FUNDACION CALDEIRO | N31: =IF(J31=" "," ",IF(J31=X31," ","Emp Orig/dest. Distinta")) | O31: =IFERROR(VLOOKUP($I31,Trabajadores!$C$3:$AF$1684,19,FALSE)," ") -> h ASL | P31: 8 | Q31: 9 | R31: =+P31*Q31 -> 72 | T31: =IF(AL31="99100165012016",AQ31,IF(AL31="28009435011996",AR31,IF(AL31="99010825011997",AS31))) -> 1.6367812 | U31: =IF(T31="no corresponde",0,+S31*T31) -> 0 | W31: =+V31*AK31+((+R31+U31)*1.3195) -> 95.004 | X31: =IFERROR(VLOOKUP($I31,Trabajadores!$C$2:$AS$1684,42,FALSE)," ") -> ALGADI | Y31: =IFERROR(VLOOKUP($I31,Trabajadores!$C$2:$AS$1684,40,FALSE)," ") -> 110021 | Z31: =IFERROR(VLOOKUP(Y31,Centros!$X$2:$Y$228,2,FALSE)," ") -> COLEGIO FUNDACION CALDEIRO | AA31: 4 y 5 septiembre | AB31: Limpieza comienzo curso | AC31: =IFERROR(VLOOKUP(H31,Centros!$AI$2:$AN$10,6,FALSE),0) -> 72 | AD31: =IF(AC31=70,R31,0) -> 0 | AE31: =IF(AC31=72,R31,0) -> 72 | AF31: =IF(AC31=73,+R31,0) -> 0 | AG31: =+U31 -> 0 | AH31: =IFERROR(VLOOKUP($I31,Trabajadores!$C$3:$AT$1684,44,FALSE),0) -> 19228 | AI31: =IFERROR(VLOOKUP($I31,Trabajadores!$C$3:$AT$1684,2,FALSE),0) -> 154 | AJ31: =IFERROR(VLOOKUP($I31,Trabajadores!$C$3:$AY$1270,21,FALSE),0) -> 20 | AK31: =IFERROR(VLOOKUP($I31,Trabajadores!$C$3:$AN$1684,38,FALSE),0) -> 9.47 | AL31: =IFERROR(VLOOKUP($I31,Trabajadores!$C$3:$AN$1684,28,FALSE),0) -> 99100165012016 | AM31: =IFERROR(VLOOKUP($I31,Trabajadores!$C$3:$AN$1684,19,FALSE),0) -> h ASL | AN31: =IFERROR(IF($J31="algadi",VLOOKUP($K31,Centros!$AB$2:$AD$142,2,FALSE),VLOOKUP($K31,Centros!$AB$143:$AD$282,2,FALSE)),0) -> 19228 | AO31: =IFERROR(IF($J31="algadi",VLOOKUP($K31,Centros!$AB$2:$AD$142,3,FALSE),VLOOKUP($K31,Centros!$AB$143:$AD$222,3,FALSE)),0) -> 20 | AQ31: =IFERROR(VLOOKUP($AM31,Centros!$AR$2:$AS$405,2,FALSE),0) -> 1.6367812 | AR31: =IFERROR(VLOOKUP($AM31,Centros!$AZ$2:$BA$6,2,FALSE),0) -> 0 | AS31: =IFERROR(VLOOKUP($AM31,Centros!$BE$2:$BF$6,2,FALSE),0) -> 0 | BD31: =+X31 -> ALGADI | BE31: INCIDENCIA | BF31: =+E31 -> 9-SEPTIEMBRE | BG31: =+Y31 -> 110021 | BH31: =VLOOKUP(Y31,Hoja1!$A$2:$O$599,14,FALSE) -> 110021 | BI31: =VLOOKUP(BH31,Hoja1!$A$2:$O$599,2,FALSE) -> COLEGIO FUNDACION CALDEIRO | BJ31: =+I31 -> FERNANDEZ JIMENEZ, Mª DOLORES | BK31: =VLOOKUP(BJ31,Trabajadores!$C$3:$AN$3285,14,FALSE) -> 300 | BL31: =VLOOKUP($BJ31,Trabajadores!$C$3:$AN$3285,19,FALSE) -> h ASL | BM31: =VLOOKUP($BJ31,Trabajadores!$C$3:$AN$3285,16,FALSE) -> 50 | BN31: =IF($G31="010 Restauración",100%,0%) -> 0 | BO31: =IF($G31="020 Limpieza",100%,0%) -> 1 | BP31: =+BN31+BO31 -> 1 | BR31: =-W31 -> -95.004 | BV31: =+J31 -> ALGADI | BW31: INCIDENCIA | BX31: =+E31 -> 9-SEPTIEMBRE | BY31: =+K31 -> 110021 | BZ31: =VLOOKUP(BY31,Hoja1!$A$2:$O$599,14,FALSE) -> 110021 | CA31: =VLOOKUP(BZ31,Hoja1!$A$2:$O$599,2,FALSE) -> COLEGIO FUNDACION CALDEIRO | CB31: =+H31 -> Refuerzo | CC31: 888 | CD31: =+BW31 -> INCIDENCIA | CJ31: =+W31 -> 95.004
D32: 945 | E32: 9-SEPTIEMBRE | F32: SI | G32: 020 Limpieza | H32: Refuerzo | I32: FERNANDEZ JIMENEZ, Mª DOLORES | J32: ALGADI | K32: 110021 | L32: =IF(W32>0,IF(OR(E32="",F32="",G32="",H32="",I32="",J32="",K32=""),"faltan datos","ok")," ") -> ok | M32: =IFERROR(VLOOKUP(K32,Centros!$E$2:$G$340,2,FALSE)," ") -> COLEGIO FUNDACION CALDEIRO | N32: =IF(J32=" "," ",IF(J32=X32," ","Emp Orig/dest. Distinta")) | O32: =IFERROR(VLOOKUP($I32,Trabajadores!$C$3:$AF$1684,19,FALSE)," ") -> h ASL | P32: 15 | Q32: 9 | R32: =+P32*Q32 -> 135 | T32: =IF(AL32="99100165012016",AQ32,IF(AL32="28009435011996",AR32,IF(AL32="99010825011997",AS32))) -> 1.6367812 | U32: =IF(T32="no corresponde",0,+S32*T32) -> 0 | W32: =+V32*AK32+((+R32+U32)*1.3195) -> 178.1325 | X32: =IFERROR(VLOOKUP($I32,Trabajadores!$C$2:$AS$1684,42,FALSE)," ") -> ALGADI | Y32: =IFERROR(VLOOKUP($I32,Trabajadores!$C$2:$AS$1684,40,FALSE)," ") -> 110021 | Z32: =IFERROR(VLOOKUP(Y32,Centros!$X$2:$Y$228,2,FALSE)," ") -> COLEGIO FUNDACION CALDEIRO | AA32: Septiembre´25 | AB32: Refuerzo por no incorporar a una persona de 5 horas en octubre | AC32: =IFERROR(VLOOKUP(H32,Centros!$AI$2:$AN$10,6,FALSE),0) -> 72 | AD32: =IF(AC32=70,R32,0) -> 0 | AE32: =IF(AC32=72,R32,0) -> 135 | AF32: =IF(AC32=73,+R32,0) -> 0 | AG32: =+U32 -> 0 | AH32: =IFERROR(VLOOKUP($I32,Trabajadores!$C$3:$AT$1684,44,FALSE),0) -> 19228 | AI32: =IFERROR(VLOOKUP($I32,Trabajadores!$C$3:$AT$1684,2,FALSE),0) -> 154 | AJ32: =IFERROR(VLOOKUP($I32,Trabajadores!$C$3:$AY$1270,21,FALSE),0) -> 20 | AK32: =IFERROR(VLOOKUP($I32,Trabajadores!$C$3:$AN$1684,38,FALSE),0) -> 9.47 | AL32: =IFERROR(VLOOKUP($I32,Trabajadores!$C$3:$AN$1684,28,FALSE),0) -> 99100165012016 | AM32: =IFERROR(VLOOKUP($I32,Trabajadores!$C$3:$AN$1684,19,FALSE),0) -> h ASL | AN32: =IFERROR(IF($J32="algadi",VLOOKUP($K32,Centros!$AB$2:$AD$142,2,FALSE),VLOOKUP($K32,Centros!$AB$143:$AD$282,2,FALSE)),0) -> 19228 | AO32: =IFERROR(IF($J32="algadi",VLOOKUP($K32,Centros!$AB$2:$AD$142,3,FALSE),VLOOKUP($K32,Centros!$AB$143:$AD$222,3,FALSE)),0) -> 20 | AQ32: =IFERROR(VLOOKUP($AM32,Centros!$AR$2:$AS$405,2,FALSE),0) -> 1.6367812 | AR32: =IFERROR(VLOOKUP($AM32,Centros!$AZ$2:$BA$6,2,FALSE),0) -> 0 | AS32: =IFERROR(VLOOKUP($AM32,Centros!$BE$2:$BF$6,2,FALSE),0) -> 0 | BD32: =+X32 -> ALGADI | BE32: INCIDENCIA | BF32: =+E32 -> 9-SEPTIEMBRE | BG32: =+Y32 -> 110021 | BH32: =VLOOKUP(Y32,Hoja1!$A$2:$O$599,14,FALSE) -> 110021 | BI32: =VLOOKUP(BH32,Hoja1!$A$2:$O$599,2,FALSE) -> COLEGIO FUNDACION CALDEIRO | BJ32: =+I32 -> FERNANDEZ JIMENEZ, Mª DOLORES | BK32: =VLOOKUP(BJ32,Trabajadores!$C$3:$AN$3285,14,FALSE) -> 300 | BL32: =VLOOKUP($BJ32,Trabajadores!$C$3:$AN$3285,19,FALSE) -> h ASL | BM32: =VLOOKUP($BJ32,Trabajadores!$C$3:$AN$3285,16,FALSE) -> 50 | BN32: =IF($G32="010 Restauración",100%,0%) -> 0 | BO32: =IF($G32="020 Limpieza",100%,0%) -> 1 | BP32: =+BN32+BO32 -> 1 | BR32: =-W32 -> -178.1325 | BV32: =+J32 -> ALGADI | BW32: INCIDENCIA | BX32: =+E32 -> 9-SEPTIEMBRE | BY32: =+K32 -> 110021 | BZ32: =VLOOKUP(BY32,Hoja1!$A$2:$O$599,14,FALSE) -> 110021 | CA32: =VLOOKUP(BZ32,Hoja1!$A$2:$O$599,2,FALSE) -> COLEGIO FUNDACION CALDEIRO | CB32: =+H32 -> Refuerzo | CC32: 888 | CD32: =+BW32 -> INCIDENCIA | CJ32: =+W32 -> 178.1325
D33: 945 | E33: 9-SEPTIEMBRE | F33: SI | G33: 020 Limpieza | H33: Refuerzo | I33: GARCIA HIERRO ANDRES, LAURA | J33: ALGADI | K33: 110021 | L33: =IF(W33>0,IF(OR(E33="",F33="",G33="",H33="",I33="",J33="",K33=""),"faltan datos","ok")," ") -> ok | M33: =IFERROR(VLOOKUP(K33,Centros!$E$2:$G$340,2,FALSE)," ") -> COLEGIO FUNDACION CALDEIRO | N33: =IF(J33=" "," ",IF(J33=X33," ","Emp Orig/dest. Distinta")) | O33: =IFERROR(VLOOKUP($I33,Trabajadores!$C$3:$AF$1684,19,FALSE)," ") -> ASL | P33: 4 | Q33: 9 | R33: =+P33*Q33 -> 36 | T33: =IF(AL33="99100165012016",AQ33,IF(AL33="28009435011996",AR33,IF(AL33="99010825011997",AS33))) -> 1.6367812 | U33: =IF(T33="no corresponde",0,+S33*T33) -> 0 | W33: =+V33*AK33+((+R33+U33)*1.3195) -> 47.502 | X33: =IFERROR(VLOOKUP($I33,Trabajadores!$C$2:$AS$1684,42,FALSE)," ") -> ALGADI | Y33: =IFERROR(VLOOKUP($I33,Trabajadores!$C$2:$AS$1684,40,FALSE)," ") -> 110021 | Z33: =IFERROR(VLOOKUP(Y33,Centros!$X$2:$Y$228,2,FALSE)," ") -> COLEGIO FUNDACION CALDEIRO | AA33: 4 y 5 septiembre | AB33: Limpieza comienzo curso | AC33: =IFERROR(VLOOKUP(H33,Centros!$AI$2:$AN$10,6,FALSE),0) -> 72 | AD33: =IF(AC33=70,R33,0) -> 0 | AE33: =IF(AC33=72,R33,0) -> 36 | AF33: =IF(AC33=73,+R33,0) -> 0 | AG33: =+U33 -> 0 | AH33: =IFERROR(VLOOKUP($I33,Trabajadores!$C$3:$AT$1684,44,FALSE),0) -> 19228 | AI33: =IFERROR(VLOOKUP($I33,Trabajadores!$C$3:$AT$1684,2,FALSE),0) -> 459 | AJ33: =IFERROR(VLOOKUP($I33,Trabajadores!$C$3:$AY$1270,21,FALSE),0) -> 20 | AK33: =IFERROR(VLOOKUP($I33,Trabajadores!$C$3:$AN$1684,38,FALSE),0) -> 7.5633333 | AL33: =IFERROR(VLOOKUP($I33,Trabajadores!$C$3:$AN$1684,28,FALSE),0) -> 99100165012016 | AM33: =IFERROR(VLOOKUP($I33,Trabajadores!$C$3:$AN$1684,19,FALSE),0) -> ASL | AN33: =IFERROR(IF($J33="algadi",VLOOKUP($K33,Centros!$AB$2:$AD$142,2,FALSE),VLOOKUP($K33,Centros!$AB$143:$AD$282,2,FALSE)),0) -> 19228 | AO33: =IFERROR(IF($J33="algadi",VLOOKUP($K33,Centros!$AB$2:$AD$142,3,FALSE),VLOOKUP($K33,Centros!$AB$143:$AD$222,3,FALSE)),0) -> 20 | AQ33: =IFERROR(VLOOKUP($AM33,Centros!$AR$2:$AS$405,2,FALSE),0) -> 1.6367812 | AR33: =IFERROR(VLOOKUP($AM33,Centros!$AZ$2:$BA$6,2,FALSE),0) -> 0 | AS33: =IFERROR(VLOOKUP($AM33,Centros!$BE$2:$BF$6,2,FALSE),0) -> 2.05 | BD33: =+X33 -> ALGADI | BE33: INCIDENCIA | BF33: =+E33 -> 9-SEPTIEMBRE | BG33: =+Y33 -> 110021 | BH33: =VLOOKUP(Y33,Hoja1!$A$2:$O$599,14,FALSE) -> 110021 | BI33: =VLOOKUP(BH33,Hoja1!$A$2:$O$599,2,FALSE) -> COLEGIO FUNDACION CALDEIRO | BJ33: =+I33 -> GARCIA HIERRO ANDRES, LAURA | BK33: =VLOOKUP(BJ33,Trabajadores!$C$3:$AN$3285,14,FALSE) -> 300 | BL33: =VLOOKUP($BJ33,Trabajadores!$C$3:$AN$3285,19,FALSE) -> ASL | BM33: =VLOOKUP($BJ33,Trabajadores!$C$3:$AN$3285,16,FALSE) -> 37.5 | BN33: =IF($G33="010 Restauración",100%,0%) -> 0 | BO33: =IF($G33="020 Limpieza",100%,0%) -> 1 | BP33: =+BN33+BO33 -> 1 | BR33: =-W33 -> -47.502 | BV33: =+J33 -> ALGADI | BW33: INCIDENCIA | BX33: =+E33 -> 9-SEPTIEMBRE | BY33: =+K33 -> 110021 | BZ33: =VLOOKUP(BY33,Hoja1!$A$2:$O$599,14,FALSE) -> 110021 | CA33: =VLOOKUP(BZ33,Hoja1!$A$2:$O$599,2,FALSE) -> COLEGIO FUNDACION CALDEIRO | CB33: =+H33 -> Refuerzo | CC33: 888 | CD33: =+BW33 -> INCIDENCIA | CJ33: =+W33 -> 47.502
D34: 945 | E34: 9-SEPTIEMBRE | F34: SI | G34: 020 Limpieza | H34: Refuerzo | I34: GARCIA HIERRO ANDRES, LAURA | J34: ALGADI | K34: 110021 | L34: =IF(W34>0,IF(OR(E34="",F34="",G34="",H34="",I34="",J34="",K34=""),"faltan datos","ok")," ") -> ok | M34: =IFERROR(VLOOKUP(K34,Centros!$E$2:$G$340,2,FALSE)," ") -> COLEGIO FUNDACION CALDEIRO | N34: =IF(J34=" "," ",IF(J34=X34," ","Emp Orig/dest. Distinta")) | O34: =IFERROR(VLOOKUP($I34,Trabajadores!$C$3:$AF$1684,19,FALSE)," ") -> ASL | P34: 15 | Q34: 9 | R34: =+P34*Q34 -> 135 | T34: =IF(AL34="99100165012016",AQ34,IF(AL34="28009435011996",AR34,IF(AL34="99010825011997",AS34))) -> 1.6367812 | U34: =IF(T34="no corresponde",0,+S34*T34) -> 0 | W34: =+V34*AK34+((+R34+U34)*1.3195) -> 178.1325 | X34: =IFERROR(VLOOKUP($I34,Trabajadores!$C$2:$AS$1684,42,FALSE)," ") -> ALGADI | Y34: =IFERROR(VLOOKUP($I34,Trabajadores!$C$2:$AS$1684,40,FALSE)," ") -> 110021 | Z34: =IFERROR(VLOOKUP(Y34,Centros!$X$2:$Y$228,2,FALSE)," ") -> COLEGIO FUNDACION CALDEIRO | AA34: Septiembre´25 | AB34: Refuerzo por no incorporar a una persona de 5 horas en octubre | AC34: =IFERROR(VLOOKUP(H34,Centros!$AI$2:$AN$10,6,FALSE),0) -> 72 | AD34: =IF(AC34=70,R34,0) -> 0 | AE34: =IF(AC34=72,R34,0) -> 135 | AF34: =IF(AC34=73,+R34,0) -> 0 | AG34: =+U34 -> 0 | AH34: =IFERROR(VLOOKUP($I34,Trabajadores!$C$3:$AT$1684,44,FALSE),0) -> 19228 | AI34: =IFERROR(VLOOKUP($I34,Trabajadores!$C$3:$AT$1684,2,FALSE),0) -> 459 | AJ34: =IFERROR(VLOOKUP($I34,Trabajadores!$C$3:$AY$1270,21,FALSE),0) -> 20 | AK34: =IFERROR(VLOOKUP($I34,Trabajadores!$C$3:$AN$1684,38,FALSE),0) -> 7.5633333 | AL34: =IFERROR(VLOOKUP($I34,Trabajadores!$C$3:$AN$1684,28,FALSE),0) -> 99100165012016 | AM34: =IFERROR(VLOOKUP($I34,Trabajadores!$C$3:$AN$1684,19,FALSE),0) -> ASL | AN34: =IFERROR(IF($J34="algadi",VLOOKUP($K34,Centros!$AB$2:$AD$142,2,FALSE),VLOOKUP($K34,Centros!$AB$143:$AD$282,2,FALSE)),0) -> 19228 | AO34: =IFERROR(IF($J34="algadi",VLOOKUP($K34,Centros!$AB$2:$AD$142,3,FALSE),VLOOKUP($K34,Centros!$AB$143:$AD$222,3,FALSE)),0) -> 20 | AQ34: =IFERROR(VLOOKUP($AM34,Centros!$AR$2:$AS$405,2,FALSE),0) -> 1.6367812 | AR34: =IFERROR(VLOOKUP($AM34,Centros!$AZ$2:$BA$6,2,FALSE),0) -> 0 | AS34: =IFERROR(VLOOKUP($AM34,Centros!$BE$2:$BF$6,2,FALSE),0) -> 2.05 | BD34: =+X34 -> ALGADI | BE34: INCIDENCIA | BF34: =+E34 -> 9-SEPTIEMBRE | BG34: =+Y34 -> 110021 | BH34: =VLOOKUP(Y34,Hoja1!$A$2:$O$599,14,FALSE) -> 110021 | BI34: =VLOOKUP(BH34,Hoja1!$A$2:$O$599,2,FALSE) -> COLEGIO FUNDACION CALDEIRO | BJ34: =+I34 -> GARCIA HIERRO ANDRES, LAURA | BK34: =VLOOKUP(BJ34,Trabajadores!$C$3:$AN$3285,14,FALSE) -> 300 | BL34: =VLOOKUP($BJ34,Trabajadores!$C$3:$AN$3285,19,FALSE) -> ASL | BM34: =VLOOKUP($BJ34,Trabajadores!$C$3:$AN$3285,16,FALSE) -> 37.5 | BN34: =IF($G34="010 Restauración",100%,0%) -> 0 | BO34: =IF($G34="020 Limpieza",100%,0%) -> 1 | BP34: =+BN34+BO34 -> 1 | BR34: =-W34 -> -178.1325 | BV34: =+J34 -> ALGADI | BW34: INCIDENCIA | BX34: =+E34 -> 9-SEPTIEMBRE | BY34: =+K34 -> 110021 | BZ34: =VLOOKUP(BY34,Hoja1!$A$2:$O$599,14,FALSE) -> 110021 | CA34: =VLOOKUP(BZ34,Hoja1!$A$2:$O$599,2,FALSE) -> COLEGIO FUNDACION CALDEIRO | CB34: =+H34 -> Refuerzo | CC34: 888 | CD34: =+BW34 -> INCIDENCIA | CJ34: =+W34 -> 178.1325
D35: 945 | E35: 9-SEPTIEMBRE | F35: NO | G35: 010 Restauración | H35: Otros | I35: GOMEZ GONZALEZ, P BEGOÑA | J35: ALGADI | K35: 110082 | L35: =IF(W35>0,IF(OR(E35="",F35="",G35="",H35="",I35="",J35="",K35=""),"faltan datos","ok")," ") -> ok | M35: =IFERROR(VLOOKUP(K35,Centros!$E$2:$G$340,2,FALSE)," ") -> COL. SAN MIGUEL ARCANGEL | N35: =IF(J35=" "," ",IF(J35=X35," ","Emp Orig/dest. Distinta")) | O35: =IFERROR(VLOOKUP($I35,Trabajadores!$C$3:$AF$1684,19,FALSE)," ") -> h Enc/J Co | P35: 6 | Q35: 9 | R35: =+P35*Q35 -> 54 | T35: =IF(AL35="99100165012016",AQ35,IF(AL35="28009435011996",AR35,IF(AL35="99010825011997",AS35))) -> 1.7971719 | U35: =IF(T35="no corresponde",0,+S35*T35) -> 0 | W35: =+V35*AK35+((+R35+U35)*1.3195) -> 71.253 | X35: =IFERROR(VLOOKUP($I35,Trabajadores!$C$2:$AS$1684,42,FALSE)," ") -> ALGADI | Y35: =IFERROR(VLOOKUP($I35,Trabajadores!$C$2:$AS$1684,40,FALSE)," ") -> 110082 | Z35: =IFERROR(VLOOKUP(Y35,Centros!$X$2:$Y$228,2,FALSE)," ") -> COL. SAN MIGUEL ARCANGEL | AA35: Septiembre´25 | AB35: Funciones administrativas | AC35: =IFERROR(VLOOKUP(H35,Centros!$AI$2:$AN$10,6,FALSE),0) -> 72 | AD35: =IF(AC35=70,R35,0) -> 0 | AE35: =IF(AC35=72,R35,0) -> 54 | AF35: =IF(AC35=73,+R35,0) -> 0 | AG35: =+U35 -> 0 | AH35: =IFERROR(VLOOKUP($I35,Trabajadores!$C$3:$AT$1684,44,FALSE),0) -> 19228 | AI35: =IFERROR(VLOOKUP($I35,Trabajadores!$C$3:$AT$1684,2,FALSE),0) -> 30 | AJ35: =IFERROR(VLOOKUP($I35,Trabajadores!$C$3:$AY$1270,21,FALSE),0) -> 4 | AK35: =IFERROR(VLOOKUP($I35,Trabajadores!$C$3:$AN$1684,38,FALSE),0) -> 9.505 | AL35: =IFERROR(VLOOKUP($I35,Trabajadores!$C$3:$AN$1684,28,FALSE),0) -> 99100165012016 | AM35: =IFERROR(VLOOKUP($I35,Trabajadores!$C$3:$AN$1684,19,FALSE),0) -> h Enc/J Co | AN35: =IFERROR(IF($J35="algadi",VLOOKUP($K35,Centros!$AB$2:$AD$142,2,FALSE),VLOOKUP($K35,Centros!$AB$143:$AD$282,2,FALSE)),0) -> 19228 | AO35: =IFERROR(IF($J35="algadi",VLOOKUP($K35,Centros!$AB$2:$AD$142,3,FALSE),VLOOKUP($K35,Centros!$AB$143:$AD$222,3,FALSE)),0) -> 4 | AQ35: =IFERROR(VLOOKUP($AM35,Centros!$AR$2:$AS$405,2,FALSE),0) -> 1.7971719 | AR35: =IFERROR(VLOOKUP($AM35,Centros!$AZ$2:$BA$6,2,FALSE),0) -> 0 | AS35: =IFERROR(VLOOKUP($AM35,Centros!$BE$2:$BF$6,2,FALSE),0) -> 0 | BD35: =+X35 -> ALGADI | BE35: INCIDENCIA | BF35: =+E35 -> 9-SEPTIEMBRE | BG35: =+Y35 -> 110082 | BH35: =VLOOKUP(Y35,Hoja1!$A$2:$O$599,14,FALSE) -> 110082 | BI35: =VLOOKUP(BH35,Hoja1!$A$2:$O$599,2,FALSE) -> COL. SAN MIGUEL ARCANGEL | BJ35: =+I35 -> GOMEZ GONZALEZ, P BEGOÑA | BK35: =VLOOKUP(BJ35,Trabajadores!$C$3:$AN$3285,14,FALSE) -> 300 | BL35: =VLOOKUP($BJ35,Trabajadores!$C$3:$AN$3285,19,FALSE) -> h Enc/J Co | BM35: =VLOOKUP($BJ35,Trabajadores!$C$3:$AN$3285,16,FALSE) -> 100 | BN35: =IF($G35="010 Restauración",100%,0%) -> 1 | BO35: =IF($G35="020 Limpieza",100%,0%) -> 0 | BP35: =+BN35+BO35 -> 1 | BR35: =-W35 -> -71.253 | BV35: =+J35 -> ALGADI | BW35: INCIDENCIA | BX35: =+E35 -> 9-SEPTIEMBRE | BY35: =+K35 -> 110082 | BZ35: =VLOOKUP(BY35,Hoja1!$A$2:$O$599,14,FALSE) -> 110082 | CA35: =VLOOKUP(BZ35,Hoja1!$A$2:$O$599,2,FALSE) -> COL. SAN MIGUEL ARCANGEL | CB35: =+H35 -> Otros | CC35: 888 | CD35: =+BW35 -> INCIDENCIA | CJ35: =+W35 -> 71.253
D36: 945 | E36: 9-SEPTIEMBRE | F36: NO | G36: 010 Restauración | H36: Permiso retribuido | I36: HERNANDEZ LIRIANO, DENNI DERN | J36: ALGADI | K36: 110091 | L36: =IF(W36>0,IF(OR(E36="",F36="",G36="",H36="",I36="",J36="",K36=""),"faltan datos","ok")," ") -> ok | M36: =IFERROR(VLOOKUP(K36,Centros!$E$2:$G$340,2,FALSE)," ") -> COLEGIO CLARET -MADRID | N36: =IF(J36=" "," ",IF(J36=X36," ","Emp Orig/dest. Distinta")) | O36: =IFERROR(VLOOKUP($I36,Trabajadores!$C$3:$AF$1684,19,FALSE)," ") -> ASL | P36: 10 | Q36: 9 | R36: =+P36*Q36 -> 90 | T36: =IF(AL36="99100165012016",AQ36,IF(AL36="28009435011996",AR36,IF(AL36="99010825011997",AS36))) -> 1.6367812 | U36: =IF(T36="no corresponde",0,+S36*T36) -> 0 | W36: =+V36*AK36+((+R36+U36)*1.3195) -> 118.755 | X36: =IFERROR(VLOOKUP($I36,Trabajadores!$C$2:$AS$1684,42,FALSE)," ") -> ALGADI | Y36: =IFERROR(VLOOKUP($I36,Trabajadores!$C$2:$AS$1684,40,FALSE)," ") -> 110091 | Z36: =IFERROR(VLOOKUP(Y36,Centros!$X$2:$Y$228,2,FALSE)," ") -> COLEGIO CLARET -MADRID | AA36: 15 al 19 septiembre | AB36: Cobertura de IT Berni | AC36: =IFERROR(VLOOKUP(H36,Centros!$AI$2:$AN$10,6,FALSE),0) -> 72 | AD36: =IF(AC36=70,R36,0) -> 0 | AE36: =IF(AC36=72,R36,0) -> 90 | AF36: =IF(AC36=73,+R36,0) -> 0 | AG36: =+U36 -> 0 | AH36: =IFERROR(VLOOKUP($I36,Trabajadores!$C$3:$AT$1684,44,FALSE),0) -> 19228 | AI36: =IFERROR(VLOOKUP($I36,Trabajadores!$C$3:$AT$1684,2,FALSE),0) -> 989 | AJ36: =IFERROR(VLOOKUP($I36,Trabajadores!$C$3:$AY$1270,21,FALSE),0) -> 50 | AK36: =IFERROR(VLOOKUP($I36,Trabajadores!$C$3:$AN$1684,38,FALSE),0) -> 7.8 | AL36: =IFERROR(VLOOKUP($I36,Trabajadores!$C$3:$AN$1684,28,FALSE),0) -> 99100165012016 | AM36: =IFERROR(VLOOKUP($I36,Trabajadores!$C$3:$AN$1684,19,FALSE),0) -> ASL | AN36: =IFERROR(IF($J36="algadi",VLOOKUP($K36,Centros!$AB$2:$AD$142,2,FALSE),VLOOKUP($K36,Centros!$AB$143:$AD$282,2,FALSE)),0) -> 0 | AO36: =IFERROR(IF($J36="algadi",VLOOKUP($K36,Centros!$AB$2:$AD$142,3,FALSE),VLOOKUP($K36,Centros!$AB$143:$AD$222,3,FALSE)),0) -> 0 | AQ36: =IFERROR(VLOOKUP($AM36,Centros!$AR$2:$AS$405,2,FALSE),0) -> 1.6367812 | AR36: =IFERROR(VLOOKUP($AM36,Centros!$AZ$2:$BA$6,2,FALSE),0) -> 0 | AS36: =IFERROR(VLOOKUP($AM36,Centros!$BE$2:$BF$6,2,FALSE),0) -> 2.05 | BD36: =+X36 -> ALGADI | BE36: INCIDENCIA | BF36: =+E36 -> 9-SEPTIEMBRE | BG36: =+Y36 -> 110091 | BH36: =VLOOKUP(Y36,Hoja1!$A$2:$O$599,14,FALSE) -> 110091 | BI36: =VLOOKUP(BH36,Hoja1!$A$2:$O$599,2,FALSE) -> COLEGIO CLARET -MADRID | BJ36: =+I36 -> HERNANDEZ LIRIANO, DENNI DERN | BK36: =VLOOKUP(BJ36,Trabajadores!$C$3:$AN$3285,14,FALSE) -> 389 | BL36: =VLOOKUP($BJ36,Trabajadores!$C$3:$AN$3285,19,FALSE) -> ASL | BM36: =VLOOKUP($BJ36,Trabajadores!$C$3:$AN$3285,16,FALSE) -> 50 | BN36: =IF($G36="010 Restauración",100%,0%) -> 1 | BO36: =IF($G36="020 Limpieza",100%,0%) -> 0 | BP36: =+BN36+BO36 -> 1 | BR36: =-W36 -> -118.755 | BV36: =+J36 -> ALGADI | BW36: INCIDENCIA | BX36: =+E36 -> 9-SEPTIEMBRE | BY36: =+K36 -> 110091 | BZ36: =VLOOKUP(BY36,Hoja1!$A$2:$O$599,14,FALSE) -> 110091 | CA36: =VLOOKUP(BZ36,Hoja1!$A$2:$O$599,2,FALSE) -> COLEGIO CLARET -MADRID | CB36: =+H36 -> Permiso retribuido | CC36: 888 | CD36: =+BW36 -> INCIDENCIA | CJ36: =+W36 -> 118.755
D37: 945 | E37: 9-SEPTIEMBRE | F37: NO | G37: 010 Restauración | H37: Permiso retribuido | I37: HERNANDEZ LIRIANO, DENNI DERN | J37: ALGADI | K37: 110091 | L37: =IF(W37>0,IF(OR(E37="",F37="",G37="",H37="",I37="",J37="",K37=""),"faltan datos","ok")," ") -> ok | M37: =IFERROR(VLOOKUP(K37,Centros!$E$2:$G$340,2,FALSE)," ") -> COLEGIO CLARET -MADRID | N37: =IF(J37=" "," ",IF(J37=X37," ","Emp Orig/dest. Distinta")) | O37: =IFERROR(VLOOKUP($I37,Trabajadores!$C$3:$AF$1684,19,FALSE)," ") -> ASL | P37: 2 | Q37: 9 | R37: =+P37*Q37 -> 18 | T37: =IF(AL37="99100165012016",AQ37,IF(AL37="28009435011996",AR37,IF(AL37="99010825011997",AS37))) -> 1.6367812 | U37: =IF(T37="no corresponde",0,+S37*T37) -> 0 | W37: =+V37*AK37+((+R37+U37)*1.3195) -> 23.751 | X37: =IFERROR(VLOOKUP($I37,Trabajadores!$C$2:$AS$1684,42,FALSE)," ") -> ALGADI | Y37: =IFERROR(VLOOKUP($I37,Trabajadores!$C$2:$AS$1684,40,FALSE)," ") -> 110091 | Z37: =IFERROR(VLOOKUP(Y37,Centros!$X$2:$Y$228,2,FALSE)," ") -> COLEGIO CLARET -MADRID | AA37: 4 y 5 septiembre | AB37: Fallecimiento nieta Berni | AC37: =IFERROR(VLOOKUP(H37,Centros!$AI$2:$AN$10,6,FALSE),0) -> 72 | AD37: =IF(AC37=70,R37,0) -> 0 | AE37: =IF(AC37=72,R37,0) -> 18 | AF37: =IF(AC37=73,+R37,0) -> 0 | AG37: =+U37 -> 0 | AH37: =IFERROR(VLOOKUP($I37,Trabajadores!$C$3:$AT$1684,44,FALSE),0) -> 19228 | AI37: =IFERROR(VLOOKUP($I37,Trabajadores!$C$3:$AT$1684,2,FALSE),0) -> 989 | AJ37: =IFERROR(VLOOKUP($I37,Trabajadores!$C$3:$AY$1270,21,FALSE),0) -> 50 | AK37: =IFERROR(VLOOKUP($I37,Trabajadores!$C$3:$AN$1684,38,FALSE),0) -> 7.8 | AL37: =IFERROR(VLOOKUP($I37,Trabajadores!$C$3:$AN$1684,28,FALSE),0) -> 99100165012016 | AM37: =IFERROR(VLOOKUP($I37,Trabajadores!$C$3:$AN$1684,19,FALSE),0) -> ASL | AN37: =IFERROR(IF($J37="algadi",VLOOKUP($K37,Centros!$AB$2:$AD$142,2,FALSE),VLOOKUP($K37,Centros!$AB$143:$AD$282,2,FALSE)),0) -> 0 | AO37: =IFERROR(IF($J37="algadi",VLOOKUP($K37,Centros!$AB$2:$AD$142,3,FALSE),VLOOKUP($K37,Centros!$AB$143:$AD$222,3,FALSE)),0) -> 0 | AQ37: =IFERROR(VLOOKUP($AM37,Centros!$AR$2:$AS$405,2,FALSE),0) -> 1.6367812 | AR37: =IFERROR(VLOOKUP($AM37,Centros!$AZ$2:$BA$6,2,FALSE),0) -> 0 | AS37: =IFERROR(VLOOKUP($AM37,Centros!$BE$2:$BF$6,2,FALSE),0) -> 2.05 | BD37: =+X37 -> ALGADI | BE37: INCIDENCIA | BF37: =+E37 -> 9-SEPTIEMBRE | BG37: =+Y37 -> 110091 | BH37: =VLOOKUP(Y37,Hoja1!$A$2:$O$599,14,FALSE) -> 110091 | BI37: =VLOOKUP(BH37,Hoja1!$A$2:$O$599,2,FALSE) -> COLEGIO CLARET -MADRID | BJ37: =+I37 -> HERNANDEZ LIRIANO, DENNI DERN | BK37: =VLOOKUP(BJ37,Trabajadores!$C$3:$AN$3285,14,FALSE) -> 389 | BL37: =VLOOKUP($BJ37,Trabajadores!$C$3:$AN$3285,19,FALSE) -> ASL | BM37: =VLOOKUP($BJ37,Trabajadores!$C$3:$AN$3285,16,FALSE) -> 50 | BN37: =IF($G37="010 Restauración",100%,0%) -> 1 | BO37: =IF($G37="020 Limpieza",100%,0%) -> 0 | BP37: =+BN37+BO37 -> 1 | BR37: =-W37 -> -23.751 | BV37: =+J37 -> ALGADI | BW37: INCIDENCIA | BX37: =+E37 -> 9-SEPTIEMBRE | BY37: =+K37 -> 110091 | BZ37: =VLOOKUP(BY37,Hoja1!$A$2:$O$599,14,FALSE) -> 110091 | CA37: =VLOOKUP(BZ37,Hoja1!$A$2:$O$599,2,FALSE) -> COLEGIO CLARET -MADRID | CB37: =+H37 -> Permiso retribuido | CC37: 888 | CD37: =+BW37 -> INCIDENCIA | CJ37: =+W37 -> 23.751
D38: 945 | E38: 9-SEPTIEMBRE | F38: NO | G38: 010 Restauración | H38: Festivos y Fines de Semana | I38: JIMENEZ GONZALO, SERGIO | J38: ALGADI | K38: 340085 | L38: =IF(W38>0,IF(OR(E38="",F38="",G38="",H38="",I38="",J38="",K38=""),"faltan datos","ok")," ") -> ok | M38: =IFERROR(VLOOKUP(K38,Centros!$E$2:$G$340,2,FALSE)," ") -> CASA MISIONERAS CLARETIANAS | N38: =IF(J38=" "," ",IF(J38=X38," ","Emp Orig/dest. Distinta")) | O38: =IFERROR(VLOOKUP($I38,Trabajadores!$C$3:$AF$1684,19,FALSE)," ") -> h JCoc/Enc | P38: 1 | Q38: 25 | R38: =+P38*Q38 -> 25 | T38: =IF(AL38="99100165012016",AQ38,IF(AL38="28009435011996",AR38,IF(AL38="99010825011997",AS38))) -> 0 | U38: =IF(T38="no corresponde",0,+S38*T38) -> 0 | W38: =+V38*AK38+((+R38+U38)*1.3195) -> 32.9875 | X38: =IFERROR(VLOOKUP($I38,Trabajadores!$C$2:$AS$1684,42,FALSE)," ") -> ALGADI | Y38: =IFERROR(VLOOKUP($I38,Trabajadores!$C$2:$AS$1684,40,FALSE)," ") -> 110091 | Z38: =IFERROR(VLOOKUP(Y38,Centros!$X$2:$Y$228,2,FALSE)," ") -> COLEGIO CLARET -MADRID | AA38: 45884 | AB38: Fata del 15 de agosto en angela figuera | AC38: =IFERROR(VLOOKUP(H38,Centros!$AI$2:$AN$10,6,FALSE),0) -> 70 | AD38: =IF(AC38=70,R38,0) -> 25 | AE38: =IF(AC38=72,R38,0) -> 0 | AF38: =IF(AC38=73,+R38,0) -> 0 | AG38: =+U38 -> 0 | AH38: =IFERROR(VLOOKUP($I38,Trabajadores!$C$3:$AT$1684,44,FALSE),0) -> 19228 | AI38: =IFERROR(VLOOKUP($I38,Trabajadores!$C$3:$AT$1684,2,FALSE),0) -> 274 | AJ38: =IFERROR(VLOOKUP($I38,Trabajadores!$C$3:$AY$1270,21,FALSE),0) -> 50 | AK38: =IFERROR(VLOOKUP($I38,Trabajadores!$C$3:$AN$1684,38,FALSE),0) -> 16.48375 | AL38: =IFERROR(VLOOKUP($I38,Trabajadores!$C$3:$AN$1684,28,FALSE),0) -> 99100165012016 | AM38: =IFERROR(VLOOKUP($I38,Trabajadores!$C$3:$AN$1684,19,FALSE),0) -> h JCoc/Enc | AN38: =IFERROR(IF($J38="algadi",VLOOKUP($K38,Centros!$AB$2:$AD$142,2,FALSE),VLOOKUP($K38,Centros!$AB$143:$AD$282,2,FALSE)),0) -> 0 | AO38: =IFERROR(IF($J38="algadi",VLOOKUP($K38,Centros!$AB$2:$AD$142,3,FALSE),VLOOKUP($K38,Centros!$AB$143:$AD$222,3,FALSE)),0) -> 0 | AQ38: =IFERROR(VLOOKUP($AM38,Centros!$AR$2:$AS$405,2,FALSE),0) -> 0 | AR38: =IFERROR(VLOOKUP($AM38,Centros!$AZ$2:$BA$6,2,FALSE),0) -> 0 | AS38: =IFERROR(VLOOKUP($AM38,Centros!$BE$2:$BF$6,2,FALSE),0) -> 0 | BD38: =+X38 -> ALGADI | BE38: INCIDENCIA | BF38: =+E38 -> 9-SEPTIEMBRE | BG38: =+Y38 -> 110091 | BH38: =VLOOKUP(Y38,Hoja1!$A$2:$O$599,14,FALSE) -> 110091 | BI38: =VLOOKUP(BH38,Hoja1!$A$2:$O$599,2,FALSE) -> COLEGIO CLARET -MADRID | BJ38: =+I38 -> JIMENEZ GONZALO, SERGIO | BK38: =VLOOKUP(BJ38,Trabajadores!$C$3:$AN$3285,14,FALSE) -> 100 | BL38: =VLOOKUP($BJ38,Trabajadores!$C$3:$AN$3285,19,FALSE) -> h JCoc/Enc | BM38: =VLOOKUP($BJ38,Trabajadores!$C$3:$AN$3285,16,FALSE) -> 100 | BN38: =IF($G38="010 Restauración",100%,0%) -> 1 | BO38: =IF($G38="020 Limpieza",100%,0%) -> 0 | BP38: =+BN38+BO38 -> 1 | BR38: =-W38 -> -32.9875 | BV38: =+J38 -> ALGADI | BW38: INCIDENCIA | BX38: =+E38 -> 9-SEPTIEMBRE | BY38: =+K38 -> 340085 | BZ38: =VLOOKUP(BY38,Hoja1!$A$2:$O$599,14,FALSE) -> 340085 | CA38: =VLOOKUP(BZ38,Hoja1!$A$2:$O$599,2,FALSE) -> CASA MISIONERAS CLARETIANAS | CB38: =+H38 -> Festivos y Fines de Semana | CC38: 888 | CD38: =+BW38 -> INCIDENCIA | CJ38: =+W38 -> 32.9875
D39: 945 | E39: 9-SEPTIEMBRE | F39: NO | G39: 010 Restauración | H39: Otros | I39: LOPEZ DE MIGUEL, RAQUEL | J39: ALGADI | K39: 110065 | L39: =IF(W39>0,IF(OR(E39="",F39="",G39="",H39="",I39="",J39="",K39=""),"faltan datos","ok")," ") -> ok | M39: =IFERROR(VLOOKUP(K39,Centros!$E$2:$G$340,2,FALSE)," ") -> COLEGIO SANTA RITA | N39: =IF(J39=" "," ",IF(J39=X39," ","Emp Orig/dest. Distinta")) | O39: =IFERROR(VLOOKUP($I39,Trabajadores!$C$3:$AF$1684,19,FALSE)," ") -> h Cociner@ | P39: 1 | Q39: 100 | R39: =+P39*Q39 -> 100 | T39: =IF(AL39="99100165012016",AQ39,IF(AL39="28009435011996",AR39,IF(AL39="99010825011997",AS39))) -> 1.7437656 | U39: =IF(T39="no corresponde",0,+S39*T39) -> 0 | W39: =+V39*AK39+((+R39+U39)*1.3195) -> 131.95 | X39: =IFERROR(VLOOKUP($I39,Trabajadores!$C$2:$AS$1684,42,FALSE)," ") -> ALGADI | Y39: =IFERROR(VLOOKUP($I39,Trabajadores!$C$2:$AS$1684,40,FALSE)," ") -> 110021 | Z39: =IFERROR(VLOOKUP(Y39,Centros!$X$2:$Y$228,2,FALSE)," ") -> COLEGIO FUNDACION CALDEIRO | AA39: 45930 | AB39: Plus función resp. Cocina | AC39: =IFERROR(VLOOKUP(H39,Centros!$AI$2:$AN$10,6,FALSE),0) -> 72 | AD39: =IF(AC39=70,R39,0) -> 0 | AE39: =IF(AC39=72,R39,0) -> 100 | AF39: =IF(AC39=73,+R39,0) -> 0 | AG39: =+U39 -> 0 | AH39: =IFERROR(VLOOKUP($I39,Trabajadores!$C$3:$AT$1684,44,FALSE),0) -> 19228 | AI39: =IFERROR(VLOOKUP($I39,Trabajadores!$C$3:$AT$1684,2,FALSE),0) -> 150 | AJ39: =IFERROR(VLOOKUP($I39,Trabajadores!$C$3:$AY$1270,21,FALSE),0) -> 20 | AK39: =IFERROR(VLOOKUP($I39,Trabajadores!$C$3:$AN$1684,38,FALSE),0) -> 9.78375 | AL39: =IFERROR(VLOOKUP($I39,Trabajadores!$C$3:$AN$1684,28,FALSE),0) -> 99100165012016 | AM39: =IFERROR(VLOOKUP($I39,Trabajadores!$C$3:$AN$1684,19,FALSE),0) -> h Cociner@ | AN39: =IFERROR(IF($J39="algadi",VLOOKUP($K39,Centros!$AB$2:$AD$142,2,FALSE),VLOOKUP($K39,Centros!$AB$143:$AD$282,2,FALSE)),0) -> 5027 | AO39: =IFERROR(IF($J39="algadi",VLOOKUP($K39,Centros!$AB$2:$AD$142,3,FALSE),VLOOKUP($K39,Centros!$AB$143:$AD$222,3,FALSE)),0) -> 33 | AQ39: =IFERROR(VLOOKUP($AM39,Centros!$AR$2:$AS$405,2,FALSE),0) -> 1.7437656 | AR39: =IFERROR(VLOOKUP($AM39,Centros!$AZ$2:$BA$6,2,FALSE),0) -> 0 | AS39: =IFERROR(VLOOKUP($AM39,Centros!$BE$2:$BF$6,2,FALSE),0) -> 0 | BD39: =+X39 -> ALGADI | BE39: INCIDENCIA | BF39: =+E39 -> 9-SEPTIEMBRE | BG39: =+Y39 -> 110021 | BH39: =VLOOKUP(Y39,Hoja1!$A$2:$O$599,14,FALSE) -> 110021 | BI39: =VLOOKUP(BH39,Hoja1!$A$2:$O$599,2,FALSE) -> COLEGIO FUNDACION CALDEIRO | BJ39: =+I39 -> LOPEZ DE MIGUEL, RAQUEL | BK39: =VLOOKUP(BJ39,Trabajadores!$C$3:$AN$3285,14,FALSE) -> 100 | BL39: =VLOOKUP($BJ39,Trabajadores!$C$3:$AN$3285,19,FALSE) -> h Cociner@ | BM39: =VLOOKUP($BJ39,Trabajadores!$C$3:$AN$3285,16,FALSE) -> 100 | BN39: =IF($G39="010 Restauración",100%,0%) -> 1 | BO39: =IF($G39="020 Limpieza",100%,0%) -> 0 | BP39: =+BN39+BO39 -> 1 | BR39: =-W39 -> -131.95 | BV39: =+J39 -> ALGADI | BW39: INCIDENCIA | BX39: =+E39 -> 9-SEPTIEMBRE | BY39: =+K39 -> 110065 | BZ39: =VLOOKUP(BY39,Hoja1!$A$2:$O$599,14,FALSE) -> 110065 | CA39: =VLOOKUP(BZ39,Hoja1!$A$2:$O$599,2,FALSE) -> COLEGIO SANTA RITA | CB39: =+H39 -> Otros | CC39: 888 | CD39: =+BW39 -> INCIDENCIA | CJ39: =+W39 -> 131.95
D40: 945 | E40: 9-SEPTIEMBRE | F40: NO | G40: 010 Restauración | H40: Festivos y Fines de Semana | I40: LOZANO ROA, ELFFY | J40: ALGADI | K40: 510009 | L40: =IF(W40>0,IF(OR(E40="",F40="",G40="",H40="",I40="",J40="",K40=""),"faltan datos","ok")," ") -> ok | M40: =IFERROR(VLOOKUP(K40,Centros!$E$2:$G$340,2,FALSE)," ") -> HH. TERCIARIAS CAPUCHINAS - EL OLIVO | N40: =IF(J40=" "," ",IF(J40=X40," ","Emp Orig/dest. Distinta")) | O40: =IFERROR(VLOOKUP($I40,Trabajadores!$C$3:$AF$1684,19,FALSE)," ") -> ASL | P40: 4 | Q40: 70 | R40: =+P40*Q40 -> 280 | T40: =IF(AL40="99100165012016",AQ40,IF(AL40="28009435011996",AR40,IF(AL40="99010825011997",AS40))) -> 1.6367812 | U40: =IF(T40="no corresponde",0,+S40*T40) -> 0 | W40: =+V40*AK40+((+R40+U40)*1.3195) -> 369.46 | X40: =IFERROR(VLOOKUP($I40,Trabajadores!$C$2:$AS$1684,42,FALSE)," ") -> ALGADI | Y40: =IFERROR(VLOOKUP($I40,Trabajadores!$C$2:$AS$1684,40,FALSE)," ") -> 110091 | Z40: =IFERROR(VLOOKUP(Y40,Centros!$X$2:$Y$228,2,FALSE)," ") -> COLEGIO CLARET -MADRID | AA40: 13,14,27 y 28 sept´25 | AB40: Fines semana Olivo | AC40: =IFERROR(VLOOKUP(H40,Centros!$AI$2:$AN$10,6,FALSE),0) -> 70 | AD40: =IF(AC40=70,R40,0) -> 280 | AE40: =IF(AC40=72,R40,0) -> 0 | AF40: =IF(AC40=73,+R40,0) -> 0 | AG40: =+U40 -> 0 | AH40: =IFERROR(VLOOKUP($I40,Trabajadores!$C$3:$AT$1684,44,FALSE),0) -> 19228 | AI40: =IFERROR(VLOOKUP($I40,Trabajadores!$C$3:$AT$1684,2,FALSE),0) -> 1993 | AJ40: =IFERROR(VLOOKUP($I40,Trabajadores!$C$3:$AY$1270,21,FALSE),0) -> 50 | AK40: =IFERROR(VLOOKUP($I40,Trabajadores!$C$3:$AN$1684,38,FALSE),0) -> 7.8 | AL40: =IFERROR(VLOOKUP($I40,Trabajadores!$C$3:$AN$1684,28,FALSE),0) -> 99100165012016 | AM40: =IFERROR(VLOOKUP($I40,Trabajadores!$C$3:$AN$1684,19,FALSE),0) -> ASL | AN40: =IFERROR(IF($J40="algadi",VLOOKUP($K40,Centros!$AB$2:$AD$142,2,FALSE),VLOOKUP($K40,Centros!$AB$143:$AD$282,2,FALSE)),0) -> 5027 | AO40: =IFERROR(IF($J40="algadi",VLOOKUP($K40,Centros!$AB$2:$AD$142,3,FALSE),VLOOKUP($K40,Centros!$AB$143:$AD$222,3,FALSE)),0) -> 69 | AQ40: =IFERROR(VLOOKUP($AM40,Centros!$AR$2:$AS$405,2,FALSE),0) -> 1.6367812 | AR40: =IFERROR(VLOOKUP($AM40,Centros!$AZ$2:$BA$6,2,FALSE),0) -> 0 | AS40: =IFERROR(VLOOKUP($AM40,Centros!$BE$2:$BF$6,2,FALSE),0) -> 2.05 | BD40: =+X40 -> ALGADI | BE40: INCIDENCIA | BF40: =+E40 -> 9-SEPTIEMBRE | BG40: =+Y40 -> 110091 | BH40: =VLOOKUP(Y40,Hoja1!$A$2:$O$599,14,FALSE) -> 110091 | BI40: =VLOOKUP(BH40,Hoja1!$A$2:$O$599,2,FALSE) -> COLEGIO CLARET -MADRID | BJ40: =+I40 -> LOZANO ROA, ELFFY | BK40: =VLOOKUP(BJ40,Trabajadores!$C$3:$AN$3285,14,FALSE) -> 389 | BL40: =VLOOKUP($BJ40,Trabajadores!$C$3:$AN$3285,19,FALSE) -> ASL | BM40: =VLOOKUP($BJ40,Trabajadores!$C$3:$AN$3285,16,FALSE) -> 50 | BN40: =IF($G40="010 Restauración",100%,0%) -> 1 | BO40: =IF($G40="020 Limpieza",100%,0%) -> 0 | BP40: =+BN40+BO40 -> 1 | BR40: =-W40 -> -369.46 | BV40: =+J40 -> ALGADI | BW40: INCIDENCIA | BX40: =+E40 -> 9-SEPTIEMBRE | BY40: =+K40 -> 510009 | BZ40: =VLOOKUP(BY40,Hoja1!$A$2:$O$599,14,FALSE) -> 510009 | CA40: =VLOOKUP(BZ40,Hoja1!$A$2:$O$599,2,FALSE) -> HH. TERCIARIAS CAPUCHINAS - EL OLIVO | CB40: =+H40 -> Festivos y Fines de Semana | CC40: 888 | CD40: =+BW40 -> INCIDENCIA | CJ40: =+W40 -> 369.46
D41: 945 | E41: 9-SEPTIEMBRE | F41: SI | G41: 020 Limpieza | H41: Refuerzo | I41: LUNA BRANDAN, NELLY MARV | J41: ALGADI | K41: 110082 | L41: =IF(W41>0,IF(OR(E41="",F41="",G41="",H41="",I41="",J41="",K41=""),"faltan datos","ok")," ") -> ok | M41: =IFERROR(VLOOKUP(K41,Centros!$E$2:$G$340,2,FALSE)," ") -> COL. SAN MIGUEL ARCANGEL | N41: =IF(J41=" "," ",IF(J41=X41," ","Emp Orig/dest. Distinta")) | O41: =IFERROR(VLOOKUP($I41,Trabajadores!$C$3:$AF$1684,19,FALSE)," ") -> ASL | P41: 17 | Q41: 9 | R41: =+P41*Q41 -> 153 | T41: =IF(AL41="99100165012016",AQ41,IF(AL41="28009435011996",AR41,IF(AL41="99010825011997",AS41))) -> 1.6367812 | U41: =IF(T41="no corresponde",0,+S41*T41) -> 0 | W41: =+V41*AK41+((+R41+U41)*1.3195) -> 201.8835 | X41: =IFERROR(VLOOKUP($I41,Trabajadores!$C$2:$AS$1684,42,FALSE)," ") -> ALGADI | Y41: =IFERROR(VLOOKUP($I41,Trabajadores!$C$2:$AS$1684,40,FALSE)," ") -> 110082 | Z41: =IFERROR(VLOOKUP(Y41,Centros!$X$2:$Y$228,2,FALSE)," ") -> COL. SAN MIGUEL ARCANGEL | AA41: 8 al 30 septiembre | AB41: Horas solicitadas cliente limpieza polideportivo | AC41: =IFERROR(VLOOKUP(H41,Centros!$AI$2:$AN$10,6,FALSE),0) -> 72 | AD41: =IF(AC41=70,R41,0) -> 0 | AE41: =IF(AC41=72,R41,0) -> 153 | AF41: =IF(AC41=73,+R41,0) -> 0 | AG41: =+U41 -> 0 | AH41: =IFERROR(VLOOKUP($I41,Trabajadores!$C$3:$AT$1684,44,FALSE),0) -> 19228 | AI41: =IFERROR(VLOOKUP($I41,Trabajadores!$C$3:$AT$1684,2,FALSE),0) -> 1585 | AJ41: =IFERROR(VLOOKUP($I41,Trabajadores!$C$3:$AY$1270,21,FALSE),0) -> 4 | AK41: =IFERROR(VLOOKUP($I41,Trabajadores!$C$3:$AN$1684,38,FALSE),0) -> 7.8342857 | AL41: =IFERROR(VLOOKUP($I41,Trabajadores!$C$3:$AN$1684,28,FALSE),0) -> 99100165012016 | AM41: =IFERROR(VLOOKUP($I41,Trabajadores!$C$3:$AN$1684,19,FALSE),0) -> ASL | AN41: =IFERROR(IF($J41="algadi",VLOOKUP($K41,Centros!$AB$2:$AD$142,2,FALSE),VLOOKUP($K41,Centros!$AB$143:$AD$282,2,FALSE)),0) -> 19228 | AO41: =IFERROR(IF($J41="algadi",VLOOKUP($K41,Centros!$AB$2:$AD$142,3,FALSE),VLOOKUP($K41,Centros!$AB$143:$AD$222,3,FALSE)),0) -> 4 | AQ41: =IFERROR(VLOOKUP($AM41,Centros!$AR$2:$AS$405,2,FALSE),0) -> 1.6367812 | AR41: =IFERROR(VLOOKUP($AM41,Centros!$AZ$2:$BA$6,2,FALSE),0) -> 0 | AS41: =IFERROR(VLOOKUP($AM41,Centros!$BE$2:$BF$6,2,FALSE),0) -> 2.05 | BD41: =+X41 -> ALGADI | BE41: INCIDENCIA | BF41: =+E41 -> 9-SEPTIEMBRE | BG41: =+Y41 -> 110082 | BH41: =VLOOKUP(Y41,Hoja1!$A$2:$O$599,14,FALSE) -> 110082 | BI41: =VLOOKUP(BH41,Hoja1!$A$2:$O$599,2,FALSE) -> COL. SAN MIGUEL ARCANGEL | BJ41: =+I41 -> LUNA BRANDAN, NELLY MARV | BK41: =VLOOKUP(BJ41,Trabajadores!$C$3:$AN$3285,14,FALSE) -> 200 | BL41: =VLOOKUP($BJ41,Trabajadores!$C$3:$AN$3285,19,FALSE) -> ASL | BM41: =VLOOKUP($BJ41,Trabajadores!$C$3:$AN$3285,16,FALSE) -> 87.5 | BN41: =IF($G41="010 Restauración",100%,0%) -> 0 | BO41: =IF($G41="020 Limpieza",100%,0%) -> 1 | BP41: =+BN41+BO41 -> 1 | BR41: =-W41 -> -201.8835 | BV41: =+J41 -> ALGADI | BW41: INCIDENCIA | BX41: =+E41 -> 9-SEPTIEMBRE | BY41: =+K41 -> 110082 | BZ41: =VLOOKUP(BY41,Hoja1!$A$2:$O$599,14,FALSE) -> 110082 | CA41: =VLOOKUP(BZ41,Hoja1!$A$2:$O$599,2,FALSE) -> COL. SAN MIGUEL ARCANGEL | CB41: =+H41 -> Refuerzo | CC41: 888 | CD41: =+BW41 -> INCIDENCIA | CJ41: =+W41 -> 201.8835
D42: 945 | E42: 9-SEPTIEMBRE | F42: SI | G42: 020 Limpieza | H42: Refuerzo | I42: LUNA BRANDAN, NELLY MARV | J42: ALGADI | K42: 110082 | L42: =IF(W42>0,IF(OR(E42="",F42="",G42="",H42="",I42="",J42="",K42=""),"faltan datos","ok")," ") -> ok | M42: =IFERROR(VLOOKUP(K42,Centros!$E$2:$G$340,2,FALSE)," ") -> COL. SAN MIGUEL ARCANGEL | N42: =IF(J42=" "," ",IF(J42=X42," ","Emp Orig/dest. Distinta")) | O42: =IFERROR(VLOOKUP($I42,Trabajadores!$C$3:$AF$1684,19,FALSE)," ") -> ASL | P42: 18 | Q42: 9 | R42: =+P42*Q42 -> 162 | T42: =IF(AL42="99100165012016",AQ42,IF(AL42="28009435011996",AR42,IF(AL42="99010825011997",AS42))) -> 1.6367812 | U42: =IF(T42="no corresponde",0,+S42*T42) -> 0 | W42: =+V42*AK42+((+R42+U42)*1.3195) -> 213.759 | X42: =IFERROR(VLOOKUP($I42,Trabajadores!$C$2:$AS$1684,42,FALSE)," ") -> ALGADI | Y42: =IFERROR(VLOOKUP($I42,Trabajadores!$C$2:$AS$1684,40,FALSE)," ") -> 110082 | Z42: =IFERROR(VLOOKUP(Y42,Centros!$X$2:$Y$228,2,FALSE)," ") -> COL. SAN MIGUEL ARCANGEL | AA42: Agosto´25 | AB42: Refuerzo por NSPP de Nikole (refuerzo limpieza pedido cliente) | AC42: =IFERROR(VLOOKUP(H42,Centros!$AI$2:$AN$10,6,FALSE),0) -> 72 | AD42: =IF(AC42=70,R42,0) -> 0 | AE42: =IF(AC42=72,R42,0) -> 162 | AF42: =IF(AC42=73,+R42,0) -> 0 | AG42: =+U42 -> 0 | AH42: =IFERROR(VLOOKUP($I42,Trabajadores!$C$3:$AT$1684,44,FALSE),0) -> 19228 | AI42: =IFERROR(VLOOKUP($I42,Trabajadores!$C$3:$AT$1684,2,FALSE),0) -> 1585 | AJ42: =IFERROR(VLOOKUP($I42,Trabajadores!$C$3:$AY$1270,21,FALSE),0) -> 4 | AK42: =IFERROR(VLOOKUP($I42,Trabajadores!$C$3:$AN$1684,38,FALSE),0) -> 7.8342857 | AL42: =IFERROR(VLOOKUP($I42,Trabajadores!$C$3:$AN$1684,28,FALSE),0) -> 99100165012016 | AM42: =IFERROR(VLOOKUP($I42,Trabajadores!$C$3:$AN$1684,19,FALSE),0) -> ASL | AN42: =IFERROR(IF($J42="algadi",VLOOKUP($K42,Centros!$AB$2:$AD$142,2,FALSE),VLOOKUP($K42,Centros!$AB$143:$AD$282,2,FALSE)),0) -> 19228 | AO42: =IFERROR(IF($J42="algadi",VLOOKUP($K42,Centros!$AB$2:$AD$142,3,FALSE),VLOOKUP($K42,Centros!$AB$143:$AD$222,3,FALSE)),0) -> 4 | AQ42: =IFERROR(VLOOKUP($AM42,Centros!$AR$2:$AS$405,2,FALSE),0) -> 1.6367812 | AR42: =IFERROR(VLOOKUP($AM42,Centros!$AZ$2:$BA$6,2,FALSE),0) -> 0 | AS42: =IFERROR(VLOOKUP($AM42,Centros!$BE$2:$BF$6,2,FALSE),0) -> 2.05 | BD42: =+X42 -> ALGADI | BE42: INCIDENCIA | BF42: =+E42 -> 9-SEPTIEMBRE | BG42: =+Y42 -> 110082 | BH42: =VLOOKUP(Y42,Hoja1!$A$2:$O$599,14,FALSE) -> 110082 | BI42: =VLOOKUP(BH42,Hoja1!$A$2:$O$599,2,FALSE) -> COL. SAN MIGUEL ARCANGEL | BJ42: =+I42 -> LUNA BRANDAN, NELLY MARV | BK42: =VLOOKUP(BJ42,Trabajadores!$C$3:$AN$3285,14,FALSE) -> 200 | BL42: =VLOOKUP($BJ42,Trabajadores!$C$3:$AN$3285,19,FALSE) -> ASL | BM42: =VLOOKUP($BJ42,Trabajadores!$C$3:$AN$3285,16,FALSE) -> 87.5 | BN42: =IF($G42="010 Restauración",100%,0%) -> 0 | BO42: =IF($G42="020 Limpieza",100%,0%) -> 1 | BP42: =+BN42+BO42 -> 1 | BR42: =-W42 -> -213.759 | BV42: =+J42 -> ALGADI | BW42: INCIDENCIA | BX42: =+E42 -> 9-SEPTIEMBRE | BY42: =+K42 -> 110082 | BZ42: =VLOOKUP(BY42,Hoja1!$A$2:$O$599,14,FALSE) -> 110082 | CA42: =VLOOKUP(BZ42,Hoja1!$A$2:$O$599,2,FALSE) -> COL. SAN MIGUEL ARCANGEL | CB42: =+H42 -> Refuerzo | CC42: 888 | CD42: =+BW42 -> INCIDENCIA | CJ42: =+W42 -> 213.759
D43: 945 | E43: 9-SEPTIEMBRE | F43: NO | G43: 020 Limpieza | H43: Refuerzo | I43: MARTIN AGUADO, ALMUDENA | J43: ALGADI | K43: 110021 | L43: =IF(W43>0,IF(OR(E43="",F43="",G43="",H43="",I43="",J43="",K43=""),"faltan datos","ok")," ") -> ok | M43: =IFERROR(VLOOKUP(K43,Centros!$E$2:$G$340,2,FALSE)," ") -> COLEGIO FUNDACION CALDEIRO | N43: =IF(J43=" "," ",IF(J43=X43," ","Emp Orig/dest. Distinta")) | O43: =IFERROR(VLOOKUP($I43,Trabajadores!$C$3:$AF$1684,19,FALSE)," ") -> h ASL | P43: 15 | Q43: 9 | R43: =+P43*Q43 -> 135 | T43: =IF(AL43="99100165012016",AQ43,IF(AL43="28009435011996",AR43,IF(AL43="99010825011997",AS43))) -> 1.6367812 | U43: =IF(T43="no corresponde",0,+S43*T43) -> 0 | W43: =+V43*AK43+((+R43+U43)*1.3195) -> 178.1325 | X43: =IFERROR(VLOOKUP($I43,Trabajadores!$C$2:$AS$1684,42,FALSE)," ") -> ALGADI | Y43: =IFERROR(VLOOKUP($I43,Trabajadores!$C$2:$AS$1684,40,FALSE)," ") -> 110021 | Z43: =IFERROR(VLOOKUP(Y43,Centros!$X$2:$Y$228,2,FALSE)," ") -> COLEGIO FUNDACION CALDEIRO | AA43: 1 al 5 sept | AB43: Refuerzo limpieza inicio curso (3 horas/día) | AC43: =IFERROR(VLOOKUP(H43,Centros!$AI$2:$AN$10,6,FALSE),0) -> 72 | AD43: =IF(AC43=70,R43,0) -> 0 | AE43: =IF(AC43=72,R43,0) -> 135 | AF43: =IF(AC43=73,+R43,0) -> 0 | AG43: =+U43 -> 0 | AH43: =IFERROR(VLOOKUP($I43,Trabajadores!$C$3:$AT$1684,44,FALSE),0) -> 19228 | AI43: =IFERROR(VLOOKUP($I43,Trabajadores!$C$3:$AT$1684,2,FALSE),0) -> 156 | AJ43: =IFERROR(VLOOKUP($I43,Trabajadores!$C$3:$AY$1270,21,FALSE),0) -> 20 | AK43: =IFERROR(VLOOKUP($I43,Trabajadores!$C$3:$AN$1684,38,FALSE),0) -> 8.974 | AL43: =IFERROR(VLOOKUP($I43,Trabajadores!$C$3:$AN$1684,28,FALSE),0) -> 99100165012016 | AM43: =IFERROR(VLOOKUP($I43,Trabajadores!$C$3:$AN$1684,19,FALSE),0) -> h ASL | AN43: =IFERROR(IF($J43="algadi",VLOOKUP($K43,Centros!$AB$2:$AD$142,2,FALSE),VLOOKUP($K43,Centros!$AB$143:$AD$282,2,FALSE)),0) -> 19228 | AO43: =IFERROR(IF($J43="algadi",VLOOKUP($K43,Centros!$AB$2:$AD$142,3,FALSE),VLOOKUP($K43,Centros!$AB$143:$AD$222,3,FALSE)),0) -> 20 | AQ43: =IFERROR(VLOOKUP($AM43,Centros!$AR$2:$AS$405,2,FALSE),0) -> 1.6367812 | AR43: =IFERROR(VLOOKUP($AM43,Centros!$AZ$2:$BA$6,2,FALSE),0) -> 0 | AS43: =IFERROR(VLOOKUP($AM43,Centros!$BE$2:$BF$6,2,FALSE),0) -> 0 | BD43: =+X43 -> ALGADI | BE43: INCIDENCIA | BF43: =+E43 -> 9-SEPTIEMBRE | BG43: =+Y43 -> 110021 | BH43: =VLOOKUP(Y43,Hoja1!$A$2:$O$599,14,FALSE) -> 110021 | BI43: =VLOOKUP(BH43,Hoja1!$A$2:$O$599,2,FALSE) -> COLEGIO FUNDACION CALDEIRO | BJ43: =+I43 -> MARTIN AGUADO, ALMUDENA | BK43: =VLOOKUP(BJ43,Trabajadores!$C$3:$AN$3285,14,FALSE) -> 300 | BL43: =VLOOKUP($BJ43,Trabajadores!$C$3:$AN$3285,19,FALSE) -> h ASL | BM43: =VLOOKUP($BJ43,Trabajadores!$C$3:$AN$3285,16,FALSE) -> 62.5 | BN43: =IF($G43="010 Restauración",100%,0%) -> 0 | BO43: =IF($G43="020 Limpieza",100%,0%) -> 1 | BP43: =+BN43+BO43 -> 1 | BR43: =-W43 -> -178.1325 | BV43: =+J43 -> ALGADI | BW43: INCIDENCIA | BX43: =+E43 -> 9-SEPTIEMBRE | BY43: =+K43 -> 110021 | BZ43: =VLOOKUP(BY43,Hoja1!$A$2:$O$599,14,FALSE) -> 110021 | CA43: =VLOOKUP(BZ43,Hoja1!$A$2:$O$599,2,FALSE) -> COLEGIO FUNDACION CALDEIRO | CB43: =+H43 -> Refuerzo | CC43: 888 | CD43: =+BW43 -> INCIDENCIA | CJ43: =+W43 -> 178.1325
D44: 945 | E44: 9-SEPTIEMBRE | F44: NO | G44: 020 Limpieza | H44: Refuerzo | I44: MARTIN AGUADO, ALMUDENA | J44: ALGADI | K44: 110021 | L44: =IF(W44>0,IF(OR(E44="",F44="",G44="",H44="",I44="",J44="",K44=""),"faltan datos","ok")," ") -> ok | M44: =IFERROR(VLOOKUP(K44,Centros!$E$2:$G$340,2,FALSE)," ") -> COLEGIO FUNDACION CALDEIRO | N44: =IF(J44=" "," ",IF(J44=X44," ","Emp Orig/dest. Distinta")) | O44: =IFERROR(VLOOKUP($I44,Trabajadores!$C$3:$AF$1684,19,FALSE)," ") -> h ASL | P44: 17 | Q44: 9 | R44: =+P44*Q44 -> 153 | T44: =IF(AL44="99100165012016",AQ44,IF(AL44="28009435011996",AR44,IF(AL44="99010825011997",AS44))) -> 1.6367812 | U44: =IF(T44="no corresponde",0,+S44*T44) -> 0 | W44: =+V44*AK44+((+R44+U44)*1.3195) -> 201.8835 | X44: =IFERROR(VLOOKUP($I44,Trabajadores!$C$2:$AS$1684,42,FALSE)," ") -> ALGADI | Y44: =IFERROR(VLOOKUP($I44,Trabajadores!$C$2:$AS$1684,40,FALSE)," ") -> 110021 | Z44: =IFERROR(VLOOKUP(Y44,Centros!$X$2:$Y$228,2,FALSE)," ") -> COLEGIO FUNDACION CALDEIRO | AA44: 8 al 30 septiembre | AB44: Refuerzo por guardería desde el año pasado (1 hora/día) | AC44: =IFERROR(VLOOKUP(H44,Centros!$AI$2:$AN$10,6,FALSE),0) -> 72 | AD44: =IF(AC44=70,R44,0) -> 0 | AE44: =IF(AC44=72,R44,0) -> 153 | AF44: =IF(AC44=73,+R44,0) -> 0 | AG44: =+U44 -> 0 | AH44: =IFERROR(VLOOKUP($I44,Trabajadores!$C$3:$AT$1684,44,FALSE),0) -> 19228 | AI44: =IFERROR(VLOOKUP($I44,Trabajadores!$C$3:$AT$1684,2,FALSE),0) -> 156 | AJ44: =IFERROR(VLOOKUP($I44,Trabajadores!$C$3:$AY$1270,21,FALSE),0) -> 20 | AK44: =IFERROR(VLOOKUP($I44,Trabajadores!$C$3:$AN$1684,38,FALSE),0) -> 8.974 | AL44: =IFERROR(VLOOKUP($I44,Trabajadores!$C$3:$AN$1684,28,FALSE),0) -> 99100165012016 | AM44: =IFERROR(VLOOKUP($I44,Trabajadores!$C$3:$AN$1684,19,FALSE),0) -> h ASL | AN44: =IFERROR(IF($J44="algadi",VLOOKUP($K44,Centros!$AB$2:$AD$142,2,FALSE),VLOOKUP($K44,Centros!$AB$143:$AD$282,2,FALSE)),0) -> 19228 | AO44: =IFERROR(IF($J44="algadi",VLOOKUP($K44,Centros!$AB$2:$AD$142,3,FALSE),VLOOKUP($K44,Centros!$AB$143:$AD$222,3,FALSE)),0) -> 20 | AQ44: =IFERROR(VLOOKUP($AM44,Centros!$AR$2:$AS$405,2,FALSE),0) -> 1.6367812 | AR44: =IFERROR(VLOOKUP($AM44,Centros!$AZ$2:$BA$6,2,FALSE),0) -> 0 | AS44: =IFERROR(VLOOKUP($AM44,Centros!$BE$2:$BF$6,2,FALSE),0) -> 0 | BD44: =+X44 -> ALGADI | BE44: INCIDENCIA | BF44: =+E44 -> 9-SEPTIEMBRE | BG44: =+Y44 -> 110021 | BH44: =VLOOKUP(Y44,Hoja1!$A$2:$O$599,14,FALSE) -> 110021 | BI44: =VLOOKUP(BH44,Hoja1!$A$2:$O$599,2,FALSE) -> COLEGIO FUNDACION CALDEIRO | BJ44: =+I44 -> MARTIN AGUADO, ALMUDENA | BK44: =VLOOKUP(BJ44,Trabajadores!$C$3:$AN$3285,14,FALSE) -> 300 | BL44: =VLOOKUP($BJ44,Trabajadores!$C$3:$AN$3285,19,FALSE) -> h ASL | BM44: =VLOOKUP($BJ44,Trabajadores!$C$3:$AN$3285,16,FALSE) -> 62.5 | BN44: =IF($G44="010 Restauración",100%,0%) -> 0 | BO44: =IF($G44="020 Limpieza",100%,0%) -> 1 | BP44: =+BN44+BO44 -> 1 | BR44: =-W44 -> -201.8835 | BV44: =+J44 -> ALGADI | BW44: INCIDENCIA | BX44: =+E44 -> 9-SEPTIEMBRE | BY44: =+K44 -> 110021 | BZ44: =VLOOKUP(BY44,Hoja1!$A$2:$O$599,14,FALSE) -> 110021 | CA44: =VLOOKUP(BZ44,Hoja1!$A$2:$O$599,2,FALSE) -> COLEGIO FUNDACION CALDEIRO | CB44: =+H44 -> Refuerzo | CC44: 888 | CD44: =+BW44 -> INCIDENCIA | CJ44: =+W44 -> 201.8835
D45: 945 | E45: 9-SEPTIEMBRE | F45: NO | G45: 010 Restauración | H45: Festivos y Fines de Semana | I45: MARTINEZ RIOS, ELIZABETH | J45: ALGADI | K45: 110065 | L45: =IF(W45>0,IF(OR(E45="",F45="",G45="",H45="",I45="",J45="",K45=""),"faltan datos","ok")," ") -> ok | M45: =IFERROR(VLOOKUP(K45,Centros!$E$2:$G$340,2,FALSE)," ") -> COLEGIO SANTA RITA | N45: =IF(J45=" "," ",IF(J45=X45," ","Emp Orig/dest. Distinta")) | O45: =IFERROR(VLOOKUP($I45,Trabajadores!$C$3:$AF$1684,19,FALSE)," ") -> Ayte Coc | P45: 2 | Q45: 9 | R45: =+P45*Q45 -> 18 | T45: =IF(AL45="99100165012016",AQ45,IF(AL45="28009435011996",AR45,IF(AL45="99010825011997",AS45))) -> 1.6906094 | U45: =IF(T45="no corresponde",0,+S45*T45) -> 0 | W45: =+V45*AK45+((+R45+U45)*1.3195) -> 23.751 | X45: =IFERROR(VLOOKUP($I45,Trabajadores!$C$2:$AS$1684,42,FALSE)," ") -> ALGADI | Y45: =IFERROR(VLOOKUP($I45,Trabajadores!$C$2:$AS$1684,40,FALSE)," ") -> 110082 | Z45: =IFERROR(VLOOKUP(Y45,Centros!$X$2:$Y$228,2,FALSE)," ") -> COL. SAN MIGUEL ARCANGEL | AA45: 45919 | AB45: Conocer comunidad de Santa Rita | AC45: =IFERROR(VLOOKUP(H45,Centros!$AI$2:$AN$10,6,FALSE),0) -> 70 | AD45: =IF(AC45=70,R45,0) -> 18 | AE45: =IF(AC45=72,R45,0) -> 0 | AF45: =IF(AC45=73,+R45,0) -> 0 | AG45: =+U45 -> 0 | AH45: =IFERROR(VLOOKUP($I45,Trabajadores!$C$3:$AT$1684,44,FALSE),0) -> 19228 | AI45: =IFERROR(VLOOKUP($I45,Trabajadores!$C$3:$AT$1684,2,FALSE),0) -> 1858 | AJ45: =IFERROR(VLOOKUP($I45,Trabajadores!$C$3:$AY$1270,21,FALSE),0) -> 4 | AK45: =IFERROR(VLOOKUP($I45,Trabajadores!$C$3:$AN$1684,38,FALSE),0) -> 7.8 | AL45: =IFERROR(VLOOKUP($I45,Trabajadores!$C$3:$AN$1684,28,FALSE),0) -> 99100165012016 | AM45: =IFERROR(VLOOKUP($I45,Trabajadores!$C$3:$AN$1684,19,FALSE),0) -> Ayte Coc | AN45: =IFERROR(IF($J45="algadi",VLOOKUP($K45,Centros!$AB$2:$AD$142,2,FALSE),VLOOKUP($K45,Centros!$AB$143:$AD$282,2,FALSE)),0) -> 5027 | AO45: =IFERROR(IF($J45="algadi",VLOOKUP($K45,Centros!$AB$2:$AD$142,3,FALSE),VLOOKUP($K45,Centros!$AB$143:$AD$222,3,FALSE)),0) -> 33 | AQ45: =IFERROR(VLOOKUP($AM45,Centros!$AR$2:$AS$405,2,FALSE),0) -> 1.6906094 | AR45: =IFERROR(VLOOKUP($AM45,Centros!$AZ$2:$BA$6,2,FALSE),0) -> 0 | AS45: =IFERROR(VLOOKUP($AM45,Centros!$BE$2:$BF$6,2,FALSE),0) -> 0 | BD45: =+X45 -> ALGADI | BE45: INCIDENCIA | BF45: =+E45 -> 9-SEPTIEMBRE | BG45: =+Y45 -> 110082 | BH45: =VLOOKUP(Y45,Hoja1!$A$2:$O$599,14,FALSE) -> 110082 | BI45: =VLOOKUP(BH45,Hoja1!$A$2:$O$599,2,FALSE) -> COL. SAN MIGUEL ARCANGEL | BJ45: =+I45 -> MARTINEZ RIOS, ELIZABETH | BK45: =VLOOKUP(BJ45,Trabajadores!$C$3:$AN$3285,14,FALSE) -> 300 | BL45: =VLOOKUP($BJ45,Trabajadores!$C$3:$AN$3285,19,FALSE) -> Ayte Coc | BM45: =VLOOKUP($BJ45,Trabajadores!$C$3:$AN$3285,16,FALSE) -> 50 | BN45: =IF($G45="010 Restauración",100%,0%) -> 1 | BO45: =IF($G45="020 Limpieza",100%,0%) -> 0 | BP45: =+BN45+BO45 -> 1 | BR45: =-W45 -> -23.751 | BV45: =+J45 -> ALGADI | BW45: INCIDENCIA | BX45: =+E45 -> 9-SEPTIEMBRE | BY45: =+K45 -> 110065 | BZ45: =VLOOKUP(BY45,Hoja1!$A$2:$O$599,14,FALSE) -> 110065 | CA45: =VLOOKUP(BZ45,Hoja1!$A$2:$O$599,2,FALSE) -> COLEGIO SANTA RITA | CB45: =+H45 -> Festivos y Fines de Semana | CC45: 888 | CD45: =+BW45 -> INCIDENCIA | CJ45: =+W45 -> 23.751
D46: 945 | E46: 9-SEPTIEMBRE | F46: NO | G46: 010 Restauración | H46: Festivos y Fines de Semana | I46: MARTINEZ RIOS, ELIZABETH | J46: ALGADI | K46: 110065 | L46: =IF(W46>0,IF(OR(E46="",F46="",G46="",H46="",I46="",J46="",K46=""),"faltan datos","ok")," ") -> ok | M46: =IFERROR(VLOOKUP(K46,Centros!$E$2:$G$340,2,FALSE)," ") -> COLEGIO SANTA RITA | N46: =IF(J46=" "," ",IF(J46=X46," ","Emp Orig/dest. Distinta")) | O46: =IFERROR(VLOOKUP($I46,Trabajadores!$C$3:$AF$1684,19,FALSE)," ") -> Ayte Coc | P46: 2 | Q46: 72.42 | R46: =+P46*Q46 -> 144.84 | T46: =IF(AL46="99100165012016",AQ46,IF(AL46="28009435011996",AR46,IF(AL46="99010825011997",AS46))) -> 1.6906094 | U46: =IF(T46="no corresponde",0,+S46*T46) -> 0 | W46: =+V46*AK46+((+R46+U46)*1.3195) -> 191.11638 | X46: =IFERROR(VLOOKUP($I46,Trabajadores!$C$2:$AS$1684,42,FALSE)," ") -> ALGADI | Y46: =IFERROR(VLOOKUP($I46,Trabajadores!$C$2:$AS$1684,40,FALSE)," ") -> 110082 | Z46: =IFERROR(VLOOKUP(Y46,Centros!$X$2:$Y$228,2,FALSE)," ") -> COL. SAN MIGUEL ARCANGEL | AA46: 20 y 21 septiembre | AB46: Comunidad Santa Rita | AC46: =IFERROR(VLOOKUP(H46,Centros!$AI$2:$AN$10,6,FALSE),0) -> 70 | AD46: =IF(AC46=70,R46,0) -> 144.84 | AE46: =IF(AC46=72,R46,0) -> 0 | AF46: =IF(AC46=73,+R46,0) -> 0 | AG46: =+U46 -> 0 | AH46: =IFERROR(VLOOKUP($I46,Trabajadores!$C$3:$AT$1684,44,FALSE),0) -> 19228 | AI46: =IFERROR(VLOOKUP($I46,Trabajadores!$C$3:$AT$1684,2,FALSE),0) -> 1858 | AJ46: =IFERROR(VLOOKUP($I46,Trabajadores!$C$3:$AY$1270,21,FALSE),0) -> 4 | AK46: =IFERROR(VLOOKUP($I46,Trabajadores!$C$3:$AN$1684,38,FALSE),0) -> 7.8 | AL46: =IFERROR(VLOOKUP($I46,Trabajadores!$C$3:$AN$1684,28,FALSE),0) -> 99100165012016 | AM46: =IFERROR(VLOOKUP($I46,Trabajadores!$C$3:$AN$1684,19,FALSE),0) -> Ayte Coc | AN46: =IFERROR(IF($J46="algadi",VLOOKUP($K46,Centros!$AB$2:$AD$142,2,FALSE),VLOOKUP($K46,Centros!$AB$143:$AD$282,2,FALSE)),0) -> 5027 | AO46: =IFERROR(IF($J46="algadi",VLOOKUP($K46,Centros!$AB$2:$AD$142,3,FALSE),VLOOKUP($K46,Centros!$AB$143:$AD$222,3,FALSE)),0) -> 33 | AQ46: =IFERROR(VLOOKUP($AM46,Centros!$AR$2:$AS$405,2,FALSE),0) -> 1.6906094 | AR46: =IFERROR(VLOOKUP($AM46,Centros!$AZ$2:$BA$6,2,FALSE),0) -> 0 | AS46: =IFERROR(VLOOKUP($AM46,Centros!$BE$2:$BF$6,2,FALSE),0) -> 0 | BD46: =+X46 -> ALGADI | BE46: INCIDENCIA | BF46: =+E46 -> 9-SEPTIEMBRE | BG46: =+Y46 -> 110082 | BH46: =VLOOKUP(Y46,Hoja1!$A$2:$O$599,14,FALSE) -> 110082 | BI46: =VLOOKUP(BH46,Hoja1!$A$2:$O$599,2,FALSE) -> COL. SAN MIGUEL ARCANGEL | BJ46: =+I46 -> MARTINEZ RIOS, ELIZABETH | BK46: =VLOOKUP(BJ46,Trabajadores!$C$3:$AN$3285,14,FALSE) -> 300 | BL46: =VLOOKUP($BJ46,Trabajadores!$C$3:$AN$3285,19,FALSE) -> Ayte Coc | BM46: =VLOOKUP($BJ46,Trabajadores!$C$3:$AN$3285,16,FALSE) -> 50 | BN46: =IF($G46="010 Restauración",100%,0%) -> 1 | BO46: =IF($G46="020 Limpieza",100%,0%) -> 0 | BP46: =+BN46+BO46 -> 1 | BR46: =-W46 -> -191.11638 | BV46: =+J46 -> ALGADI | BW46: INCIDENCIA | BX46: =+E46 -> 9-SEPTIEMBRE | BY46: =+K46 -> 110065 | BZ46: =VLOOKUP(BY46,Hoja1!$A$2:$O$599,14,FALSE) -> 110065 | CA46: =VLOOKUP(BZ46,Hoja1!$A$2:$O$599,2,FALSE) -> COLEGIO SANTA RITA | CB46: =+H46 -> Festivos y Fines de Semana | CC46: 888 | CD46: =+BW46 -> INCIDENCIA | CJ46: =+W46 -> 191.11638
D47: 945 | E47: 9-SEPTIEMBRE | F47: NO | G47: 010 Restauración | H47: Permiso retribuido | I47: LOPEZ GALLEGO, SONIA | J47: ALGADI | K47: 110030 | L47: =IF(W47>0,IF(OR(E47="",F47="",G47="",H47="",I47="",J47="",K47=""),"faltan datos","ok")," ") -> ok | M47: =IFERROR(VLOOKUP(K47,Centros!$E$2:$G$340,2,FALSE)," ") -> COLEGIO INMACULADA | N47: =IF(J47=" "," ",IF(J47=X47," ","Emp Orig/dest. Distinta")) | O47: =IFERROR(VLOOKUP($I47,Trabajadores!$C$3:$AF$1684,19,FALSE)," ") -> ASL | P47: 1.25 | Q47: 9 | R47: =+P47*Q47 -> 11.25 | T47: =IF(AL47="99100165012016",AQ47,IF(AL47="28009435011996",AR47,IF(AL47="99010825011997",AS47))) -> 1.6367812 | U47: =IF(T47="no corresponde",0,+S47*T47) -> 0 | W47: =+V47*AK47+((+R47+U47)*1.3195) -> 14.844375 | X47: =IFERROR(VLOOKUP($I47,Trabajadores!$C$2:$AS$1684,42,FALSE)," ") -> ALGADI | Y47: =IFERROR(VLOOKUP($I47,Trabajadores!$C$2:$AS$1684,40,FALSE)," ") -> 110030 | Z47: =IFERROR(VLOOKUP(Y47,Centros!$X$2:$Y$228,2,FALSE)," ") -> COLEGIO INMACULADA | AA47: 45905 | AB47: No sustitución de Mildred Mogollón | AC47: =IFERROR(VLOOKUP(H47,Centros!$AI$2:$AN$10,6,FALSE),0) -> 72 | AD47: =IF(AC47=70,R47,0) -> 0 | AE47: =IF(AC47=72,R47,0) -> 11.25 | AF47: =IF(AC47=73,+R47,0) -> 0 | AG47: =+U47 -> 0 | AH47: =IFERROR(VLOOKUP($I47,Trabajadores!$C$3:$AT$1684,44,FALSE),0) -> 19228 | AI47: =IFERROR(VLOOKUP($I47,Trabajadores!$C$3:$AT$1684,2,FALSE),0) -> 206 | AJ47: =IFERROR(VLOOKUP($I47,Trabajadores!$C$3:$AY$1270,21,FALSE),0) -> 36 | AK47: =IFERROR(VLOOKUP($I47,Trabajadores!$C$3:$AN$1684,38,FALSE),0) -> 7.8 | AL47: =IFERROR(VLOOKUP($I47,Trabajadores!$C$3:$AN$1684,28,FALSE),0) -> 99100165012016 | AM47: =IFERROR(VLOOKUP($I47,Trabajadores!$C$3:$AN$1684,19,FALSE),0) -> ASL | AN47: =IFERROR(IF($J47="algadi",VLOOKUP($K47,Centros!$AB$2:$AD$142,2,FALSE),VLOOKUP($K47,Centros!$AB$143:$AD$282,2,FALSE)),0) -> 19228 | AO47: =IFERROR(IF($J47="algadi",VLOOKUP($K47,Centros!$AB$2:$AD$142,3,FALSE),VLOOKUP($K47,Centros!$AB$143:$AD$222,3,FALSE)),0) -> 36 | AQ47: =IFERROR(VLOOKUP($AM47,Centros!$AR$2:$AS$405,2,FALSE),0) -> 1.6367812 | AR47: =IFERROR(VLOOKUP($AM47,Centros!$AZ$2:$BA$6,2,FALSE),0) -> 0 | AS47: =IFERROR(VLOOKUP($AM47,Centros!$BE$2:$BF$6,2,FALSE),0) -> 2.05 | BD47: =+X47 -> ALGADI | BE47: INCIDENCIA | BF47: =+E47 -> 9-SEPTIEMBRE | BG47: =+Y47 -> 110030 | BH47: =VLOOKUP(Y47,Hoja1!$A$2:$O$599,14,FALSE) -> 110030 | BI47: =VLOOKUP(BH47,Hoja1!$A$2:$O$599,2,FALSE) -> COLEGIO INMACULADA | BJ47: =+I47 -> LOPEZ GALLEGO, SONIA | BK47: =VLOOKUP(BJ47,Trabajadores!$C$3:$AN$3285,14,FALSE) -> 300 | BL47: =VLOOKUP($BJ47,Trabajadores!$C$3:$AN$3285,19,FALSE) -> ASL | BM47: =VLOOKUP($BJ47,Trabajadores!$C$3:$AN$3285,16,FALSE) -> 37.5 | BN47: =IF($G47="010 Restauración",100%,0%) -> 1 | BO47: =IF($G47="020 Limpieza",100%,0%) -> 0 | BP47: =+BN47+BO47 -> 1 | BR47: =-W47 -> -14.844375 | BV47: =+J47 -> ALGADI | BW47: INCIDENCIA | BX47: =+E47 -> 9-SEPTIEMBRE | BY47: =+K47 -> 110030 | BZ47: =VLOOKUP(BY47,Hoja1!$A$2:$O$599,14,FALSE) -> 110030 | CA47: =VLOOKUP(BZ47,Hoja1!$A$2:$O$599,2,FALSE) -> COLEGIO INMACULADA | CB47: =+H47 -> Permiso retribuido | CC47: 888 | CD47: =+BW47 -> INCIDENCIA | CJ47: =+W47 -> 14.844375
D48: 945 | E48: 9-SEPTIEMBRE | F48: NO | G48: 010 Restauración | H48: Festivos y Fines de Semana | I48: OBANDO OLIVAS, INDRANY | J48: ALGADI | K48: 400020 | L48: =IF(W48>0,IF(OR(E48="",F48="",G48="",H48="",I48="",J48="",K48=""),"faltan datos","ok")," ") -> ok | M48: =IFERROR(VLOOKUP(K48,Centros!$E$2:$G$340,2,FALSE)," ") -> HOGAR INFANTIL LUIS AMIGO | N48: =IF(J48=" "," ",IF(J48=X48," ","Emp Orig/dest. Distinta")) | O48: =IFERROR(VLOOKUP($I48,Trabajadores!$C$3:$AF$1684,19,FALSE)," ") -> ASL | P48: 1 | Q48: 45 | R48: =+P48*Q48 -> 45 | T48: =IF(AL48="99100165012016",AQ48,IF(AL48="28009435011996",AR48,IF(AL48="99010825011997",AS48))) -> 1.6367812 | U48: =IF(T48="no corresponde",0,+S48*T48) -> 0 | W48: =+V48*AK48+((+R48+U48)*1.3195) -> 59.3775 | X48: =IFERROR(VLOOKUP($I48,Trabajadores!$C$2:$AS$1684,42,FALSE)," ") -> ALGADI | Y48: =IFERROR(VLOOKUP($I48,Trabajadores!$C$2:$AS$1684,40,FALSE)," ") -> 510002 | Z48: =IFERROR(VLOOKUP(Y48,Centros!$X$2:$Y$228,2,FALSE)," ") -> DOMINICAS MISIONERAS DE LA SAGRADA FAMILIA | AA48: 45921 | AB48: Domingo Luis amigó | AC48: =IFERROR(VLOOKUP(H48,Centros!$AI$2:$AN$10,6,FALSE),0) -> 70 | AD48: =IF(AC48=70,R48,0) -> 45 | AE48: =IF(AC48=72,R48,0) -> 0 | AF48: =IF(AC48=73,+R48,0) -> 0 | AG48: =+U48 -> 0 | AH48: =IFERROR(VLOOKUP($I48,Trabajadores!$C$3:$AT$1684,44,FALSE),0) -> 19228 | AI48: =IFERROR(VLOOKUP($I48,Trabajadores!$C$3:$AT$1684,2,FALSE),0) -> 1351 | AJ48: =IFERROR(VLOOKUP($I48,Trabajadores!$C$3:$AY$1270,21,FALSE),0) -> 108 | AK48: =IFERROR(VLOOKUP($I48,Trabajadores!$C$3:$AN$1684,38,FALSE),0) -> 7.8055556 | AL48: =IFERROR(VLOOKUP($I48,Trabajadores!$C$3:$AN$1684,28,FALSE),0) -> 99100165012016 | AM48: =IFERROR(VLOOKUP($I48,Trabajadores!$C$3:$AN$1684,19,FALSE),0) -> ASL | AN48: =IFERROR(IF($J48="algadi",VLOOKUP($K48,Centros!$AB$2:$AD$142,2,FALSE),VLOOKUP($K48,Centros!$AB$143:$AD$282,2,FALSE)),0) -> 5027 | AO48: =IFERROR(IF($J48="algadi",VLOOKUP($K48,Centros!$AB$2:$AD$142,3,FALSE),VLOOKUP($K48,Centros!$AB$143:$AD$222,3,FALSE)),0) -> 68 | AQ48: =IFERROR(VLOOKUP($AM48,Centros!$AR$2:$AS$405,2,FALSE),0) -> 1.6367812 | AR48: =IFERROR(VLOOKUP($AM48,Centros!$AZ$2:$BA$6,2,FALSE),0) -> 0 | AS48: =IFERROR(VLOOKUP($AM48,Centros!$BE$2:$BF$6,2,FALSE),0) -> 2.05 | BD48: =+X48 -> ALGADI | BE48: INCIDENCIA | BF48: =+E48 -> 9-SEPTIEMBRE | BG48: =+Y48 -> 510002 | BH48: =VLOOKUP(Y48,Hoja1!$A$2:$O$599,14,FALSE) -> 510002 | BI48: =VLOOKUP(BH48,Hoja1!$A$2:$O$599,2,FALSE) -> DOMINICAS MISIONERAS DE LA SAGRADA FAMILIA | BJ48: =+I48 -> OBANDO OLIVAS, INDRANY | BK48: =VLOOKUP(BJ48,Trabajadores!$C$3:$AN$3285,14,FALSE) -> 200 | BL48: =VLOOKUP($BJ48,Trabajadores!$C$3:$AN$3285,19,FALSE) -> ASL | BM48: =VLOOKUP($BJ48,Trabajadores!$C$3:$AN$3285,16,FALSE) -> 90 | BN48: =IF($G48="010 Restauración",100%,0%) -> 1 | BO48: =IF($G48="020 Limpieza",100%,0%) -> 0 | BP48: =+BN48+BO48 -> 1 | BR48: =-W48 -> -59.3775 | BV48: =+J48 -> ALGADI | BW48: INCIDENCIA | BX48: =+E48 -> 9-SEPTIEMBRE | BY48: =+K48 -> 400020 | BZ48: =VLOOKUP(BY48,Hoja1!$A$2:$O$599,14,FALSE) -> 400020 | CA48: =VLOOKUP(BZ48,Hoja1!$A$2:$O$599,2,FALSE) -> HOGAR INFANTIL LUIS AMIGO | CB48: =+H48 -> Festivos y Fines de Semana | CC48: 888 | CD48: =+BW48 -> INCIDENCIA | CJ48: =+W48 -> 59.3775
D49: 945 | E49: 9-SEPTIEMBRE | F49: SI | G49: 010 Restauración | H49: Festivos y Fines de Semana | I49: PEÑA CARBAJAL, AGRIPINA | J49: ALGADI | K49: 340085 | L49: =IF(W49>0,IF(OR(E49="",F49="",G49="",H49="",I49="",J49="",K49=""),"faltan datos","ok")," ") -> ok | M49: =IFERROR(VLOOKUP(K49,Centros!$E$2:$G$340,2,FALSE)," ") -> CASA MISIONERAS CLARETIANAS | N49: =IF(J49=" "," ",IF(J49=X49," ","Emp Orig/dest. Distinta")) | O49: =IFERROR(VLOOKUP($I49,Trabajadores!$C$3:$AF$1684,19,FALSE)," ") -> Cociner@ | P49: 1 | Q49: 80 | R49: =+P49*Q49 -> 80 | T49: =IF(AL49="99100165012016",AQ49,IF(AL49="28009435011996",AR49,IF(AL49="99010825011997",AS49))) -> 1.7437656 | U49: =IF(T49="no corresponde",0,+S49*T49) -> 0 | W49: =+V49*AK49+((+R49+U49)*1.3195) -> 105.56 | X49: =IFERROR(VLOOKUP($I49,Trabajadores!$C$2:$AS$1684,42,FALSE)," ") -> ALGADI | Y49: =IFERROR(VLOOKUP($I49,Trabajadores!$C$2:$AS$1684,40,FALSE)," ") -> 340013 | Z49: =IFERROR(VLOOKUP(Y49,Centros!$X$2:$Y$228,2,FALSE)," ") -> CLARETIANOS BUEN SUCESO | AA49: 45928 | AB49: Angela Figuera | AC49: =IFERROR(VLOOKUP(H49,Centros!$AI$2:$AN$10,6,FALSE),0) -> 70 | AD49: =IF(AC49=70,R49,0) -> 80 | AE49: =IF(AC49=72,R49,0) -> 0 | AF49: =IF(AC49=73,+R49,0) -> 0 | AG49: =+U49 -> 0 | AH49: =IFERROR(VLOOKUP($I49,Trabajadores!$C$3:$AT$1684,44,FALSE),0) -> 19228 | AI49: =IFERROR(VLOOKUP($I49,Trabajadores!$C$3:$AT$1684,2,FALSE),0) -> 955 | AJ49: =IFERROR(VLOOKUP($I49,Trabajadores!$C$3:$AY$1270,21,FALSE),0) -> 74 | AK49: =IFERROR(VLOOKUP($I49,Trabajadores!$C$3:$AN$1684,38,FALSE),0) -> 7.60125 | AL49: =IFERROR(VLOOKUP($I49,Trabajadores!$C$3:$AN$1684,28,FALSE),0) -> 99100165012016 | AM49: =IFERROR(VLOOKUP($I49,Trabajadores!$C$3:$AN$1684,19,FALSE),0) -> Cociner@ | AN49: =IFERROR(IF($J49="algadi",VLOOKUP($K49,Centros!$AB$2:$AD$142,2,FALSE),VLOOKUP($K49,Centros!$AB$143:$AD$282,2,FALSE)),0) -> 0 | AO49: =IFERROR(IF($J49="algadi",VLOOKUP($K49,Centros!$AB$2:$AD$142,3,FALSE),VLOOKUP($K49,Centros!$AB$143:$AD$222,3,FALSE)),0) -> 0 | AQ49: =IFERROR(VLOOKUP($AM49,Centros!$AR$2:$AS$405,2,FALSE),0) -> 1.7437656 | AR49: =IFERROR(VLOOKUP($AM49,Centros!$AZ$2:$BA$6,2,FALSE),0) -> 2.32225 | AS49: =IFERROR(VLOOKUP($AM49,Centros!$BE$2:$BF$6,2,FALSE),0) -> 0 | BD49: =+X49 -> ALGADI | BE49: INCIDENCIA | BF49: =+E49 -> 9-SEPTIEMBRE | BG49: =+Y49 -> 340013 | BH49: =VLOOKUP(Y49,Hoja1!$A$2:$O$599,14,FALSE) -> 340013 | BI49: =VLOOKUP(BH49,Hoja1!$A$2:$O$599,2,FALSE) -> CLARETIANOS BUEN SUCESO | BJ49: =+I49 -> PEÑA CARBAJAL, AGRIPINA | BK49: =VLOOKUP(BJ49,Trabajadores!$C$3:$AN$3285,14,FALSE) -> 100 | BL49: =VLOOKUP($BJ49,Trabajadores!$C$3:$AN$3285,19,FALSE) -> Cociner@ | BM49: =VLOOKUP($BJ49,Trabajadores!$C$3:$AN$3285,16,FALSE) -> 100 | BN49: =IF($G49="010 Restauración",100%,0%) -> 1 | BO49: =IF($G49="020 Limpieza",100%,0%) -> 0 | BP49: =+BN49+BO49 -> 1 | BR49: =-W49 -> -105.56 | BV49: =+J49 -> ALGADI | BW49: INCIDENCIA | BX49: =+E49 -> 9-SEPTIEMBRE | BY49: =+K49 -> 340085 | BZ49: =VLOOKUP(BY49,Hoja1!$A$2:$O$599,14,FALSE) -> 340085 | CA49: =VLOOKUP(BZ49,Hoja1!$A$2:$O$599,2,FALSE) -> CASA MISIONERAS CLARETIANAS | CB49: =+H49 -> Festivos y Fines de Semana | CC49: 888 | CD49: =+BW49 -> INCIDENCIA | CJ49: =+W49 -> 105.56
D50: 945 | E50: 9-SEPTIEMBRE | F50: NO | G50: 010 Restauración | H50: Permiso retribuido | I50: RIOFRIO RIOFRIO, LUCY | J50: ALGADI | K50: 110030 | L50: =IF(W50>0,IF(OR(E50="",F50="",G50="",H50="",I50="",J50="",K50=""),"faltan datos","ok")," ") -> ok | M50: =IFERROR(VLOOKUP(K50,Centros!$E$2:$G$340,2,FALSE)," ") -> COLEGIO INMACULADA | N50: =IF(J50=" "," ",IF(J50=X50," ","Emp Orig/dest. Distinta")) | O50: =IFERROR(VLOOKUP($I50,Trabajadores!$C$3:$AF$1684,19,FALSE)," ") -> h Cociner@ | P50: 1.25 | Q50: 11 | R50: =+P50*Q50 -> 13.75 | T50: =IF(AL50="99100165012016",AQ50,IF(AL50="28009435011996",AR50,IF(AL50="99010825011997",AS50))) -> 1.7437656 | U50: =IF(T50="no corresponde",0,+S50*T50) -> 0 | W50: =+V50*AK50+((+R50+U50)*1.3195) -> 18.143125 | X50: =IFERROR(VLOOKUP($I50,Trabajadores!$C$2:$AS$1684,42,FALSE)," ") -> ALGADI | Y50: =IFERROR(VLOOKUP($I50,Trabajadores!$C$2:$AS$1684,40,FALSE)," ") -> 110030 | Z50: =IFERROR(VLOOKUP(Y50,Centros!$X$2:$Y$228,2,FALSE)," ") -> COLEGIO INMACULADA | AA50: 45905 | AB50: No sustitución de Mildred Mogollón | AC50: =IFERROR(VLOOKUP(H50,Centros!$AI$2:$AN$10,6,FALSE),0) -> 72 | AD50: =IF(AC50=70,R50,0) -> 0 | AE50: =IF(AC50=72,R50,0) -> 13.75 | AF50: =IF(AC50=73,+R50,0) -> 0 | AG50: =+U50 -> 0 | AH50: =IFERROR(VLOOKUP($I50,Trabajadores!$C$3:$AT$1684,44,FALSE),0) -> 19228 | AI50: =IFERROR(VLOOKUP($I50,Trabajadores!$C$3:$AT$1684,2,FALSE),0) -> 183 | AJ50: =IFERROR(VLOOKUP($I50,Trabajadores!$C$3:$AY$1270,21,FALSE),0) -> 36 | AK50: =IFERROR(VLOOKUP($I50,Trabajadores!$C$3:$AN$1684,38,FALSE),0) -> 9.8775 | AL50: =IFERROR(VLOOKUP($I50,Trabajadores!$C$3:$AN$1684,28,FALSE),0) -> 99100165012016 | AM50: =IFERROR(VLOOKUP($I50,Trabajadores!$C$3:$AN$1684,19,FALSE),0) -> h Cociner@ | AN50: =IFERROR(IF($J50="algadi",VLOOKUP($K50,Centros!$AB$2:$AD$142,2,FALSE),VLOOKUP($K50,Centros!$AB$143:$AD$282,2,FALSE)),0) -> 19228 | AO50: =IFERROR(IF($J50="algadi",VLOOKUP($K50,Centros!$AB$2:$AD$142,3,FALSE),VLOOKUP($K50,Centros!$AB$143:$AD$222,3,FALSE)),0) -> 36 | AQ50: =IFERROR(VLOOKUP($AM50,Centros!$AR$2:$AS$405,2,FALSE),0) -> 1.7437656 | AR50: =IFERROR(VLOOKUP($AM50,Centros!$AZ$2:$BA$6,2,FALSE),0) -> 0 | AS50: =IFERROR(VLOOKUP($AM50,Centros!$BE$2:$BF$6,2,FALSE),0) -> 0 | BD50: =+X50 -> ALGADI | BE50: INCIDENCIA | BF50: =+E50 -> 9-SEPTIEMBRE | BG50: =+Y50 -> 110030 | BH50: =VLOOKUP(Y50,Hoja1!$A$2:$O$599,14,FALSE) -> 110030 | BI50: =VLOOKUP(BH50,Hoja1!$A$2:$O$599,2,FALSE) -> COLEGIO INMACULADA | BJ50: =+I50 -> RIOFRIO RIOFRIO, LUCY | BK50: =VLOOKUP(BJ50,Trabajadores!$C$3:$AN$3285,14,FALSE) -> 300 | BL50: =VLOOKUP($BJ50,Trabajadores!$C$3:$AN$3285,19,FALSE) -> h Cociner@ | BM50: =VLOOKUP($BJ50,Trabajadores!$C$3:$AN$3285,16,FALSE) -> 100 | BN50: =IF($G50="010 Restauración",100%,0%) -> 1 | BO50: =IF($G50="020 Limpieza",100%,0%) -> 0 | BP50: =+BN50+BO50 -> 1 | BR50: =-W50 -> -18.143125 | BV50: =+J50 -> ALGADI | BW50: INCIDENCIA | BX50: =+E50 -> 9-SEPTIEMBRE | BY50: =+K50 -> 110030 | BZ50: =VLOOKUP(BY50,Hoja1!$A$2:$O$599,14,FALSE) -> 110030 | CA50: =VLOOKUP(BZ50,Hoja1!$A$2:$O$599,2,FALSE) -> COLEGIO INMACULADA | CB50: =+H50 -> Permiso retribuido | CC50: 888 | CD50: =+BW50 -> INCIDENCIA | CJ50: =+W50 -> 18.143125
D51: 945 | E51: 9-SEPTIEMBRE | F51: NO | G51: 010 Restauración | H51: Festivos y Fines de Semana | I51: RIOFRIO RIOFRIO, LUCY | J51: ALGADI | K51: 110030 | L51: =IF(W51>0,IF(OR(E51="",F51="",G51="",H51="",I51="",J51="",K51=""),"faltan datos","ok")," ") -> ok | M51: =IFERROR(VLOOKUP(K51,Centros!$E$2:$G$340,2,FALSE)," ") -> COLEGIO INMACULADA | N51: =IF(J51=" "," ",IF(J51=X51," ","Emp Orig/dest. Distinta")) | O51: =IFERROR(VLOOKUP($I51,Trabajadores!$C$3:$AF$1684,19,FALSE)," ") -> h Cociner@ | P51: 1 | Q51: 82.5 | R51: =+P51*Q51 -> 82.5 | T51: =IF(AL51="99100165012016",AQ51,IF(AL51="28009435011996",AR51,IF(AL51="99010825011997",AS51))) -> 1.7437656 | U51: =IF(T51="no corresponde",0,+S51*T51) -> 0 | W51: =+V51*AK51+((+R51+U51)*1.3195) -> 108.85875 | X51: =IFERROR(VLOOKUP($I51,Trabajadores!$C$2:$AS$1684,42,FALSE)," ") -> ALGADI | Y51: =IFERROR(VLOOKUP($I51,Trabajadores!$C$2:$AS$1684,40,FALSE)," ") -> 110030 | Z51: =IFERROR(VLOOKUP(Y51,Centros!$X$2:$Y$228,2,FALSE)," ") -> COLEGIO INMACULADA | AA51: 45920 | AB51: 1/2 especial y 1/2 ASL | AC51: =IFERROR(VLOOKUP(H51,Centros!$AI$2:$AN$10,6,FALSE),0) -> 70 | AD51: =IF(AC51=70,R51,0) -> 82.5 | AE51: =IF(AC51=72,R51,0) -> 0 | AF51: =IF(AC51=73,+R51,0) -> 0 | AG51: =+U51 -> 0 | AH51: =IFERROR(VLOOKUP($I51,Trabajadores!$C$3:$AT$1684,44,FALSE),0) -> 19228 | AI51: =IFERROR(VLOOKUP($I51,Trabajadores!$C$3:$AT$1684,2,FALSE),0) -> 183 | AJ51: =IFERROR(VLOOKUP($I51,Trabajadores!$C$3:$AY$1270,21,FALSE),0) -> 36 | AK51: =IFERROR(VLOOKUP($I51,Trabajadores!$C$3:$AN$1684,38,FALSE),0) -> 9.8775 | AL51: =IFERROR(VLOOKUP($I51,Trabajadores!$C$3:$AN$1684,28,FALSE),0) -> 99100165012016 | AM51: =IFERROR(VLOOKUP($I51,Trabajadores!$C$3:$AN$1684,19,FALSE),0) -> h Cociner@ | AN51: =IFERROR(IF($J51="algadi",VLOOKUP($K51,Centros!$AB$2:$AD$142,2,FALSE),VLOOKUP($K51,Centros!$AB$143:$AD$282,2,FALSE)),0) -> 19228 | AO51: =IFERROR(IF($J51="algadi",VLOOKUP($K51,Centros!$AB$2:$AD$142,3,FALSE),VLOOKUP($K51,Centros!$AB$143:$AD$222,3,FALSE)),0) -> 36 | AQ51: =IFERROR(VLOOKUP($AM51,Centros!$AR$2:$AS$405,2,FALSE),0) -> 1.7437656 | AR51: =IFERROR(VLOOKUP($AM51,Centros!$AZ$2:$BA$6,2,FALSE),0) -> 0 | AS51: =IFERROR(VLOOKUP($AM51,Centros!$BE$2:$BF$6,2,FALSE),0) -> 0 | BD51: =+X51 -> ALGADI | BE51: INCIDENCIA | BF51: =+E51 -> 9-SEPTIEMBRE | BG51: =+Y51 -> 110030 | BH51: =VLOOKUP(Y51,Hoja1!$A$2:$O$599,14,FALSE) -> 110030 | BI51: =VLOOKUP(BH51,Hoja1!$A$2:$O$599,2,FALSE) -> COLEGIO INMACULADA | BJ51: =+I51 -> RIOFRIO RIOFRIO, LUCY | BK51: =VLOOKUP(BJ51,Trabajadores!$C$3:$AN$3285,14,FALSE) -> 300 | BL51: =VLOOKUP($BJ51,Trabajadores!$C$3:$AN$3285,19,FALSE) -> h Cociner@ | BM51: =VLOOKUP($BJ51,Trabajadores!$C$3:$AN$3285,16,FALSE) -> 100 | BN51: =IF($G51="010 Restauración",100%,0%) -> 1 | BO51: =IF($G51="020 Limpieza",100%,0%) -> 0 | BP51: =+BN51+BO51 -> 1 | BR51: =-W51 -> -108.85875 | BV51: =+J51 -> ALGADI | BW51: INCIDENCIA | BX51: =+E51 -> 9-SEPTIEMBRE | BY51: =+K51 -> 110030 | BZ51: =VLOOKUP(BY51,Hoja1!$A$2:$O$599,14,FALSE) -> 110030 | CA51: =VLOOKUP(BZ51,Hoja1!$A$2:$O$599,2,FALSE) -> COLEGIO INMACULADA | CB51: =+H51 -> Festivos y Fines de Semana | CC51: 888 | CD51: =+BW51 -> INCIDENCIA | CJ51: =+W51 -> 108.85875
D52: 945 | E52: 9-SEPTIEMBRE | F52: NO | G52: 010 Restauración | H52: Festivos y Fines de Semana | I52: RIOFRIO RIOFRIO, LUCY | J52: ALGADI | K52: 110030 | L52: =IF(W52>0,IF(OR(E52="",F52="",G52="",H52="",I52="",J52="",K52=""),"faltan datos","ok")," ") -> ok | M52: =IFERROR(VLOOKUP(K52,Centros!$E$2:$G$340,2,FALSE)," ") -> COLEGIO INMACULADA | N52: =IF(J52=" "," ",IF(J52=X52," ","Emp Orig/dest. Distinta")) | O52: =IFERROR(VLOOKUP($I52,Trabajadores!$C$3:$AF$1684,19,FALSE)," ") -> h Cociner@ | P52: 1 | Q52: 70 | R52: =+P52*Q52 -> 70 | T52: =IF(AL52="99100165012016",AQ52,IF(AL52="28009435011996",AR52,IF(AL52="99010825011997",AS52))) -> 1.7437656 | U52: =IF(T52="no corresponde",0,+S52*T52) -> 0 | W52: =+V52*AK52+((+R52+U52)*1.3195) -> 92.365 | X52: =IFERROR(VLOOKUP($I52,Trabajadores!$C$2:$AS$1684,42,FALSE)," ") -> ALGADI | Y52: =IFERROR(VLOOKUP($I52,Trabajadores!$C$2:$AS$1684,40,FALSE)," ") -> 110030 | Z52: =IFERROR(VLOOKUP(Y52,Centros!$X$2:$Y$228,2,FALSE)," ") -> COLEGIO INMACULADA | AA52: 45927 | AB52: Cocina sábado comunidad | AC52: =IFERROR(VLOOKUP(H52,Centros!$AI$2:$AN$10,6,FALSE),0) -> 70 | AD52: =IF(AC52=70,R52,0) -> 70 | AE52: =IF(AC52=72,R52,0) -> 0 | AF52: =IF(AC52=73,+R52,0) -> 0 | AG52: =+U52 -> 0 | AH52: =IFERROR(VLOOKUP($I52,Trabajadores!$C$3:$AT$1684,44,FALSE),0) -> 19228 | AI52: =IFERROR(VLOOKUP($I52,Trabajadores!$C$3:$AT$1684,2,FALSE),0) -> 183 | AJ52: =IFERROR(VLOOKUP($I52,Trabajadores!$C$3:$AY$1270,21,FALSE),0) -> 36 | AK52: =IFERROR(VLOOKUP($I52,Trabajadores!$C$3:$AN$1684,38,FALSE),0) -> 9.8775 | AL52: =IFERROR(VLOOKUP($I52,Trabajadores!$C$3:$AN$1684,28,FALSE),0) -> 99100165012016 | AM52: =IFERROR(VLOOKUP($I52,Trabajadores!$C$3:$AN$1684,19,FALSE),0) -> h Cociner@ | AN52: =IFERROR(IF($J52="algadi",VLOOKUP($K52,Centros!$AB$2:$AD$142,2,FALSE),VLOOKUP($K52,Centros!$AB$143:$AD$282,2,FALSE)),0) -> 19228 | AO52: =IFERROR(IF($J52="algadi",VLOOKUP($K52,Centros!$AB$2:$AD$142,3,FALSE),VLOOKUP($K52,Centros!$AB$143:$AD$222,3,FALSE)),0) -> 36 | AQ52: =IFERROR(VLOOKUP($AM52,Centros!$AR$2:$AS$405,2,FALSE),0) -> 1.7437656 | AR52: =IFERROR(VLOOKUP($AM52,Centros!$AZ$2:$BA$6,2,FALSE),0) -> 0 | AS52: =IFERROR(VLOOKUP($AM52,Centros!$BE$2:$BF$6,2,FALSE),0) -> 0 | BD52: =+X52 -> ALGADI | BE52: INCIDENCIA | BF52: =+E52 -> 9-SEPTIEMBRE | BG52: =+Y52 -> 110030 | BH52: =VLOOKUP(Y52,Hoja1!$A$2:$O$599,14,FALSE) -> 110030 | BI52: =VLOOKUP(BH52,Hoja1!$A$2:$O$599,2,FALSE) -> COLEGIO INMACULADA | BJ52: =+I52 -> RIOFRIO RIOFRIO, LUCY | BK52: =VLOOKUP(BJ52,Trabajadores!$C$3:$AN$3285,14,FALSE) -> 300 | BL52: =VLOOKUP($BJ52,Trabajadores!$C$3:$AN$3285,19,FALSE) -> h Cociner@ | BM52: =VLOOKUP($BJ52,Trabajadores!$C$3:$AN$3285,16,FALSE) -> 100 | BN52: =IF($G52="010 Restauración",100%,0%) -> 1 | BO52: =IF($G52="020 Limpieza",100%,0%) -> 0 | BP52: =+BN52+BO52 -> 1 | BR52: =-W52 -> -92.365 | BV52: =+J52 -> ALGADI | BW52: INCIDENCIA | BX52: =+E52 -> 9-SEPTIEMBRE | BY52: =+K52 -> 110030 | BZ52: =VLOOKUP(BY52,Hoja1!$A$2:$O$599,14,FALSE) -> 110030 | CA52: =VLOOKUP(BZ52,Hoja1!$A$2:$O$599,2,FALSE) -> COLEGIO INMACULADA | CB52: =+H52 -> Festivos y Fines de Semana | CC52: 888 | CD52: =+BW52 -> INCIDENCIA | CJ52: =+W52 -> 92.365
D53: 945 | E53: 9-SEPTIEMBRE | F53: NO | G53: 010 Restauración | H53: Festivos y Fines de Semana | I53: RIOFRIO RIOFRIO, LUCY | J53: ALGADI | K53: 110030 | L53: =IF(W53>0,IF(OR(E53="",F53="",G53="",H53="",I53="",J53="",K53=""),"faltan datos","ok")," ") -> ok | M53: =IFERROR(VLOOKUP(K53,Centros!$E$2:$G$340,2,FALSE)," ") -> COLEGIO INMACULADA | N53: =IF(J53=" "," ",IF(J53=X53," ","Emp Orig/dest. Distinta")) | O53: =IFERROR(VLOOKUP($I53,Trabajadores!$C$3:$AF$1684,19,FALSE)," ") -> h Cociner@ | P53: 2 | Q53: 110 | R53: =+P53*Q53 -> 220 | T53: =IF(AL53="99100165012016",AQ53,IF(AL53="28009435011996",AR53,IF(AL53="99010825011997",AS53))) -> 1.7437656 | U53: =IF(T53="no corresponde",0,+S53*T53) -> 0 | W53: =+V53*AK53+((+R53+U53)*1.3195) -> 290.29 | X53: =IFERROR(VLOOKUP($I53,Trabajadores!$C$2:$AS$1684,42,FALSE)," ") -> ALGADI | Y53: =IFERROR(VLOOKUP($I53,Trabajadores!$C$2:$AS$1684,40,FALSE)," ") -> 110030 | Z53: =IFERROR(VLOOKUP(Y53,Centros!$X$2:$Y$228,2,FALSE)," ") -> COLEGIO INMACULADA | AA53: 6 y 13-09-25 | AB53: COCINA Y ASL | AC53: =IFERROR(VLOOKUP(H53,Centros!$AI$2:$AN$10,6,FALSE),0) -> 70 | AD53: =IF(AC53=70,R53,0) -> 220 | AE53: =IF(AC53=72,R53,0) -> 0 | AF53: =IF(AC53=73,+R53,0) -> 0 | AG53: =+U53 -> 0 | AH53: =IFERROR(VLOOKUP($I53,Trabajadores!$C$3:$AT$1684,44,FALSE),0) -> 19228 | AI53: =IFERROR(VLOOKUP($I53,Trabajadores!$C$3:$AT$1684,2,FALSE),0) -> 183 | AJ53: =IFERROR(VLOOKUP($I53,Trabajadores!$C$3:$AY$1270,21,FALSE),0) -> 36 | AK53: =IFERROR(VLOOKUP($I53,Trabajadores!$C$3:$AN$1684,38,FALSE),0) -> 9.8775 | AL53: =IFERROR(VLOOKUP($I53,Trabajadores!$C$3:$AN$1684,28,FALSE),0) -> 99100165012016 | AM53: =IFERROR(VLOOKUP($I53,Trabajadores!$C$3:$AN$1684,19,FALSE),0) -> h Cociner@ | AN53: =IFERROR(IF($J53="algadi",VLOOKUP($K53,Centros!$AB$2:$AD$142,2,FALSE),VLOOKUP($K53,Centros!$AB$143:$AD$282,2,FALSE)),0) -> 19228 | AO53: =IFERROR(IF($J53="algadi",VLOOKUP($K53,Centros!$AB$2:$AD$142,3,FALSE),VLOOKUP($K53,Centros!$AB$143:$AD$222,3,FALSE)),0) -> 36 | AQ53: =IFERROR(VLOOKUP($AM53,Centros!$AR$2:$AS$405,2,FALSE),0) -> 1.7437656 | AR53: =IFERROR(VLOOKUP($AM53,Centros!$AZ$2:$BA$6,2,FALSE),0) -> 0 | AS53: =IFERROR(VLOOKUP($AM53,Centros!$BE$2:$BF$6,2,FALSE),0) -> 0 | BD53: =+X53 -> ALGADI | BE53: INCIDENCIA | BF53: =+E53 -> 9-SEPTIEMBRE | BG53: =+Y53 -> 110030 | BH53: =VLOOKUP(Y53,Hoja1!$A$2:$O$599,14,FALSE) -> 110030 | BI53: =VLOOKUP(BH53,Hoja1!$A$2:$O$599,2,FALSE) -> COLEGIO INMACULADA | BJ53: =+I53 -> RIOFRIO RIOFRIO, LUCY | BK53: =VLOOKUP(BJ53,Trabajadores!$C$3:$AN$3285,14,FALSE) -> 300 | BL53: =VLOOKUP($BJ53,Trabajadores!$C$3:$AN$3285,19,FALSE) -> h Cociner@ | BM53: =VLOOKUP($BJ53,Trabajadores!$C$3:$AN$3285,16,FALSE) -> 100 | BN53: =IF($G53="010 Restauración",100%,0%) -> 1 | BO53: =IF($G53="020 Limpieza",100%,0%) -> 0 | BP53: =+BN53+BO53 -> 1 | BR53: =-W53 -> -290.29 | BV53: =+J53 -> ALGADI | BW53: INCIDENCIA | BX53: =+E53 -> 9-SEPTIEMBRE | BY53: =+K53 -> 110030 | BZ53: =VLOOKUP(BY53,Hoja1!$A$2:$O$599,14,FALSE) -> 110030 | CA53: =VLOOKUP(BZ53,Hoja1!$A$2:$O$599,2,FALSE) -> COLEGIO INMACULADA | CB53: =+H53 -> Festivos y Fines de Semana | CC53: 888 | CD53: =+BW53 -> INCIDENCIA | CJ53: =+W53 -> 290.29
D54: 945 | E54: 9-SEPTIEMBRE | F54: NO | G54: 020 Limpieza | H54: Otros | I54: ROA FERNANDEZ, M GEMA | J54: ALGADI | K54: 110021 | L54: =IF(W54>0,IF(OR(E54="",F54="",G54="",H54="",I54="",J54="",K54=""),"faltan datos","ok")," ") -> ok | M54: =IFERROR(VLOOKUP(K54,Centros!$E$2:$G$340,2,FALSE)," ") -> COLEGIO FUNDACION CALDEIRO | N54: =IF(J54=" "," ",IF(J54=X54," ","Emp Orig/dest. Distinta")) | O54: =IFERROR(VLOOKUP($I54,Trabajadores!$C$3:$AF$1684,19,FALSE)," ") -> Limpiador@ | P54: 1 | Q54: 125 | R54: =+P54*Q54 -> 125 | T54: =IF(AL54="99100165012016",AQ54,IF(AL54="28009435011996",AR54,IF(AL54="99010825011997",AS54))) -> FALSE | U54: =IF(T54="no corresponde",0,+S54*T54) -> 0 | W54: =+V54*AK54+((+R54+U54)*1.3195) -> 164.9375 | X54: =IFERROR(VLOOKUP($I54,Trabajadores!$C$2:$AS$1684,42,FALSE)," ") -> ALGADI | Y54: =IFERROR(VLOOKUP($I54,Trabajadores!$C$2:$AS$1684,40,FALSE)," ") -> 110021 | Z54: =IFERROR(VLOOKUP(Y54,Centros!$X$2:$Y$228,2,FALSE)," ") -> COLEGIO FUNDACION CALDEIRO | AA54: 45930 | AB54: Plus función encargada limpieza | AC54: =IFERROR(VLOOKUP(H54,Centros!$AI$2:$AN$10,6,FALSE),0) -> 72 | AD54: =IF(AC54=70,R54,0) -> 0 | AE54: =IF(AC54=72,R54,0) -> 125 | AF54: =IF(AC54=73,+R54,0) -> 0 | AG54: =+U54 -> 0 | AH54: =IFERROR(VLOOKUP($I54,Trabajadores!$C$3:$AT$1684,44,FALSE),0) -> 19228 | AI54: =IFERROR(VLOOKUP($I54,Trabajadores!$C$3:$AT$1684,2,FALSE),0) -> 760 | AJ54: =IFERROR(VLOOKUP($I54,Trabajadores!$C$3:$AY$1270,21,FALSE),0) -> 20 | AK54: =IFERROR(VLOOKUP($I54,Trabajadores!$C$3:$AN$1684,38,FALSE),0) -> 8.9713328 | AL54: =IFERROR(VLOOKUP($I54,Trabajadores!$C$3:$AN$1684,28,FALSE),0) -> 28002585011981 | AM54: =IFERROR(VLOOKUP($I54,Trabajadores!$C$3:$AN$1684,19,FALSE),0) -> Limpiador@ | AN54: =IFERROR(IF($J54="algadi",VLOOKUP($K54,Centros!$AB$2:$AD$142,2,FALSE),VLOOKUP($K54,Centros!$AB$143:$AD$282,2,FALSE)),0) -> 19228 | AO54: =IFERROR(IF($J54="algadi",VLOOKUP($K54,Centros!$AB$2:$AD$142,3,FALSE),VLOOKUP($K54,Centros!$AB$143:$AD$222,3,FALSE)),0) -> 20 | AQ54: =IFERROR(VLOOKUP($AM54,Centros!$AR$2:$AS$405,2,FALSE),0) -> 1.6367812 | AR54: =IFERROR(VLOOKUP($AM54,Centros!$AZ$2:$BA$6,2,FALSE),0) -> 0 | AS54: =IFERROR(VLOOKUP($AM54,Centros!$BE$2:$BF$6,2,FALSE),0) -> 0 | BD54: =+X54 -> ALGADI | BE54: INCIDENCIA | BF54: =+E54 -> 9-SEPTIEMBRE | BG54: =+Y54 -> 110021 | BH54: =VLOOKUP(Y54,Hoja1!$A$2:$O$599,14,FALSE) -> 110021 | BI54: =VLOOKUP(BH54,Hoja1!$A$2:$O$599,2,FALSE) -> COLEGIO FUNDACION CALDEIRO | BJ54: =+I54 -> ROA FERNANDEZ, M GEMA | BK54: =VLOOKUP(BJ54,Trabajadores!$C$3:$AN$3285,14,FALSE) -> 200 | BL54: =VLOOKUP($BJ54,Trabajadores!$C$3:$AN$3285,19,FALSE) -> Limpiador@ | BM54: =VLOOKUP($BJ54,Trabajadores!$C$3:$AN$3285,16,FALSE) -> 73.08 | BN54: =IF($G54="010 Restauración",100%,0%) -> 0 | BO54: =IF($G54="020 Limpieza",100%,0%) -> 1 | BP54: =+BN54+BO54 -> 1 | BR54: =-W54 -> -164.9375 | BV54: =+J54 -> ALGADI | BW54: INCIDENCIA | BX54: =+E54 -> 9-SEPTIEMBRE | BY54: =+K54 -> 110021 | BZ54: =VLOOKUP(BY54,Hoja1!$A$2:$O$599,14,FALSE) -> 110021 | CA54: =VLOOKUP(BZ54,Hoja1!$A$2:$O$599,2,FALSE) -> COLEGIO FUNDACION CALDEIRO | CB54: =+H54 -> Otros | CC54: 888 | CD54: =+BW54 -> INCIDENCIA | CJ54: =+W54 -> 164.9375
D55: 945 | E55: 9-SEPTIEMBRE | F55: NO | G55: 010 Restauración | H55: Festivos y Fines de Semana | I55: RODRIGUES GOMES, GRACIETE F | J55: ALGADI | K55: 510006 | L55: =IF(W55>0,IF(OR(E55="",F55="",G55="",H55="",I55="",J55="",K55=""),"faltan datos","ok")," ") -> ok | M55: =IFERROR(VLOOKUP(K55,Centros!$E$2:$G$340,2,FALSE)," ") -> C.P. CONCEPCIONISTAS - BELISANA | N55: =IF(J55=" "," ",IF(J55=X55," ","Emp Orig/dest. Distinta")) | O55: =IFERROR(VLOOKUP($I55,Trabajadores!$C$3:$AF$1684,19,FALSE)," ") -> h Cociner@ | P55: 2 | Q55: 80 | R55: =+P55*Q55 -> 160 | T55: =IF(AL55="99100165012016",AQ55,IF(AL55="28009435011996",AR55,IF(AL55="99010825011997",AS55))) -> 1.7437656 | U55: =IF(T55="no corresponde",0,+S55*T55) -> 0 | W55: =+V55*AK55+((+R55+U55)*1.3195) -> 211.12 | X55: =IFERROR(VLOOKUP($I55,Trabajadores!$C$2:$AS$1684,42,FALSE)," ") -> ALGADI | Y55: =IFERROR(VLOOKUP($I55,Trabajadores!$C$2:$AS$1684,40,FALSE)," ") -> 510006 | Z55: =IFERROR(VLOOKUP(Y55,Centros!$X$2:$Y$228,2,FALSE)," ") -> C.P. CONCEPCIONISTAS - BELISANA | AA55: 13 y 27 septiembre | AB55: Sábado Belisana | AC55: =IFERROR(VLOOKUP(H55,Centros!$AI$2:$AN$10,6,FALSE),0) -> 70 | AD55: =IF(AC55=70,R55,0) -> 160 | AE55: =IF(AC55=72,R55,0) -> 0 | AF55: =IF(AC55=73,+R55,0) -> 0 | AG55: =+U55 -> 0 | AH55: =IFERROR(VLOOKUP($I55,Trabajadores!$C$3:$AT$1684,44,FALSE),0) -> 19228 | AI55: =IFERROR(VLOOKUP($I55,Trabajadores!$C$3:$AT$1684,2,FALSE),0) -> 1545 | AJ55: =IFERROR(VLOOKUP($I55,Trabajadores!$C$3:$AY$1270,21,FALSE),0) -> 27 | AK55: =IFERROR(VLOOKUP($I55,Trabajadores!$C$3:$AN$1684,38,FALSE),0) -> 8.8614286 | AL55: =IFERROR(VLOOKUP($I55,Trabajadores!$C$3:$AN$1684,28,FALSE),0) -> 99100165012016 | AM55: =IFERROR(VLOOKUP($I55,Trabajadores!$C$3:$AN$1684,19,FALSE),0) -> h Cociner@ | AN55: =IFERROR(IF($J55="algadi",VLOOKUP($K55,Centros!$AB$2:$AD$142,2,FALSE),VLOOKUP($K55,Centros!$AB$143:$AD$282,2,FALSE)),0) -> 5027 | AO55: =IFERROR(IF($J55="algadi",VLOOKUP($K55,Centros!$AB$2:$AD$142,3,FALSE),VLOOKUP($K55,Centros!$AB$143:$AD$222,3,FALSE)),0) -> 70 | AQ55: =IFERROR(VLOOKUP($AM55,Centros!$AR$2:$AS$405,2,FALSE),0) -> 1.7437656 | AR55: =IFERROR(VLOOKUP($AM55,Centros!$AZ$2:$BA$6,2,FALSE),0) -> 0 | AS55: =IFERROR(VLOOKUP($AM55,Centros!$BE$2:$BF$6,2,FALSE),0) -> 0 | BD55: =+X55 -> ALGADI | BE55: INCIDENCIA | BF55: =+E55 -> 9-SEPTIEMBRE | BG55: =+Y55 -> 510006 | BH55: =VLOOKUP(Y55,Hoja1!$A$2:$O$599,14,FALSE) -> 510006 | BI55: =VLOOKUP(BH55,Hoja1!$A$2:$O$599,2,FALSE) -> C.P. CONCEPCIONISTAS - BELISANA | BJ55: =+I55 -> RODRIGUES GOMES, GRACIETE F | BK55: =VLOOKUP(BJ55,Trabajadores!$C$3:$AN$3285,14,FALSE) -> 200 | BL55: =VLOOKUP($BJ55,Trabajadores!$C$3:$AN$3285,19,FALSE) -> h Cociner@ | BM55: =VLOOKUP($BJ55,Trabajadores!$C$3:$AN$3285,16,FALSE) -> 87.5 | BN55: =IF($G55="010 Restauración",100%,0%) -> 1 | BO55: =IF($G55="020 Limpieza",100%,0%) -> 0 | BP55: =+BN55+BO55 -> 1 | BR55: =-W55 -> -211.12 | BV55: =+J55 -> ALGADI | BW55: INCIDENCIA | BX55: =+E55 -> 9-SEPTIEMBRE | BY55: =+K55 -> 510006 | BZ55: =VLOOKUP(BY55,Hoja1!$A$2:$O$599,14,FALSE) -> 510006 | CA55: =VLOOKUP(BZ55,Hoja1!$A$2:$O$599,2,FALSE) -> C.P. CONCEPCIONISTAS - BELISANA | CB55: =+H55 -> Festivos y Fines de Semana | CC55: 888 | CD55: =+BW55 -> INCIDENCIA | CJ55: =+W55 -> 211.12
D56: 945 | E56: 9-SEPTIEMBRE | F56: NO | G56: 010 Restauración | H56: Permiso retribuido | I56: RODRIGUEZ DIAZ, M TERESA | J56: ALGADI | K56: 110091 | L56: =IF(W56>0,IF(OR(E56="",F56="",G56="",H56="",I56="",J56="",K56=""),"faltan datos","ok")," ") -> ok | M56: =IFERROR(VLOOKUP(K56,Centros!$E$2:$G$340,2,FALSE)," ") -> COLEGIO CLARET -MADRID | N56: =IF(J56=" "," ",IF(J56=X56," ","Emp Orig/dest. Distinta")) | O56: =IFERROR(VLOOKUP($I56,Trabajadores!$C$3:$AF$1684,19,FALSE)," ") -> ASL | P56: 2 | Q56: 9 | R56: =+P56*Q56 -> 18 | T56: =IF(AL56="99100165012016",AQ56,IF(AL56="28009435011996",AR56,IF(AL56="99010825011997",AS56))) -> 1.6367812 | U56: =IF(T56="no corresponde",0,+S56*T56) -> 0 | W56: =+V56*AK56+((+R56+U56)*1.3195) -> 23.751 | X56: =IFERROR(VLOOKUP($I56,Trabajadores!$C$2:$AS$1684,42,FALSE)," ") -> ALGADI | Y56: =IFERROR(VLOOKUP($I56,Trabajadores!$C$2:$AS$1684,40,FALSE)," ") -> 110091 | Z56: =IFERROR(VLOOKUP(Y56,Centros!$X$2:$Y$228,2,FALSE)," ") -> COLEGIO CLARET -MADRID | AA56: 4 y 5 septiembre | AB56: Fallecimiento nieta Berni | AC56: =IFERROR(VLOOKUP(H56,Centros!$AI$2:$AN$10,6,FALSE),0) -> 72 | AD56: =IF(AC56=70,R56,0) -> 0 | AE56: =IF(AC56=72,R56,0) -> 18 | AF56: =IF(AC56=73,+R56,0) -> 0 | AG56: =+U56 -> 0 | AH56: =IFERROR(VLOOKUP($I56,Trabajadores!$C$3:$AT$1684,44,FALSE),0) -> 19228 | AI56: =IFERROR(VLOOKUP($I56,Trabajadores!$C$3:$AT$1684,2,FALSE),0) -> 1471 | AJ56: =IFERROR(VLOOKUP($I56,Trabajadores!$C$3:$AY$1270,21,FALSE),0) -> 50 | AK56: =IFERROR(VLOOKUP($I56,Trabajadores!$C$3:$AN$1684,38,FALSE),0) -> 7.8 | AL56: =IFERROR(VLOOKUP($I56,Trabajadores!$C$3:$AN$1684,28,FALSE),0) -> 99100165012016 | AM56: =IFERROR(VLOOKUP($I56,Trabajadores!$C$3:$AN$1684,19,FALSE),0) -> ASL | AN56: =IFERROR(IF($J56="algadi",VLOOKUP($K56,Centros!$AB$2:$AD$142,2,FALSE),VLOOKUP($K56,Centros!$AB$143:$AD$282,2,FALSE)),0) -> 0 | AO56: =IFERROR(IF($J56="algadi",VLOOKUP($K56,Centros!$AB$2:$AD$142,3,FALSE),VLOOKUP($K56,Centros!$AB$143:$AD$222,3,FALSE)),0) -> 0 | AQ56: =IFERROR(VLOOKUP($AM56,Centros!$AR$2:$AS$405,2,FALSE),0) -> 1.6367812 | AR56: =IFERROR(VLOOKUP($AM56,Centros!$AZ$2:$BA$6,2,FALSE),0) -> 0 | AS56: =IFERROR(VLOOKUP($AM56,Centros!$BE$2:$BF$6,2,FALSE),0) -> 2.05 | BD56: =+X56 -> ALGADI | BE56: INCIDENCIA | BF56: =+E56 -> 9-SEPTIEMBRE | BG56: =+Y56 -> 110091 | BH56: =VLOOKUP(Y56,Hoja1!$A$2:$O$599,14,FALSE) -> 110091 | BI56: =VLOOKUP(BH56,Hoja1!$A$2:$O$599,2,FALSE) -> COLEGIO CLARET -MADRID | BJ56: =+I56 -> RODRIGUEZ DIAZ, M TERESA | BK56: =VLOOKUP(BJ56,Trabajadores!$C$3:$AN$3285,14,FALSE) -> 389 | BL56: =VLOOKUP($BJ56,Trabajadores!$C$3:$AN$3285,19,FALSE) -> ASL | BM56: =VLOOKUP($BJ56,Trabajadores!$C$3:$AN$3285,16,FALSE) -> 50 | BN56: =IF($G56="010 Restauración",100%,0%) -> 1 | BO56: =IF($G56="020 Limpieza",100%,0%) -> 0 | BP56: =+BN56+BO56 -> 1 | BR56: =-W56 -> -23.751 | BV56: =+J56 -> ALGADI | BW56: INCIDENCIA | BX56: =+E56 -> 9-SEPTIEMBRE | BY56: =+K56 -> 110091 | BZ56: =VLOOKUP(BY56,Hoja1!$A$2:$O$599,14,FALSE) -> 110091 | CA56: =VLOOKUP(BZ56,Hoja1!$A$2:$O$599,2,FALSE) -> COLEGIO CLARET -MADRID | CB56: =+H56 -> Permiso retribuido | CC56: 888 | CD56: =+BW56 -> INCIDENCIA | CJ56: =+W56 -> 23.751
D57: 945 | E57: 9-SEPTIEMBRE | F57: NO | G57: 010 Restauración | H57: Festivos y Fines de Semana | I57: SANCHEZ BARCO, RAQUEL | J57: ALGADI | K57: 110021 | L57: =IF(W57>0,IF(OR(E57="",F57="",G57="",H57="",I57="",J57="",K57=""),"faltan datos","ok")," ") -> ok | M57: =IFERROR(VLOOKUP(K57,Centros!$E$2:$G$340,2,FALSE)," ") -> COLEGIO FUNDACION CALDEIRO | N57: =IF(J57=" "," ",IF(J57=X57," ","Emp Orig/dest. Distinta")) | O57: =IFERROR(VLOOKUP($I57,Trabajadores!$C$3:$AF$1684,19,FALSE)," ") -> h Enc/J Co | P57: 4 | Q57: 75 | R57: =+P57*Q57 -> 300 | T57: =IF(AL57="99100165012016",AQ57,IF(AL57="28009435011996",AR57,IF(AL57="99010825011997",AS57))) -> 1.7971719 | U57: =IF(T57="no corresponde",0,+S57*T57) -> 0 | W57: =+V57*AK57+((+R57+U57)*1.3195) -> 395.85 | X57: =IFERROR(VLOOKUP($I57,Trabajadores!$C$2:$AS$1684,42,FALSE)," ") -> ALGADI | Y57: =IFERROR(VLOOKUP($I57,Trabajadores!$C$2:$AS$1684,40,FALSE)," ") -> 110004 | Z57: =IFERROR(VLOOKUP(Y57,Centros!$X$2:$Y$228,2,FALSE)," ") -> COLEGIO AMOR MISERICORDIOSO | AA57: 6,7,20 y 21 septiembre | AB57: Fines de semana y festivo Comunidad Caldeiro | AC57: =IFERROR(VLOOKUP(H57,Centros!$AI$2:$AN$10,6,FALSE),0) -> 70 | AD57: =IF(AC57=70,R57,0) -> 300 | AE57: =IF(AC57=72,R57,0) -> 0 | AF57: =IF(AC57=73,+R57,0) -> 0 | AG57: =+U57 -> 0 | AH57: =IFERROR(VLOOKUP($I57,Trabajadores!$C$3:$AT$1684,44,FALSE),0) -> 19228 | AI57: =IFERROR(VLOOKUP($I57,Trabajadores!$C$3:$AT$1684,2,FALSE),0) -> 10 | AJ57: =IFERROR(VLOOKUP($I57,Trabajadores!$C$3:$AY$1270,21,FALSE),0) -> 2 | AK57: =IFERROR(VLOOKUP($I57,Trabajadores!$C$3:$AN$1684,38,FALSE),0) -> 10.49375 | AL57: =IFERROR(VLOOKUP($I57,Trabajadores!$C$3:$AN$1684,28,FALSE),0) -> 99100165012016 | AM57: =IFERROR(VLOOKUP($I57,Trabajadores!$C$3:$AN$1684,19,FALSE),0) -> h Enc/J Co | AN57: =IFERROR(IF($J57="algadi",VLOOKUP($K57,Centros!$AB$2:$AD$142,2,FALSE),VLOOKUP($K57,Centros!$AB$143:$AD$282,2,FALSE)),0) -> 19228 | AO57: =IFERROR(IF($J57="algadi",VLOOKUP($K57,Centros!$AB$2:$AD$142,3,FALSE),VLOOKUP($K57,Centros!$AB$143:$AD$222,3,FALSE)),0) -> 20 | AQ57: =IFERROR(VLOOKUP($AM57,Centros!$AR$2:$AS$405,2,FALSE),0) -> 1.7971719 | AR57: =IFERROR(VLOOKUP($AM57,Centros!$AZ$2:$BA$6,2,FALSE),0) -> 0 | AS57: =IFERROR(VLOOKUP($AM57,Centros!$BE$2:$BF$6,2,FALSE),0) -> 0 | BD57: =+X57 -> ALGADI | BE57: INCIDENCIA | BF57: =+E57 -> 9-SEPTIEMBRE | BG57: =+Y57 -> 110004 | BH57: =VLOOKUP(Y57,Hoja1!$A$2:$O$599,14,FALSE) -> 110004 | BI57: =VLOOKUP(BH57,Hoja1!$A$2:$O$599,2,FALSE) -> COLEGIO AMOR MISERICORDIOSO | BJ57: =+I57 -> SANCHEZ BARCO, RAQUEL | BK57: =VLOOKUP(BJ57,Trabajadores!$C$3:$AN$3285,14,FALSE) -> 100 | BL57: =VLOOKUP($BJ57,Trabajadores!$C$3:$AN$3285,19,FALSE) -> h Enc/J Co | BM57: =VLOOKUP($BJ57,Trabajadores!$C$3:$AN$3285,16,FALSE) -> 100 | BN57: =IF($G57="010 Restauración",100%,0%) -> 1 | BO57: =IF($G57="020 Limpieza",100%,0%) -> 0 | BP57: =+BN57+BO57 -> 1 | BR57: =-W57 -> -395.85 | BV57: =+J57 -> ALGADI | BW57: INCIDENCIA | BX57: =+E57 -> 9-SEPTIEMBRE | BY57: =+K57 -> 110021 | BZ57: =VLOOKUP(BY57,Hoja1!$A$2:$O$599,14,FALSE) -> 110021 | CA57: =VLOOKUP(BZ57,Hoja1!$A$2:$O$599,2,FALSE) -> COLEGIO FUNDACION CALDEIRO | CB57: =+H57 -> Festivos y Fines de Semana | CC57: 888 | CD57: =+BW57 -> INCIDENCIA | CJ57: =+W57 -> 395.85
D58: 945 | E58: 9-SEPTIEMBRE | F58: NO | G58: 010 Restauración | H58: Eventos | I58: TITO SANCHEZ, LILIAN S. | J58: DISTEGSA | K58: 110065 | L58: =IF(W58>0,IF(OR(E58="",F58="",G58="",H58="",I58="",J58="",K58=""),"faltan datos","ok")," ") -> ok | M58: =IFERROR(VLOOKUP(K58,Centros!$E$2:$G$340,2,FALSE)," ") -> COLEGIO SANTA RITA | N58: =IF(J58=" "," ",IF(J58=X58," ","Emp Orig/dest. Distinta")) -> Emp Orig/dest. Distinta | O58: =IFERROR(VLOOKUP($I58,Trabajadores!$C$3:$AF$1684,19,FALSE)," ") -> h ASL | P58: 2 | Q58: 9 | R58: =+P58*Q58 -> 18 | T58: =IF(AL58="99100165012016",AQ58,IF(AL58="28009435011996",AR58,IF(AL58="99010825011997",AS58))) -> 1.6367812 | U58: =IF(T58="no corresponde",0,+S58*T58) -> 0 | W58: =+V58*AK58+((+R58+U58)*1.3195) -> 23.751 | X58: =IFERROR(VLOOKUP($I58,Trabajadores!$C$2:$AS$1684,42,FALSE)," ") -> ALGADI | Y58: =IFERROR(VLOOKUP($I58,Trabajadores!$C$2:$AS$1684,40,FALSE)," ") -> 110021 | Z58: =IFERROR(VLOOKUP(Y58,Centros!$X$2:$Y$228,2,FALSE)," ") -> COLEGIO FUNDACION CALDEIRO | AA58: 45902 | AB58: Ayuda evento profesores | AC58: =IFERROR(VLOOKUP(H58,Centros!$AI$2:$AN$10,6,FALSE),0) -> 72 | AD58: =IF(AC58=70,R58,0) -> 0 | AE58: =IF(AC58=72,R58,0) -> 18 | AF58: =IF(AC58=73,+R58,0) -> 0 | AG58: =+U58 -> 0 | AH58: =IFERROR(VLOOKUP($I58,Trabajadores!$C$3:$AT$1684,44,FALSE),0) -> 19228 | AI58: =IFERROR(VLOOKUP($I58,Trabajadores!$C$3:$AT$1684,2,FALSE),0) -> 157 | AJ58: =IFERROR(VLOOKUP($I58,Trabajadores!$C$3:$AY$1270,21,FALSE),0) -> 20 | AK58: =IFERROR(VLOOKUP($I58,Trabajadores!$C$3:$AN$1684,38,FALSE),0) -> 10.3 | AL58: =IFERROR(VLOOKUP($I58,Trabajadores!$C$3:$AN$1684,28,FALSE),0) -> 99100165012016 | AM58: =IFERROR(VLOOKUP($I58,Trabajadores!$C$3:$AN$1684,19,FALSE),0) -> h ASL | AN58: =IFERROR(IF($J58="algadi",VLOOKUP($K58,Centros!$AB$2:$AD$142,2,FALSE),VLOOKUP($K58,Centros!$AB$143:$AD$282,2,FALSE)),0) -> 0 | AO58: =IFERROR(IF($J58="algadi",VLOOKUP($K58,Centros!$AB$2:$AD$142,3,FALSE),VLOOKUP($K58,Centros!$AB$143:$AD$222,3,FALSE)),0) -> 0 | AQ58: =IFERROR(VLOOKUP($AM58,Centros!$AR$2:$AS$405,2,FALSE),0) -> 1.6367812 | AR58: =IFERROR(VLOOKUP($AM58,Centros!$AZ$2:$BA$6,2,FALSE),0) -> 0 | AS58: =IFERROR(VLOOKUP($AM58,Centros!$BE$2:$BF$6,2,FALSE),0) -> 0 | BD58: =+X58 -> ALGADI | BE58: INCIDENCIA | BF58: =+E58 -> 9-SEPTIEMBRE | BG58: =+Y58 -> 110021 | BH58: =VLOOKUP(Y58,Hoja1!$A$2:$O$599,14,FALSE) -> 110021 | BI58: =VLOOKUP(BH58,Hoja1!$A$2:$O$599,2,FALSE) -> COLEGIO FUNDACION CALDEIRO | BJ58: =+I58 -> TITO SANCHEZ, LILIAN S. | BK58: =VLOOKUP(BJ58,Trabajadores!$C$3:$AN$3285,14,FALSE) -> 300 | BL58: =VLOOKUP($BJ58,Trabajadores!$C$3:$AN$3285,19,FALSE) -> h ASL | BM58: =VLOOKUP($BJ58,Trabajadores!$C$3:$AN$3285,16,FALSE) -> 37.5 | BN58: =IF($G58="010 Restauración",100%,0%) -> 1 | BO58: =IF($G58="020 Limpieza",100%,0%) -> 0 | BP58: =+BN58+BO58 -> 1 | BR58: =-W58 -> -23.751 | BV58: =+J58 -> DISTEGSA | BW58: INCIDENCIA | BX58: =+E58 -> 9-SEPTIEMBRE | BY58: =+K58 -> 110065 | BZ58: =VLOOKUP(BY58,Hoja1!$A$2:$O$599,14,FALSE) -> 110065 | CA58: =VLOOKUP(BZ58,Hoja1!$A$2:$O$599,2,FALSE) -> COLEGIO SANTA RITA | CB58: =+H58 -> Eventos | CC58: 888 | CD58: =+BW58 -> INCIDENCIA | CJ58: =+W58 -> 23.751
D59: 945 | E59: 9-SEPTIEMBRE | F59: NO | G59: 010 Restauración | H59: Festivos y Fines de Semana | I59: TITO SANCHEZ, LILIAN S. | J59: DISTEGSA | K59: 110065 | L59: =IF(W59>0,IF(OR(E59="",F59="",G59="",H59="",I59="",J59="",K59=""),"faltan datos","ok")," ") -> ok | M59: =IFERROR(VLOOKUP(K59,Centros!$E$2:$G$340,2,FALSE)," ") -> COLEGIO SANTA RITA | N59: =IF(J59=" "," ",IF(J59=X59," ","Emp Orig/dest. Distinta")) -> Emp Orig/dest. Distinta | O59: =IFERROR(VLOOKUP($I59,Trabajadores!$C$3:$AF$1684,19,FALSE)," ") -> h ASL | P59: 2 | Q59: 72.42 | R59: =+P59*Q59 -> 144.84 | T59: =IF(AL59="99100165012016",AQ59,IF(AL59="28009435011996",AR59,IF(AL59="99010825011997",AS59))) -> 1.6367812 | U59: =IF(T59="no corresponde",0,+S59*T59) -> 0 | W59: =+V59*AK59+((+R59+U59)*1.3195) -> 191.11638 | X59: =IFERROR(VLOOKUP($I59,Trabajadores!$C$2:$AS$1684,42,FALSE)," ") -> ALGADI | Y59: =IFERROR(VLOOKUP($I59,Trabajadores!$C$2:$AS$1684,40,FALSE)," ") -> 110021 | Z59: =IFERROR(VLOOKUP(Y59,Centros!$X$2:$Y$228,2,FALSE)," ") -> COLEGIO FUNDACION CALDEIRO | AA59: 6 y 7 septiembre | AB59: Fines de semana Santa Rita | AC59: =IFERROR(VLOOKUP(H59,Centros!$AI$2:$AN$10,6,FALSE),0) -> 70 | AD59: =IF(AC59=70,R59,0) -> 144.84 | AE59: =IF(AC59=72,R59,0) -> 0 | AF59: =IF(AC59=73,+R59,0) -> 0 | AG59: =+U59 -> 0 | AH59: =IFERROR(VLOOKUP($I59,Trabajadores!$C$3:$AT$1684,44,FALSE),0) -> 19228 | AI59: =IFERROR(VLOOKUP($I59,Trabajadores!$C$3:$AT$1684,2,FALSE),0) -> 157 | AJ59: =IFERROR(VLOOKUP($I59,Trabajadores!$C$3:$AY$1270,21,FALSE),0) -> 20 | AK59: =IFERROR(VLOOKUP($I59,Trabajadores!$C$3:$AN$1684,38,FALSE),0) -> 10.3 | AL59: =IFERROR(VLOOKUP($I59,Trabajadores!$C$3:$AN$1684,28,FALSE),0) -> 99100165012016 | AM59: =IFERROR(VLOOKUP($I59,Trabajadores!$C$3:$AN$1684,19,FALSE),0) -> h ASL | AN59: =IFERROR(IF($J59="algadi",VLOOKUP($K59,Centros!$AB$2:$AD$142,2,FALSE),VLOOKUP($K59,Centros!$AB$143:$AD$282,2,FALSE)),0) -> 0 | AO59: =IFERROR(IF($J59="algadi",VLOOKUP($K59,Centros!$AB$2:$AD$142,3,FALSE),VLOOKUP($K59,Centros!$AB$143:$AD$222,3,FALSE)),0) -> 0 | AQ59: =IFERROR(VLOOKUP($AM59,Centros!$AR$2:$AS$405,2,FALSE),0) -> 1.6367812 | AR59: =IFERROR(VLOOKUP($AM59,Centros!$AZ$2:$BA$6,2,FALSE),0) -> 0 | AS59: =IFERROR(VLOOKUP($AM59,Centros!$BE$2:$BF$6,2,FALSE),0) -> 0 | BD59: =+X59 -> ALGADI | BE59: INCIDENCIA | BF59: =+E59 -> 9-SEPTIEMBRE | BG59: =+Y59 -> 110021 | BH59: =VLOOKUP(Y59,Hoja1!$A$2:$O$599,14,FALSE) -> 110021 | BI59: =VLOOKUP(BH59,Hoja1!$A$2:$O$599,2,FALSE) -> COLEGIO FUNDACION CALDEIRO | BJ59: =+I59 -> TITO SANCHEZ, LILIAN S. | BK59: =VLOOKUP(BJ59,Trabajadores!$C$3:$AN$3285,14,FALSE) -> 300 | BL59: =VLOOKUP($BJ59,Trabajadores!$C$3:$AN$3285,19,FALSE) -> h ASL | BM59: =VLOOKUP($BJ59,Trabajadores!$C$3:$AN$3285,16,FALSE) -> 37.5 | BN59: =IF($G59="010 Restauración",100%,0%) -> 1 | BO59: =IF($G59="020 Limpieza",100%,0%) -> 0 | BP59: =+BN59+BO59 -> 1 | BR59: =-W59 -> -191.11638 | BV59: =+J59 -> DISTEGSA | BW59: INCIDENCIA | BX59: =+E59 -> 9-SEPTIEMBRE | BY59: =+K59 -> 110065 | BZ59: =VLOOKUP(BY59,Hoja1!$A$2:$O$599,14,FALSE) -> 110065 | CA59: =VLOOKUP(BZ59,Hoja1!$A$2:$O$599,2,FALSE) -> COLEGIO SANTA RITA | CB59: =+H59 -> Festivos y Fines de Semana | CC59: 888 | CD59: =+BW59 -> INCIDENCIA | CJ59: =+W59 -> 191.11638
D60: 945 | E60: 9-SEPTIEMBRE | F60: NO | G60: 010 Restauración | H60: Otros | I60: TORTOSA APARICIO, ROSA MARIA | J60: ALGADI | K60: 110065 | L60: =IF(W60>0,IF(OR(E60="",F60="",G60="",H60="",I60="",J60="",K60=""),"faltan datos","ok")," ") -> ok | M60: =IFERROR(VLOOKUP(K60,Centros!$E$2:$G$340,2,FALSE)," ") -> COLEGIO SANTA RITA | N60: =IF(J60=" "," ",IF(J60=X60," ","Emp Orig/dest. Distinta")) | O60: =IFERROR(VLOOKUP($I60,Trabajadores!$C$3:$AF$1684,19,FALSE)," ") -> h ASL | P60: 1 | Q60: 50 | R60: =+P60*Q60 -> 50 | T60: =IF(AL60="99100165012016",AQ60,IF(AL60="28009435011996",AR60,IF(AL60="99010825011997",AS60))) -> 1.6367812 | U60: =IF(T60="no corresponde",0,+S60*T60) -> 0 | W60: =+V60*AK60+((+R60+U60)*1.3195) -> 65.975 | X60: =IFERROR(VLOOKUP($I60,Trabajadores!$C$2:$AS$1684,42,FALSE)," ") -> ALGADI | Y60: =IFERROR(VLOOKUP($I60,Trabajadores!$C$2:$AS$1684,40,FALSE)," ") -> 110065 | Z60: =IFERROR(VLOOKUP(Y60,Centros!$X$2:$Y$228,2,FALSE)," ") -> COLEGIO SANTA RITA | AA60: 45930 | AB60: Plus encargada | AC60: =IFERROR(VLOOKUP(H60,Centros!$AI$2:$AN$10,6,FALSE),0) -> 72 | AD60: =IF(AC60=70,R60,0) -> 0 | AE60: =IF(AC60=72,R60,0) -> 50 | AF60: =IF(AC60=73,+R60,0) -> 0 | AG60: =+U60 -> 0 | AH60: =IFERROR(VLOOKUP($I60,Trabajadores!$C$3:$AT$1684,44,FALSE),0) -> 19228 | AI60: =IFERROR(VLOOKUP($I60,Trabajadores!$C$3:$AT$1684,2,FALSE),0) -> 1183 | AJ60: =IFERROR(VLOOKUP($I60,Trabajadores!$C$3:$AY$1270,21,FALSE),0) -> 6 | AK60: =IFERROR(VLOOKUP($I60,Trabajadores!$C$3:$AN$1684,38,FALSE),0) -> 8.2275 | AL60: =IFERROR(VLOOKUP($I60,Trabajadores!$C$3:$AN$1684,28,FALSE),0) -> 99100165012016 | AM60: =IFERROR(VLOOKUP($I60,Trabajadores!$C$3:$AN$1684,19,FALSE),0) -> h ASL | AN60: =IFERROR(IF($J60="algadi",VLOOKUP($K60,Centros!$AB$2:$AD$142,2,FALSE),VLOOKUP($K60,Centros!$AB$143:$AD$282,2,FALSE)),0) -> 5027 | AO60: =IFERROR(IF($J60="algadi",VLOOKUP($K60,Centros!$AB$2:$AD$142,3,FALSE),VLOOKUP($K60,Centros!$AB$143:$AD$222,3,FALSE)),0) -> 33 | AQ60: =IFERROR(VLOOKUP($AM60,Centros!$AR$2:$AS$405,2,FALSE),0) -> 1.6367812 | AR60: =IFERROR(VLOOKUP($AM60,Centros!$AZ$2:$BA$6,2,FALSE),0) -> 0 | AS60: =IFERROR(VLOOKUP($AM60,Centros!$BE$2:$BF$6,2,FALSE),0) -> 0 | BD60: =+X60 -> ALGADI | BE60: INCIDENCIA | BF60: =+E60 -> 9-SEPTIEMBRE | BG60: =+Y60 -> 110065 | BH60: =VLOOKUP(Y60,Hoja1!$A$2:$O$599,14,FALSE) -> 110065 | BI60: =VLOOKUP(BH60,Hoja1!$A$2:$O$599,2,FALSE) -> COLEGIO SANTA RITA | BJ60: =+I60 -> TORTOSA APARICIO, ROSA MARIA | BK60: =VLOOKUP(BJ60,Trabajadores!$C$3:$AN$3285,14,FALSE) -> 300 | BL60: =VLOOKUP($BJ60,Trabajadores!$C$3:$AN$3285,19,FALSE) -> h ASL | BM60: =VLOOKUP($BJ60,Trabajadores!$C$3:$AN$3285,16,FALSE) -> 100 | BN60: =IF($G60="010 Restauración",100%,0%) -> 1 | BO60: =IF($G60="020 Limpieza",100%,0%) -> 0 | BP60: =+BN60+BO60 -> 1 | BR60: =-W60 -> -65.975 | BV60: =+J60 -> ALGADI | BW60: INCIDENCIA | BX60: =+E60 -> 9-SEPTIEMBRE | BY60: =+K60 -> 110065 | BZ60: =VLOOKUP(BY60,Hoja1!$A$2:$O$599,14,FALSE) -> 110065 | CA60: =VLOOKUP(BZ60,Hoja1!$A$2:$O$599,2,FALSE) -> COLEGIO SANTA RITA | CB60: =+H60 -> Otros | CC60: 888 | CD60: =+BW60 -> INCIDENCIA | CJ60: =+W60 -> 65.975
D61: 945 | E61: 9-SEPTIEMBRE | F61: NO | G61: 010 Restauración | H61: Eventos | I61: VILLALBA DIAZ, M VICTORIA | J61: ALGADI | K61: 110091 | L61: =IF(W61>0,IF(OR(E61="",F61="",G61="",H61="",I61="",J61="",K61=""),"faltan datos","ok")," ") -> ok | M61: =IFERROR(VLOOKUP(K61,Centros!$E$2:$G$340,2,FALSE)," ") -> COLEGIO CLARET -MADRID | N61: =IF(J61=" "," ",IF(J61=X61," ","Emp Orig/dest. Distinta")) | O61: =IFERROR(VLOOKUP($I61,Trabajadores!$C$3:$AF$1684,19,FALSE)," ") -> ENCARGADA | P61: 1 | Q61: 80 | R61: =+P61*Q61 -> 80 | T61: =IF(AL61="99100165012016",AQ61,IF(AL61="28009435011996",AR61,IF(AL61="99010825011997",AS61))) -> 1.7971719 | U61: =IF(T61="no corresponde",0,+S61*T61) -> 0 | W61: =+V61*AK61+((+R61+U61)*1.3195) -> 105.56 | X61: =IFERROR(VLOOKUP($I61,Trabajadores!$C$2:$AS$1684,42,FALSE)," ") -> ALGADI | Y61: =IFERROR(VLOOKUP($I61,Trabajadores!$C$2:$AS$1684,40,FALSE)," ") -> 110091 | Z61: =IFERROR(VLOOKUP(Y61,Centros!$X$2:$Y$228,2,FALSE)," ") -> COLEGIO CLARET -MADRID | AA61: 45838 | AB61: Evento Claret no abonado en junio | AC61: =IFERROR(VLOOKUP(H61,Centros!$AI$2:$AN$10,6,FALSE),0) -> 72 | AD61: =IF(AC61=70,R61,0) -> 0 | AE61: =IF(AC61=72,R61,0) -> 80 | AF61: =IF(AC61=73,+R61,0) -> 0 | AG61: =+U61 -> 0 | AH61: =IFERROR(VLOOKUP($I61,Trabajadores!$C$3:$AT$1684,44,FALSE),0) -> 19228 | AI61: =IFERROR(VLOOKUP($I61,Trabajadores!$C$3:$AT$1684,2,FALSE),0) -> 479 | AJ61: =IFERROR(VLOOKUP($I61,Trabajadores!$C$3:$AY$1270,21,FALSE),0) -> 50 | AK61: =IFERROR(VLOOKUP($I61,Trabajadores!$C$3:$AN$1684,38,FALSE),0) -> 9.45625 | AL61: =IFERROR(VLOOKUP($I61,Trabajadores!$C$3:$AN$1684,28,FALSE),0) -> 99100165012016 | AM61: =IFERROR(VLOOKUP($I61,Trabajadores!$C$3:$AN$1684,19,FALSE),0) -> ENCARGADA | AN61: =IFERROR(IF($J61="algadi",VLOOKUP($K61,Centros!$AB$2:$AD$142,2,FALSE),VLOOKUP($K61,Centros!$AB$143:$AD$282,2,FALSE)),0) -> 0 | AO61: =IFERROR(IF($J61="algadi",VLOOKUP($K61,Centros!$AB$2:$AD$142,3,FALSE),VLOOKUP($K61,Centros!$AB$143:$AD$222,3,FALSE)),0) -> 0 | AQ61: =IFERROR(VLOOKUP($AM61,Centros!$AR$2:$AS$405,2,FALSE),0) -> 1.7971719 | AR61: =IFERROR(VLOOKUP($AM61,Centros!$AZ$2:$BA$6,2,FALSE),0) -> 0 | AS61: =IFERROR(VLOOKUP($AM61,Centros!$BE$2:$BF$6,2,FALSE),0) -> 0 | BD61: =+X61 -> ALGADI | BE61: INCIDENCIA | BF61: =+E61 -> 9-SEPTIEMBRE | BG61: =+Y61 -> 110091 | BH61: =VLOOKUP(Y61,Hoja1!$A$2:$O$599,14,FALSE) -> 110091 | BI61: =VLOOKUP(BH61,Hoja1!$A$2:$O$599,2,FALSE) -> COLEGIO CLARET -MADRID | BJ61: =+I61 -> VILLALBA DIAZ, M VICTORIA | BK61: =VLOOKUP(BJ61,Trabajadores!$C$3:$AN$3285,14,FALSE) -> 300 | BL61: =VLOOKUP($BJ61,Trabajadores!$C$3:$AN$3285,19,FALSE) -> ENCARGADA | BM61: =VLOOKUP($BJ61,Trabajadores!$C$3:$AN$3285,16,FALSE) -> 100 | BN61: =IF($G61="010 Restauración",100%,0%) -> 1 | BO61: =IF($G61="020 Limpieza",100%,0%) -> 0 | BP61: =+BN61+BO61 -> 1 | BR61: =-W61 -> -105.56 | BV61: =+J61 -> ALGADI | BW61: INCIDENCIA | BX61: =+E61 -> 9-SEPTIEMBRE | BY61: =+K61 -> 110091 | BZ61: =VLOOKUP(BY61,Hoja1!$A$2:$O$599,14,FALSE) -> 110091 | CA61: =VLOOKUP(BZ61,Hoja1!$A$2:$O$599,2,FALSE) -> COLEGIO CLARET -MADRID | CB61: =+H61 -> Eventos | CC61: 888 | CD61: =+BW61 -> INCIDENCIA | CJ61: =+W61 -> 105.56
D62: 945 | E62: 9-SEPTIEMBRE | F62: NO | G62: 010 Restauración | H62: Eventos | I62: VILLALBA DIAZ, M VICTORIA | J62: ALGADI | K62: 110091 | L62: =IF(W62>0,IF(OR(E62="",F62="",G62="",H62="",I62="",J62="",K62=""),"faltan datos","ok")," ") -> ok | M62: =IFERROR(VLOOKUP(K62,Centros!$E$2:$G$340,2,FALSE)," ") -> COLEGIO CLARET -MADRID | N62: =IF(J62=" "," ",IF(J62=X62," ","Emp Orig/dest. Distinta")) | O62: =IFERROR(VLOOKUP($I62,Trabajadores!$C$3:$AF$1684,19,FALSE)," ") -> ENCARGADA | P62: 1 | Q62: 9 | R62: =+P62*Q62 -> 9 | T62: =IF(AL62="99100165012016",AQ62,IF(AL62="28009435011996",AR62,IF(AL62="99010825011997",AS62))) -> 1.7971719 | U62: =IF(T62="no corresponde",0,+S62*T62) -> 0 | W62: =+V62*AK62+((+R62+U62)*1.3195) -> 11.8755 | X62: =IFERROR(VLOOKUP($I62,Trabajadores!$C$2:$AS$1684,42,FALSE)," ") -> ALGADI | Y62: =IFERROR(VLOOKUP($I62,Trabajadores!$C$2:$AS$1684,40,FALSE)," ") -> 110091 | Z62: =IFERROR(VLOOKUP(Y62,Centros!$X$2:$Y$228,2,FALSE)," ") -> COLEGIO CLARET -MADRID | AA62: 45901 | AB62: Desayunos comienzo profesores | AC62: =IFERROR(VLOOKUP(H62,Centros!$AI$2:$AN$10,6,FALSE),0) -> 72 | AD62: =IF(AC62=70,R62,0) -> 0 | AE62: =IF(AC62=72,R62,0) -> 9 | AF62: =IF(AC62=73,+R62,0) -> 0 | AG62: =+U62 -> 0 | AH62: =IFERROR(VLOOKUP($I62,Trabajadores!$C$3:$AT$1684,44,FALSE),0) -> 19228 | AI62: =IFERROR(VLOOKUP($I62,Trabajadores!$C$3:$AT$1684,2,FALSE),0) -> 479 | AJ62: =IFERROR(VLOOKUP($I62,Trabajadores!$C$3:$AY$1270,21,FALSE),0) -> 50 | AK62: =IFERROR(VLOOKUP($I62,Trabajadores!$C$3:$AN$1684,38,FALSE),0) -> 9.45625 | AL62: =IFERROR(VLOOKUP($I62,Trabajadores!$C$3:$AN$1684,28,FALSE),0) -> 99100165012016 | AM62: =IFERROR(VLOOKUP($I62,Trabajadores!$C$3:$AN$1684,19,FALSE),0) -> ENCARGADA | AN62: =IFERROR(IF($J62="algadi",VLOOKUP($K62,Centros!$AB$2:$AD$142,2,FALSE),VLOOKUP($K62,Centros!$AB$143:$AD$282,2,FALSE)),0) -> 0 | AO62: =IFERROR(IF($J62="algadi",VLOOKUP($K62,Centros!$AB$2:$AD$142,3,FALSE),VLOOKUP($K62,Centros!$AB$143:$AD$222,3,FALSE)),0) -> 0 | AQ62: =IFERROR(VLOOKUP($AM62,Centros!$AR$2:$AS$405,2,FALSE),0) -> 1.7971719 | AR62: =IFERROR(VLOOKUP($AM62,Centros!$AZ$2:$BA$6,2,FALSE),0) -> 0 | AS62: =IFERROR(VLOOKUP($AM62,Centros!$BE$2:$BF$6,2,FALSE),0) -> 0 | BD62: =+X62 -> ALGADI | BE62: INCIDENCIA | BF62: =+E62 -> 9-SEPTIEMBRE | BG62: =+Y62 -> 110091 | BH62: =VLOOKUP(Y62,Hoja1!$A$2:$O$599,14,FALSE) -> 110091 | BI62: =VLOOKUP(BH62,Hoja1!$A$2:$O$599,2,FALSE) -> COLEGIO CLARET -MADRID | BJ62: =+I62 -> VILLALBA DIAZ, M VICTORIA | BK62: =VLOOKUP(BJ62,Trabajadores!$C$3:$AN$3285,14,FALSE) -> 300 | BL62: =VLOOKUP($BJ62,Trabajadores!$C$3:$AN$3285,19,FALSE) -> ENCARGADA | BM62: =VLOOKUP($BJ62,Trabajadores!$C$3:$AN$3285,16,FALSE) -> 100 | BN62: =IF($G62="010 Restauración",100%,0%) -> 1 | BO62: =IF($G62="020 Limpieza",100%,0%) -> 0 | BP62: =+BN62+BO62 -> 1 | BR62: =-W62 -> -11.8755 | BV62: =+J62 -> ALGADI | BW62: INCIDENCIA | BX62: =+E62 -> 9-SEPTIEMBRE | BY62: =+K62 -> 110091 | BZ62: =VLOOKUP(BY62,Hoja1!$A$2:$O$599,14,FALSE) -> 110091 | CA62: =VLOOKUP(BZ62,Hoja1!$A$2:$O$599,2,FALSE) -> COLEGIO CLARET -MADRID | CB62: =+H62 -> Eventos | CC62: 888 | CD62: =+BW62 -> INCIDENCIA | CJ62: =+W62 -> 11.8755
D63: 945 | E63: 9-SEPTIEMBRE | F63: NO | G63: 010 Restauración | H63: Eventos | I63: VILLALBA DIAZ, M VICTORIA | J63: ALGADI | K63: 110091 | L63: =IF(W63>0,IF(OR(E63="",F63="",G63="",H63="",I63="",J63="",K63=""),"faltan datos","ok")," ") -> ok | M63: =IFERROR(VLOOKUP(K63,Centros!$E$2:$G$340,2,FALSE)," ") -> COLEGIO CLARET -MADRID | N63: =IF(J63=" "," ",IF(J63=X63," ","Emp Orig/dest. Distinta")) | O63: =IFERROR(VLOOKUP($I63,Trabajadores!$C$3:$AF$1684,19,FALSE)," ") -> ENCARGADA | P63: 1 | Q63: 9 | R63: =+P63*Q63 -> 9 | T63: =IF(AL63="99100165012016",AQ63,IF(AL63="28009435011996",AR63,IF(AL63="99010825011997",AS63))) -> 1.7971719 | U63: =IF(T63="no corresponde",0,+S63*T63) -> 0 | W63: =+V63*AK63+((+R63+U63)*1.3195) -> 11.8755 | X63: =IFERROR(VLOOKUP($I63,Trabajadores!$C$2:$AS$1684,42,FALSE)," ") -> ALGADI | Y63: =IFERROR(VLOOKUP($I63,Trabajadores!$C$2:$AS$1684,40,FALSE)," ") -> 110091 | Z63: =IFERROR(VLOOKUP(Y63,Centros!$X$2:$Y$228,2,FALSE)," ") -> COLEGIO CLARET -MADRID | AA63: 45918 | AB63: Desayuno bachilleres | AC63: =IFERROR(VLOOKUP(H63,Centros!$AI$2:$AN$10,6,FALSE),0) -> 72 | AD63: =IF(AC63=70,R63,0) -> 0 | AE63: =IF(AC63=72,R63,0) -> 9 | AF63: =IF(AC63=73,+R63,0) -> 0 | AG63: =+U63 -> 0 | AH63: =IFERROR(VLOOKUP($I63,Trabajadores!$C$3:$AT$1684,44,FALSE),0) -> 19228 | AI63: =IFERROR(VLOOKUP($I63,Trabajadores!$C$3:$AT$1684,2,FALSE),0) -> 479 | AJ63: =IFERROR(VLOOKUP($I63,Trabajadores!$C$3:$AY$1270,21,FALSE),0) -> 50 | AK63: =IFERROR(VLOOKUP($I63,Trabajadores!$C$3:$AN$1684,38,FALSE),0) -> 9.45625 | AL63: =IFERROR(VLOOKUP($I63,Trabajadores!$C$3:$AN$1684,28,FALSE),0) -> 99100165012016 | AM63: =IFERROR(VLOOKUP($I63,Trabajadores!$C$3:$AN$1684,19,FALSE),0) -> ENCARGADA | AN63: =IFERROR(IF($J63="algadi",VLOOKUP($K63,Centros!$AB$2:$AD$142,2,FALSE),VLOOKUP($K63,Centros!$AB$143:$AD$282,2,FALSE)),0) -> 0 | AO63: =IFERROR(IF($J63="algadi",VLOOKUP($K63,Centros!$AB$2:$AD$142,3,FALSE),VLOOKUP($K63,Centros!$AB$143:$AD$222,3,FALSE)),0) -> 0 | AQ63: =IFERROR(VLOOKUP($AM63,Centros!$AR$2:$AS$405,2,FALSE),0) -> 1.7971719 | AR63: =IFERROR(VLOOKUP($AM63,Centros!$AZ$2:$BA$6,2,FALSE),0) -> 0 | AS63: =IFERROR(VLOOKUP($AM63,Centros!$BE$2:$BF$6,2,FALSE),0) -> 0 | BD63: =+X63 -> ALGADI | BE63: INCIDENCIA | BF63: =+E63 -> 9-SEPTIEMBRE | BG63: =+Y63 -> 110091 | BH63: =VLOOKUP(Y63,Hoja1!$A$2:$O$599,14,FALSE) -> 110091 | BI63: =VLOOKUP(BH63,Hoja1!$A$2:$O$599,2,FALSE) -> COLEGIO CLARET -MADRID | BJ63: =+I63 -> VILLALBA DIAZ, M VICTORIA | BK63: =VLOOKUP(BJ63,Trabajadores!$C$3:$AN$3285,14,FALSE) -> 300 | BL63: =VLOOKUP($BJ63,Trabajadores!$C$3:$AN$3285,19,FALSE) -> ENCARGADA | BM63: =VLOOKUP($BJ63,Trabajadores!$C$3:$AN$3285,16,FALSE) -> 100 | BN63: =IF($G63="010 Restauración",100%,0%) -> 1 | BO63: =IF($G63="020 Limpieza",100%,0%) -> 0 | BP63: =+BN63+BO63 -> 1 | BR63: =-W63 -> -11.8755 | BV63: =+J63 -> ALGADI | BW63: INCIDENCIA | BX63: =+E63 -> 9-SEPTIEMBRE | BY63: =+K63 -> 110091 | BZ63: =VLOOKUP(BY63,Hoja1!$A$2:$O$599,14,FALSE) -> 110091 | CA63: =VLOOKUP(BZ63,Hoja1!$A$2:$O$599,2,FALSE) -> COLEGIO CLARET -MADRID | CB63: =+H63 -> Eventos | CC63: 888 | CD63: =+BW63 -> INCIDENCIA | CJ63: =+W63 -> 11.8755
D64: 945 | E64: 9-SEPTIEMBRE | F64: NO | G64: 010 Restauración | H64: Refuerzo | I64: BAUTISTA DELGADO, ISABEL | J64: ALGADI | K64: 110216 | L64: =IF(W64>0,IF(OR(E64="",F64="",G64="",H64="",I64="",J64="",K64=""),"faltan datos","ok")," ") -> ok | M64: =IFERROR(VLOOKUP(K64,Centros!$E$2:$G$340,2,FALSE)," ") -> COL. MATER INMACULATA | N64: =IF(J64=" "," ",IF(J64=X64," ","Emp Orig/dest. Distinta")) | O64: =IFERROR(VLOOKUP($I64,Trabajadores!$C$3:$AF$1684,19,FALSE)," ") -> h R ASL | P64: 2 | Q64: 9 | R64: =+P64*Q64 -> 18 | T64: =IF(AL64="99100165012016",AQ64,IF(AL64="28009435011996",AR64,IF(AL64="99010825011997",AS64))) -> 1.7437656 | U64: =IF(T64="no corresponde",0,+S64*T64) -> 0 | W64: =+V64*AK64+((+R64+U64)*1.3195) -> 23.751 | X64: =IFERROR(VLOOKUP($I64,Trabajadores!$C$2:$AS$1684,42,FALSE)," ") -> ALGADI | Y64: =IFERROR(VLOOKUP($I64,Trabajadores!$C$2:$AS$1684,40,FALSE)," ") -> 110216 | Z64: =IFERROR(VLOOKUP(Y64,Centros!$X$2:$Y$228,2,FALSE)," ") -> COL. MATER INMACULATA | AA64: 45908 | AB64: Refuerzo limpieza inicio curso | AC64: =IFERROR(VLOOKUP(H64,Centros!$AI$2:$AN$10,6,FALSE),0) -> 72 | AD64: =IF(AC64=70,R64,0) -> 0 | AE64: =IF(AC64=72,R64,0) -> 18 | AF64: =IF(AC64=73,+R64,0) -> 0 | AG64: =+U64 -> 0 | AH64: =IFERROR(VLOOKUP($I64,Trabajadores!$C$3:$AT$1684,44,FALSE),0) -> 19228 | AI64: =IFERROR(VLOOKUP($I64,Trabajadores!$C$3:$AT$1684,2,FALSE),0) -> 1338 | AJ64: =IFERROR(VLOOKUP($I64,Trabajadores!$C$3:$AY$1270,21,FALSE),0) -> 107 | AK64: =IFERROR(VLOOKUP($I64,Trabajadores!$C$3:$AN$1684,38,FALSE),0) -> 9.988 | AL64: =IFERROR(VLOOKUP($I64,Trabajadores!$C$3:$AN$1684,28,FALSE),0) -> 99100165012016 | AM64: =IFERROR(VLOOKUP($I64,Trabajadores!$C$3:$AN$1684,19,FALSE),0) -> h R ASL | AN64: =IFERROR(IF($J64="algadi",VLOOKUP($K64,Centros!$AB$2:$AD$142,2,FALSE),VLOOKUP($K64,Centros!$AB$143:$AD$282,2,FALSE)),0) -> 0 | AO64: =IFERROR(IF($J64="algadi",VLOOKUP($K64,Centros!$AB$2:$AD$142,3,FALSE),VLOOKUP($K64,Centros!$AB$143:$AD$222,3,FALSE)),0) -> 0 | AQ64: =IFERROR(VLOOKUP($AM64,Centros!$AR$2:$AS$405,2,FALSE),0) -> 1.7437656 | AR64: =IFERROR(VLOOKUP($AM64,Centros!$AZ$2:$BA$6,2,FALSE),0) -> 0 | AS64: =IFERROR(VLOOKUP($AM64,Centros!$BE$2:$BF$6,2,FALSE),0) -> 0 | BD64: =+X64 -> ALGADI | BE64: INCIDENCIA | BF64: =+E64 -> 9-SEPTIEMBRE | BG64: =+Y64 -> 110216 | BH64: =VLOOKUP(Y64,Hoja1!$A$2:$O$599,14,FALSE) -> 110216 | BI64: =VLOOKUP(BH64,Hoja1!$A$2:$O$599,2,FALSE) -> COL. MATER INMACULATA | BJ64: =+I64 -> BAUTISTA DELGADO, ISABEL | BK64: =VLOOKUP(BJ64,Trabajadores!$C$3:$AN$3285,14,FALSE) -> 300 | BL64: =VLOOKUP($BJ64,Trabajadores!$C$3:$AN$3285,19,FALSE) -> h R ASL | BM64: =VLOOKUP($BJ64,Trabajadores!$C$3:$AN$3285,16,FALSE) -> 62.5 | BN64: =IF($G64="010 Restauración",100%,0%) -> 1 | BO64: =IF($G64="020 Limpieza",100%,0%) -> 0 | BP64: =+BN64+BO64 -> 1 | BR64: =-W64 -> -23.751 | BV64: =+J64 -> ALGADI | BW64: INCIDENCIA | BX64: =+E64 -> 9-SEPTIEMBRE | BY64: =+K64 -> 110216 | BZ64: =VLOOKUP(BY64,Hoja1!$A$2:$O$599,14,FALSE) -> 110216 | CA64: =VLOOKUP(BZ64,Hoja1!$A$2:$O$599,2,FALSE) -> COL. MATER INMACULATA | CB64: =+H64 -> Refuerzo | CC64: 888 | CD64: =+BW64 -> INCIDENCIA | CJ64: =+W64 -> 23.751
